Workbook
Name CONCEPTO: DETALLADO!$C$3:$C$61
Name CONCEPTOS: DETALLADO!$B$3:$B$61
Name PRO: PROVEEDORES!$B$2:$B$197
Name PROV: PROVEEDORES!#REF!
Name PROVEEDORES: PROVEEDORES!$B$2:$B$450
Name V.: DETALLADO!$C$3:$C$61

Sheet 1
A1: =1 -> 1 | B1: QUESO Y CAFÉ | D1: 46143 | G1: CUADRE DE CAJA MAÑANA | I1: CUADRE DE CAJA TARDE
A2: NIT | B2: PROVEEDOR | C2: CONCEPTO | D2: DESCRIPCIÓN | E2: VALOR | G2: PROP. TRANSF.: | H2: 0 | I2: PROP. TRANSF.: | J2: 0
A3: =IF(B3="","",VLOOKUP(B3,PROVEEDORES!$B:$C,2,FALSE)) | E3: 0 | G3: PROP. BANCO: | H3: 0 | I3: PROP. BANCO: | J3: 0
A4: =IF(B4="","",VLOOKUP(B4,PROVEEDORES!$B:$C,2,FALSE)) | E4: 0 | G4: PROP. EFECTIVO: | H4: 0 | I4: PROP. EFECTIVO: | J4: 0
A5: =IF(B5="","",VLOOKUP(B5,PROVEEDORES!$B:$C,2,FALSE)) | E5: 0 | G5: GASTO: | H5: 0 | I5: GASTO: | J5: 0
A6: =IF(B6="","",VLOOKUP(B6,PROVEEDORES!$B:$C,2,FALSE)) | E6: 0 | G6: TRANSFERENCIA: | H6: 0 | I6: TRANSFERENCIA: | J6: 0
A7: =IF(B7="","",VLOOKUP(B7,PROVEEDORES!$B:$C,2,FALSE)) | E7: 0 | G7: BANCO: | H7: 0 | I7: BANCO: | J7: 0
A8: =IF(B8="","",VLOOKUP(B8,PROVEEDORES!$B:$C,2,FALSE)) | E8: 0 | G8: EFECTIVO: | H8: 0 | I8: EFECTIVO: | J8: 0
A9: =IF(B9="","",VLOOKUP(B9,PROVEEDORES!$B:$C,2,FALSE)) | E9: 0 | G9: TOTAL: | H9: =SUM(H5:H8) -> 0 | I9: TOTAL: | J9: =SUM(J5:J8) -> 0
A10: =IF(B10="","",VLOOKUP(B10,PROVEEDORES!$B:$C,2,FALSE)) | E10: 0 | G10: DIFERENCIA: | H10: =+H11-H9 -> 0 | I10: DIFERENCIA: | J10: =+J11-J9 -> 0
A11: =IF(B11="","",VLOOKUP(B11,PROVEEDORES!$B:$C,2,FALSE)) | E11: 0 | G11: TOTAL VENTA: | H11: 0 | I11: TOTAL VENTA: | J11: 0
A12: =IF(B12="","",VLOOKUP(B12,PROVEEDORES!$B:$C,2,FALSE)) | E12: 0
A13: PROPINA TRANSFERENCIA: | C13: =SUM(H2,J2) -> 0 | D13: ACUM. PROPINA TRANFERENCIA: | E13: =SUM(C13,I37)-C57 -> 0 | G13: DIFERENCIA PLANILLA VS CUADRE DE CAJA | I13: =+C20-(SUM(H9,J9)) -> 0
A14: PROPINA POR BANCO: | C14: =SUM(H3,J3) -> 0 | D14: ACUM. PROPINA BANCO: | E14: =SUM(C14,I38)-C58 -> 0
A15: PROPINA EN EFECTIVO: | C15: =SUM(H4,J4) -> 0 | D15: ACUM. PROPINA EFECTIVO: | E15: =SUM(C15,I39)-C59 -> 0 | G15: FACTURAS EN EFECTIVO: | I15: 0
A16: TOTAL EGRESOS: | C16: =SUM(E3:E12) -> 0 | D16: ACUMULADO TRANSFERENCIA: | E16: =SUM(C17,I40) -> 0 | G16: EFECTIVO: | I16: 0
A17: TRANSFERENCIA: | C17: =SUM(H6,J6) -> 0 | D17: ACUMULADO BANCO: | E17: =SUM(C18,I41) -> 0 | G17: TOTAL EFECTIVO REAL ACTUAL: | I17: =SUM(I15,I16) -> 0
A18: BANCO: | C18: =SUM(H7,J7) -> 0 | D18: TOTAL BANCO: | E18: =SUM(C18,I42)-(SUM(E36:E55)) -> 0 | G18: DIFERENCIA: | I18: =+I19-I17 -> 0
A19: EFECTIVO: | C19: =SUM(H8,J8) -> 0 | D19: TOTAL EFECTIVO: | E19: =SUM(C19,E20,E57:E59)-(SUM(E23:E34)) -> 0 | G19: EFECTIVO ACTUAL PLANILLA: | I19: =E19 -> 0
A20: TOTAL VENTA: | C20: =SUM(C16:C19) -> 0 | D20: EFECTIVO ANTERIOR: | E20: =+I43 -> 0
A21: EGRESO DE CAJA MAYOR | G21: CONTEO DE EFECTIVO
A22: NIT | B22: PROVEEDOR | C22: CONCEPTO | D22: DESCRIPCIÓN | E22: EFECTIVO | G22: DENOMINACIÓN | H22: CANTIDAD | I22: EFECTIVO
A23: =IF(B23="","",VLOOKUP(B23,PROVEEDORES!$B:$C,2,FALSE)) | E23: 0 | G23: MONEDAS DE 100 | H23: 0 | I23: =100*H23 -> 0
A24: =IF(B24="","",VLOOKUP(B24,PROVEEDORES!$B:$C,2,FALSE)) | E24: 0 | G24: MONEDAS DE 200 | H24: 0 | I24: =200*H24 -> 0
A25: =IF(B25="","",VLOOKUP(B25,PROVEEDORES!$B:$C,2,FALSE)) | E25: 0 | G25: MONEDAS DE 500 | H25: 0 | I25: =500*H25 -> 0
A26: =IF(B26="","",VLOOKUP(B26,PROVEEDORES!$B:$C,2,FALSE)) | E26: 0 | G26: MONEDAS DE 1.000 | H26: 0 | I26: =1000*H26 -> 0
A27: =IF(B27="","",VLOOKUP(B27,PROVEEDORES!$B:$C,2,FALSE)) | E27: 0 | G27: BILLETES DE 2.000 | H27: 0 | I27: =2000*H27 -> 0
A28: =IF(B28="","",VLOOKUP(B28,PROVEEDORES!$B:$C,2,FALSE)) | E28: 0 | G28: BILLETES DE 5.000 | H28: 0 | I28: =5000*H28 -> 0
A29: =IF(B29="","",VLOOKUP(B29,PROVEEDORES!$B:$C,2,FALSE)) | E29: 0 | G29: BILLETES DE 10.000 | H29: 0 | I29: =10000*H29 -> 0
A30: =IF(B30="","",VLOOKUP(B30,PROVEEDORES!$B:$C,2,FALSE)) | E30: 0 | G30: BILLETES DE 20.000 | H30: 0 | I30: =20000*H30 -> 0
A31: =IF(B31="","",VLOOKUP(B31,PROVEEDORES!$B:$C,2,FALSE)) | E31: 0 | G31: BILLETES DE 50.000 | H31: 0 | I31: =50000*H31 -> 0
A32: =IF(B32="","",VLOOKUP(B32,PROVEEDORES!$B:$C,2,FALSE)) | E32: 0 | G32: BILLETES DE 100.000 | H32: 0 | I32: =100000*H32 -> 0
A33: =IF(B33="","",VLOOKUP(B33,PROVEEDORES!$B:$C,2,FALSE)) | E33: 0 | G33: TOTAL EFECTIVO: | I33: =SUM(I23:I32) -> 0
A34: =IF(B34="","",VLOOKUP(B34,PROVEEDORES!$B:$C,2,FALSE)) | E34: 0 | G34: BASE: | I34: 0
A35: NIT | B35: PROVEEDOR | C35: CONCEPTO | D35: DESCRIPCIÓN | E35: BANCO | G35: TOTAL EFECTIVO MENOS LA BASE: | I35: =I33-I34 -> 0
A36: =IF(B36="","",VLOOKUP(B36,PROVEEDORES!$B:$C,2,FALSE)) | E36: 0
A37: =IF(B37="","",VLOOKUP(B37,PROVEEDORES!$B:$C,2,FALSE)) | E37: 0 | G37: ACUM. DE PROPINA TRANSFERENCIA: | I37: 0
A38: =IF(B38="","",VLOOKUP(B38,PROVEEDORES!$B:$C,2,FALSE)) | E38: 0 | G38: ACUMULADO DE PROPINA EN BANCO: | I38: 0
A39: =IF(B39="","",VLOOKUP(B39,PROVEEDORES!$B:$C,2,FALSE)) | E39: 0 | G39: ACUMULADO DE PROPINA POR EFECTIVO: | I39: 0
A40: =IF(B40="","",VLOOKUP(B40,PROVEEDORES!$B:$C,2,FALSE)) | E40: 0 | G40: ACUMULADO DE TRANSFERENCIA: | I40: 0
A41: =IF(B41="","",VLOOKUP(B41,PROVEEDORES!$B:$C,2,FALSE)) | E41: 0 | G41: ACUMULADO DE BANCO: | I41: 0
A42: =IF(B42="","",VLOOKUP(B42,PROVEEDORES!$B:$C,2,FALSE)) | E42: 0 | G42: REAL DE BANCO: | I42: 0
A43: =IF(B43="","",VLOOKUP(B43,PROVEEDORES!$B:$C,2,FALSE)) | E43: 0 | G43: EFECTIVO ANTERIOR: | I43: 0
A44: =IF(B44="","",VLOOKUP(B44,PROVEEDORES!$B:$C,2,FALSE)) | E44: 0
A45: =IF(B45="","",VLOOKUP(B45,PROVEEDORES!$B:$C,2,FALSE)) | E45: 0
A46: =IF(B46="","",VLOOKUP(B46,PROVEEDORES!$B:$C,2,FALSE)) | E46: 0
A47: =IF(B47="","",VLOOKUP(B47,PROVEEDORES!$B:$C,2,FALSE)) | E47: 0
A48: =IF(B48="","",VLOOKUP(B48,PROVEEDORES!$B:$C,2,FALSE)) | E48: 0
A49: =IF(B49="","",VLOOKUP(B49,PROVEEDORES!$B:$C,2,FALSE)) | E49: 0
A50: =IF(B50="","",VLOOKUP(B50,PROVEEDORES!$B:$C,2,FALSE)) | E50: 0
A51: =IF(B51="","",VLOOKUP(B51,PROVEEDORES!$B:$C,2,FALSE)) | E51: 0
A52: =IF(B52="","",VLOOKUP(B52,PROVEEDORES!$B:$C,2,FALSE)) | E52: 0
A53: =IF(B53="","",VLOOKUP(B53,PROVEEDORES!$B:$C,2,FALSE)) | E53: 0
A54: =IF(B54="","",VLOOKUP(B54,PROVEEDORES!$B:$C,2,FALSE)) | E54: 0
A55: =IF(B55="","",VLOOKUP(B55,PROVEEDORES!$B:$C,2,FALSE)) | E55: 0
A56: EGRESO PROPINA | D56: INGRESO DE EFECTIVO
A57: PROPINA TRANSFERENCIA: | C57: 0 | E57: 0
A58: PROPINA BANCO: | C58: 0 | E58: 0
A59: PROPINA EFECTIVO: | C59: 0 | E59: 0

Sheet 2
A1: ='1'!A1+1 -> 2 | B1: =+'1'!B1 -> QUESO Y CAFÉ | D1: =+'1'!D1:E1+1 -> 46144 | G1: CUADRE DE CAJA MAÑANA | I1: CUADRE DE CAJA TARDE
A2: NIT | B2: PROVEEDOR | C2: CONCEPTO | D2: DESCRIPCIÓN | E2: VALOR | G2: PROP. TRANSF.: | H2: 0 | I2: PROP. TRANSF.: | J2: 0
A3: =IF(B3="","",VLOOKUP(B3,PROVEEDORES!$B:$C,2,FALSE)) | E3: 0 | G3: PROP. BANCO: | H3: 0 | I3: PROP. BANCO: | J3: 0
A4: =IF(B4="","",VLOOKUP(B4,PROVEEDORES!$B:$C,2,FALSE)) | E4: 0 | G4: PROP. EFECTIVO: | H4: 0 | I4: PROP. EFECTIVO: | J4: 0
A5: =IF(B5="","",VLOOKUP(B5,PROVEEDORES!$B:$C,2,FALSE)) | E5: 0 | G5: GASTO: | H5: 0 | I5: GASTO: | J5: 0
A6: =IF(B6="","",VLOOKUP(B6,PROVEEDORES!$B:$C,2,FALSE)) | E6: 0 | G6: TRANSFERENCIA: | H6: 0 | I6: TRANSFERENCIA: | J6: 0
A7: =IF(B7="","",VLOOKUP(B7,PROVEEDORES!$B:$C,2,FALSE)) | E7: 0 | G7: BANCO: | H7: 0 | I7: BANCO: | J7: 0
A8: =IF(B8="","",VLOOKUP(B8,PROVEEDORES!$B:$C,2,FALSE)) | E8: 0 | G8: EFECTIVO: | H8: 0 | I8: EFECTIVO: | J8: 0
A9: =IF(B9="","",VLOOKUP(B9,PROVEEDORES!$B:$C,2,FALSE)) | E9: 0 | G9: TOTAL: | H9: =SUM(H5:H8) -> 0 | I9: TOTAL: | J9: =SUM(J5:J8) -> 0
A10: =IF(B10="","",VLOOKUP(B10,PROVEEDORES!$B:$C,2,FALSE)) | E10: 0 | G10: DIFERENCIA: | H10: =+H11-H9 -> 0 | I10: DIFERENCIA: | J10: =+J11-J9 -> 0
A11: =IF(B11="","",VLOOKUP(B11,PROVEEDORES!$B:$C,2,FALSE)) | E11: 0 | G11: TOTAL VENTA: | H11: 0 | I11: TOTAL VENTA: | J11: 0
A12: =IF(B12="","",VLOOKUP(B12,PROVEEDORES!$B:$C,2,FALSE)) | E12: 0
A13: PROPINA TRANSFERENCIA: | C13: =SUM(H2,J2) -> 0 | D13: ACUM. PROPINA TRANFERENCIA: | E13: =SUM(C13,I37)-C57 -> 0 | G13: DIFERENCIA PLANILLA VS CUADRE DE CAJA | I13: =+C20-(SUM(H9,J9)) -> 0
A14: PROPINA POR BANCO: | C14: =SUM(H3,J3) -> 0 | D14: ACUM. PROPINA BANCO: | E14: =SUM(C14,I38)-C58 -> 0
A15: PROPINA EN EFECTIVO: | C15: =SUM(H4,J4) -> 0 | D15: ACUM. PROPINA EFECTIVO: | E15: =SUM(C15,I39)-C59 -> 0 | G15: FACTURAS EN EFECTIVO: | I15: 0
A16: TOTAL EGRESOS: | C16: =SUM(E3:E12) -> 0 | D16: ACUMULADO TRANSFERENCIA: | E16: =SUM(C17,I40) -> 0 | G16: EFECTIVO: | I16: 0
A17: TRANSFERENCIA: | C17: =SUM(H6,J6) -> 0 | D17: ACUMULADO BANCO: | E17: =SUM(C18,I41) -> 0 | G17: TOTAL EFECTIVO REAL ACTUAL: | I17: =SUM(I15,I16) -> 0
A18: BANCO: | C18: =SUM(H7,J7) -> 0 | D18: TOTAL BANCO: | E18: =SUM(C18,I42)-(SUM(E36:E55)) -> 0 | G18: DIFERENCIA: | I18: =+I19-I17 -> 0
A19: EFECTIVO: | C19: =SUM(H8,J8) -> 0 | D19: TOTAL EFECTIVO: | E19: =SUM(C19,E20,E57:E59)-(SUM(E23:E34)) -> 0 | G19: EFECTIVO ACTUAL PLANILLA: | I19: =E19 -> 0
A20: TOTAL VENTA: | C20: =SUM(C16:C19) -> 0 | D20: EFECTIVO ANTERIOR: | E20: =+I43 -> 0
A21: EGRESO DE CAJA MAYOR | G21: CONTEO DE EFECTIVO
A22: NIT | B22: PROVEEDOR | C22: CONCEPTO | D22: DESCRIPCIÓN | E22: EFECTIVO | G22: DENOMINACIÓN | H22: CANTIDAD | I22: EFECTIVO
A23: =IF(B23="","",VLOOKUP(B23,PROVEEDORES!$B:$C,2,FALSE)) | E23: 0 | G23: MONEDAS DE 100 | H23: 0 | I23: =100*H23 -> 0
A24: =IF(B24="","",VLOOKUP(B24,PROVEEDORES!$B:$C,2,FALSE)) | E24: 0 | G24: MONEDAS DE 200 | H24: 0 | I24: =200*H24 -> 0
A25: =IF(B25="","",VLOOKUP(B25,PROVEEDORES!$B:$C,2,FALSE)) | E25: 0 | G25: MONEDAS DE 500 | H25: 0 | I25: =500*H25 -> 0
A26: =IF(B26="","",VLOOKUP(B26,PROVEEDORES!$B:$C,2,FALSE)) | E26: 0 | G26: MONEDAS DE 1.000 | H26: 0 | I26: =1000*H26 -> 0
A27: =IF(B27="","",VLOOKUP(B27,PROVEEDORES!$B:$C,2,FALSE)) | E27: 0 | G27: BILLETES DE 2.000 | H27: 0 | I27: =2000*H27 -> 0
A28: =IF(B28="","",VLOOKUP(B28,PROVEEDORES!$B:$C,2,FALSE)) | E28: 0 | G28: BILLETES DE 5.000 | H28: 0 | I28: =5000*H28 -> 0
A29: =IF(B29="","",VLOOKUP(B29,PROVEEDORES!$B:$C,2,FALSE)) | E29: 0 | G29: BILLETES DE 10.000 | H29: 0 | I29: =10000*H29 -> 0
A30: =IF(B30="","",VLOOKUP(B30,PROVEEDORES!$B:$C,2,FALSE)) | E30: 0 | G30: BILLETES DE 20.000 | H30: 0 | I30: =20000*H30 -> 0
A31: =IF(B31="","",VLOOKUP(B31,PROVEEDORES!$B:$C,2,FALSE)) | E31: 0 | G31: BILLETES DE 50.000 | H31: 0 | I31: =50000*H31 -> 0
A32: =IF(B32="","",VLOOKUP(B32,PROVEEDORES!$B:$C,2,FALSE)) | E32: 0 | G32: BILLETES DE 100.000 | H32: 0 | I32: =100000*H32 -> 0
A33: =IF(B33="","",VLOOKUP(B33,PROVEEDORES!$B:$C,2,FALSE)) | E33: 0 | G33: TOTAL EFECTIVO: | I33: =SUM(I23:I32) -> 0
A34: =IF(B34="","",VLOOKUP(B34,PROVEEDORES!$B:$C,2,FALSE)) | E34: 0 | G34: BASE: | I34: 0
A35: NIT | B35: PROVEEDOR | C35: CONCEPTO | D35: DESCRIPCIÓN | E35: BANCO | G35: TOTAL EFECTIVO MENOS LA BASE: | I35: =I33-I34 -> 0
A36: =IF(B36="","",VLOOKUP(B36,PROVEEDORES!$B:$C,2,FALSE)) | E36: 0
A37: =IF(B37="","",VLOOKUP(B37,PROVEEDORES!$B:$C,2,FALSE)) | E37: 0 | G37: ACUM. DE PROPINA TRANSFERENCIA: | I37: =+'1'!E13 -> 0
A38: =IF(B38="","",VLOOKUP(B38,PROVEEDORES!$B:$C,2,FALSE)) | E38: 0 | G38: ACUMULADO DE PROPINA EN BANCO: | I38: =+'1'!E14 -> 0
A39: =IF(B39="","",VLOOKUP(B39,PROVEEDORES!$B:$C,2,FALSE)) | E39: 0 | G39: ACUMULADO DE PROPINA POR EFECTIVO: | I39: =+'1'!E15 -> 0
A40: =IF(B40="","",VLOOKUP(B40,PROVEEDORES!$B:$C,2,FALSE)) | E40: 0 | G40: ACUMULADO DE TRANSFERENCIA: | I40: =+'1'!E16 -> 0
A41: =IF(B41="","",VLOOKUP(B41,PROVEEDORES!$B:$C,2,FALSE)) | E41: 0 | G41: ACUMULADO DE BANCO: | I41: =+'1'!E17 -> 0
A42: =IF(B42="","",VLOOKUP(B42,PROVEEDORES!$B:$C,2,FALSE)) | E42: 0 | G42: REAL DE BANCO: | I42: =+'1'!E18 -> 0
A43: =IF(B43="","",VLOOKUP(B43,PROVEEDORES!$B:$C,2,FALSE)) | E43: 0 | G43: EFECTIVO ANTERIOR: | I43: =+'1'!E19 -> 0
A44: =IF(B44="","",VLOOKUP(B44,PROVEEDORES!$B:$C,2,FALSE)) | E44: 0
A45: =IF(B45="","",VLOOKUP(B45,PROVEEDORES!$B:$C,2,FALSE)) | E45: 0
A46: =IF(B46="","",VLOOKUP(B46,PROVEEDORES!$B:$C,2,FALSE)) | E46: 0
A47: =IF(B47="","",VLOOKUP(B47,PROVEEDORES!$B:$C,2,FALSE)) | E47: 0
A48: =IF(B48="","",VLOOKUP(B48,PROVEEDORES!$B:$C,2,FALSE)) | E48: 0
A49: =IF(B49="","",VLOOKUP(B49,PROVEEDORES!$B:$C,2,FALSE)) | E49: 0
A50: =IF(B50="","",VLOOKUP(B50,PROVEEDORES!$B:$C,2,FALSE)) | E50: 0
A51: =IF(B51="","",VLOOKUP(B51,PROVEEDORES!$B:$C,2,FALSE)) | E51: 0
A52: =IF(B52="","",VLOOKUP(B52,PROVEEDORES!$B:$C,2,FALSE)) | E52: 0
A53: =IF(B53="","",VLOOKUP(B53,PROVEEDORES!$B:$C,2,FALSE)) | E53: 0
A54: =IF(B54="","",VLOOKUP(B54,PROVEEDORES!$B:$C,2,FALSE)) | E54: 0
A55: =IF(B55="","",VLOOKUP(B55,PROVEEDORES!$B:$C,2,FALSE)) | E55: 0
A56: EGRESO PROPINA | D56: INGRESO DE EFECTIVO
A57: PROPINA TRANSFERENCIA: | C57: 0 | E57: 0
A58: PROPINA BANCO: | C58: 0 | E58: 0
A59: PROPINA EFECTIVO: | C59: 0 | E59: 0

Sheet 3
A1: ='2'!A1+1 -> 3 | B1: =+'1'!B1 -> QUESO Y CAFÉ | D1: =+'2'!D1:E1+1 -> 46145 | G1: CUADRE DE CAJA MAÑANA | I1: CUADRE DE CAJA TARDE
A2: NIT | B2: PROVEEDOR | C2: CONCEPTO | D2: DESCRIPCIÓN | E2: VALOR | G2: PROP. TRANSF.: | H2: 0 | I2: PROP. TRANSF.: | J2: 0
A3: =IF(B3="","",VLOOKUP(B3,PROVEEDORES!$B:$C,2,FALSE)) | E3: 0 | G3: PROP. BANCO: | H3: 0 | I3: PROP. BANCO: | J3: 0
A4: =IF(B4="","",VLOOKUP(B4,PROVEEDORES!$B:$C,2,FALSE)) | E4: 0 | G4: PROP. EFECTIVO: | H4: 0 | I4: PROP. EFECTIVO: | J4: 0
A5: =IF(B5="","",VLOOKUP(B5,PROVEEDORES!$B:$C,2,FALSE)) | E5: 0 | G5: GASTO: | H5: 0 | I5: GASTO: | J5: 0
A6: =IF(B6="","",VLOOKUP(B6,PROVEEDORES!$B:$C,2,FALSE)) | E6: 0 | G6: TRANSFERENCIA: | H6: 0 | I6: TRANSFERENCIA: | J6: 0
A7: =IF(B7="","",VLOOKUP(B7,PROVEEDORES!$B:$C,2,FALSE)) | E7: 0 | G7: BANCO: | H7: 0 | I7: BANCO: | J7: 0
A8: =IF(B8="","",VLOOKUP(B8,PROVEEDORES!$B:$C,2,FALSE)) | E8: 0 | G8: EFECTIVO: | H8: 0 | I8: EFECTIVO: | J8: 0
A9: =IF(B9="","",VLOOKUP(B9,PROVEEDORES!$B:$C,2,FALSE)) | E9: 0 | G9: TOTAL: | H9: =SUM(H5:H8) -> 0 | I9: TOTAL: | J9: =SUM(J5:J8) -> 0
A10: =IF(B10="","",VLOOKUP(B10,PROVEEDORES!$B:$C,2,FALSE)) | E10: 0 | G10: DIFERENCIA: | H10: =+H11-H9 -> 0 | I10: DIFERENCIA: | J10: =+J11-J9 -> 0
A11: =IF(B11="","",VLOOKUP(B11,PROVEEDORES!$B:$C,2,FALSE)) | E11: 0 | G11: TOTAL VENTA: | H11: 0 | I11: TOTAL VENTA: | J11: 0
A12: =IF(B12="","",VLOOKUP(B12,PROVEEDORES!$B:$C,2,FALSE)) | E12: 0
A13: PROPINA TRANSFERENCIA: | C13: =SUM(H2,J2) -> 0 | D13: ACUM. PROPINA TRANFERENCIA: | E13: =SUM(C13,I37)-C57 -> 0 | G13: DIFERENCIA PLANILLA VS CUADRE DE CAJA | I13: =+C20-(SUM(H9,J9)) -> 0
A14: PROPINA POR BANCO: | C14: =SUM(H3,J3) -> 0 | D14: ACUM. PROPINA BANCO: | E14: =SUM(C14,I38)-C58 -> 0
A15: PROPINA EN EFECTIVO: | C15: =SUM(H4,J4) -> 0 | D15: ACUM. PROPINA EFECTIVO: | E15: =SUM(C15,I39)-C59 -> 0 | G15: FACTURAS EN EFECTIVO: | I15: 0
A16: TOTAL EGRESOS: | C16: =SUM(E3:E12) -> 0 | D16: ACUMULADO TRANSFERENCIA: | E16: =SUM(C17,I40) -> 0 | G16: EFECTIVO: | I16: 0
A17: TRANSFERENCIA: | C17: =SUM(H6,J6) -> 0 | D17: ACUMULADO BANCO: | E17: =SUM(C18,I41) -> 0 | G17: TOTAL EFECTIVO REAL ACTUAL: | I17: =SUM(I15,I16) -> 0
A18: BANCO: | C18: =SUM(H7,J7) -> 0 | D18: TOTAL BANCO: | E18: =SUM(C18,I42)-(SUM(E36:E55)) -> 0 | G18: DIFERENCIA: | I18: =+I19-I17 -> 0
A19: EFECTIVO: | C19: =SUM(H8,J8) -> 0 | D19: TOTAL EFECTIVO: | E19: =SUM(C19,E20,E57:E59)-(SUM(E23:E34)) -> 0 | G19: EFECTIVO ACTUAL PLANILLA: | I19: =E19 -> 0
A20: TOTAL VENTA: | C20: =SUM(C16:C19) -> 0 | D20: EFECTIVO ANTERIOR: | E20: =+I43 -> 0
A21: EGRESO DE CAJA MAYOR | G21: CONTEO DE EFECTIVO
A22: NIT | B22: PROVEEDOR | C22: CONCEPTO | D22: DESCRIPCIÓN | E22: EFECTIVO | G22: DENOMINACIÓN | H22: CANTIDAD | I22: EFECTIVO
A23: =IF(B23="","",VLOOKUP(B23,PROVEEDORES!$B:$C,2,FALSE)) | E23: 0 | G23: MONEDAS DE 100 | H23: 0 | I23: =100*H23 -> 0
A24: =IF(B24="","",VLOOKUP(B24,PROVEEDORES!$B:$C,2,FALSE)) | E24: 0 | G24: MONEDAS DE 200 | H24: 0 | I24: =200*H24 -> 0
A25: =IF(B25="","",VLOOKUP(B25,PROVEEDORES!$B:$C,2,FALSE)) | E25: 0 | G25: MONEDAS DE 500 | H25: 0 | I25: =500*H25 -> 0
A26: =IF(B26="","",VLOOKUP(B26,PROVEEDORES!$B:$C,2,FALSE)) | E26: 0 | G26: MONEDAS DE 1.000 | H26: 0 | I26: =1000*H26 -> 0
A27: =IF(B27="","",VLOOKUP(B27,PROVEEDORES!$B:$C,2,FALSE)) | E27: 0 | G27: BILLETES DE 2.000 | H27: 0 | I27: =2000*H27 -> 0
A28: =IF(B28="","",VLOOKUP(B28,PROVEEDORES!$B:$C,2,FALSE)) | E28: 0 | G28: BILLETES DE 5.000 | H28: 0 | I28: =5000*H28 -> 0
A29: =IF(B29="","",VLOOKUP(B29,PROVEEDORES!$B:$C,2,FALSE)) | E29: 0 | G29: BILLETES DE 10.000 | H29: 0 | I29: =10000*H29 -> 0
A30: =IF(B30="","",VLOOKUP(B30,PROVEEDORES!$B:$C,2,FALSE)) | E30: 0 | G30: BILLETES DE 20.000 | H30: 0 | I30: =20000*H30 -> 0
A31: =IF(B31="","",VLOOKUP(B31,PROVEEDORES!$B:$C,2,FALSE)) | E31: 0 | G31: BILLETES DE 50.000 | H31: 0 | I31: =50000*H31 -> 0
A32: =IF(B32="","",VLOOKUP(B32,PROVEEDORES!$B:$C,2,FALSE)) | E32: 0 | G32: BILLETES DE 100.000 | H32: 0 | I32: =100000*H32 -> 0
A33: =IF(B33="","",VLOOKUP(B33,PROVEEDORES!$B:$C,2,FALSE)) | E33: 0 | G33: TOTAL EFECTIVO: | I33: =SUM(I23:I32) -> 0
A34: =IF(B34="","",VLOOKUP(B34,PROVEEDORES!$B:$C,2,FALSE)) | E34: 0 | G34: BASE: | I34: 0
A35: NIT | B35: PROVEEDOR | C35: CONCEPTO | D35: DESCRIPCIÓN | E35: BANCO | G35: TOTAL EFECTIVO MENOS LA BASE: | I35: =I33-I34 -> 0
A36: =IF(B36="","",VLOOKUP(B36,PROVEEDORES!$B:$C,2,FALSE)) | E36: 0
A37: =IF(B37="","",VLOOKUP(B37,PROVEEDORES!$B:$C,2,FALSE)) | E37: 0 | G37: ACUM. DE PROPINA TRANSFERENCIA: | I37: =+'2'!E13 -> 0
A38: =IF(B38="","",VLOOKUP(B38,PROVEEDORES!$B:$C,2,FALSE)) | E38: 0 | G38: ACUMULADO DE PROPINA EN BANCO: | I38: =+'2'!E14 -> 0
A39: =IF(B39="","",VLOOKUP(B39,PROVEEDORES!$B:$C,2,FALSE)) | E39: 0 | G39: ACUMULADO DE PROPINA POR EFECTIVO: | I39: =+'2'!E15 -> 0
A40: =IF(B40="","",VLOOKUP(B40,PROVEEDORES!$B:$C,2,FALSE)) | E40: 0 | G40: ACUMULADO DE TRANSFERENCIA: | I40: =+'2'!E16 -> 0
A41: =IF(B41="","",VLOOKUP(B41,PROVEEDORES!$B:$C,2,FALSE)) | E41: 0 | G41: ACUMULADO DE BANCO: | I41: =+'2'!E17 -> 0
A42: =IF(B42="","",VLOOKUP(B42,PROVEEDORES!$B:$C,2,FALSE)) | E42: 0 | G42: REAL DE BANCO: | I42: =+'2'!E18 -> 0
A43: =IF(B43="","",VLOOKUP(B43,PROVEEDORES!$B:$C,2,FALSE)) | E43: 0 | G43: EFECTIVO ANTERIOR: | I43: =+'2'!E19 -> 0
A44: =IF(B44="","",VLOOKUP(B44,PROVEEDORES!$B:$C,2,FALSE)) | E44: 0
A45: =IF(B45="","",VLOOKUP(B45,PROVEEDORES!$B:$C,2,FALSE)) | E45: 0
A46: =IF(B46="","",VLOOKUP(B46,PROVEEDORES!$B:$C,2,FALSE)) | E46: 0
A47: =IF(B47="","",VLOOKUP(B47,PROVEEDORES!$B:$C,2,FALSE)) | E47: 0
A48: =IF(B48="","",VLOOKUP(B48,PROVEEDORES!$B:$C,2,FALSE)) | E48: 0
A49: =IF(B49="","",VLOOKUP(B49,PROVEEDORES!$B:$C,2,FALSE)) | E49: 0
A50: =IF(B50="","",VLOOKUP(B50,PROVEEDORES!$B:$C,2,FALSE)) | E50: 0
A51: =IF(B51="","",VLOOKUP(B51,PROVEEDORES!$B:$C,2,FALSE)) | E51: 0
A52: =IF(B52="","",VLOOKUP(B52,PROVEEDORES!$B:$C,2,FALSE)) | E52: 0
A53: =IF(B53="","",VLOOKUP(B53,PROVEEDORES!$B:$C,2,FALSE)) | E53: 0
A54: =IF(B54="","",VLOOKUP(B54,PROVEEDORES!$B:$C,2,FALSE)) | E54: 0
A55: =IF(B55="","",VLOOKUP(B55,PROVEEDORES!$B:$C,2,FALSE)) | E55: 0
A56: EGRESO PROPINA | D56: INGRESO DE EFECTIVO
A57: PROPINA TRANSFERENCIA: | C57: 0 | E57: 0
A58: PROPINA BANCO: | C58: 0 | E58: 0
A59: PROPINA EFECTIVO: | C59: 0 | E59: 0

Sheet 4
A1: ='3'!A1+1 -> 4 | B1: =+'1'!B1 -> QUESO Y CAFÉ | D1: =+'3'!D1:E1+1 -> 46146 | G1: CUADRE DE CAJA MAÑANA | I1: CUADRE DE CAJA TARDE
A2: NIT | B2: PROVEEDOR | C2: CONCEPTO | D2: DESCRIPCIÓN | E2: VALOR | G2: PROP. TRANSF.: | H2: 0 | I2: PROP. TRANSF.: | J2: 0
A3: =IF(B3="","",VLOOKUP(B3,PROVEEDORES!$B:$C,2,FALSE)) | E3: 0 | G3: PROP. BANCO: | H3: 0 | I3: PROP. BANCO: | J3: 0
A4: =IF(B4="","",VLOOKUP(B4,PROVEEDORES!$B:$C,2,FALSE)) | E4: 0 | G4: PROP. EFECTIVO: | H4: 0 | I4: PROP. EFECTIVO: | J4: 0
A5: =IF(B5="","",VLOOKUP(B5,PROVEEDORES!$B:$C,2,FALSE)) | E5: 0 | G5: GASTO: | H5: 0 | I5: GASTO: | J5: 0
A6: =IF(B6="","",VLOOKUP(B6,PROVEEDORES!$B:$C,2,FALSE)) | E6: 0 | G6: TRANSFERENCIA: | H6: 0 | I6: TRANSFERENCIA: | J6: 0
A7: =IF(B7="","",VLOOKUP(B7,PROVEEDORES!$B:$C,2,FALSE)) | E7: 0 | G7: BANCO: | H7: 0 | I7: BANCO: | J7: 0
A8: =IF(B8="","",VLOOKUP(B8,PROVEEDORES!$B:$C,2,FALSE)) | E8: 0 | G8: EFECTIVO: | H8: 0 | I8: EFECTIVO: | J8: 0
A9: =IF(B9="","",VLOOKUP(B9,PROVEEDORES!$B:$C,2,FALSE)) | E9: 0 | G9: TOTAL: | H9: =SUM(H5:H8) -> 0 | I9: TOTAL: | J9: =SUM(J5:J8) -> 0
A10: =IF(B10="","",VLOOKUP(B10,PROVEEDORES!$B:$C,2,FALSE)) | E10: 0 | G10: DIFERENCIA: | H10: =+H11-H9 -> 0 | I10: DIFERENCIA: | J10: =+J11-J9 -> 0
A11: =IF(B11="","",VLOOKUP(B11,PROVEEDORES!$B:$C,2,FALSE)) | E11: 0 | G11: TOTAL VENTA: | H11: 0 | I11: TOTAL VENTA: | J11: 0
A12: =IF(B12="","",VLOOKUP(B12,PROVEEDORES!$B:$C,2,FALSE)) | E12: 0
A13: PROPINA TRANSFERENCIA: | C13: =SUM(H2,J2) -> 0 | D13: ACUM. PROPINA TRANFERENCIA: | E13: =SUM(C13,I37)-C57 -> 0 | G13: DIFERENCIA PLANILLA VS CUADRE DE CAJA | I13: =+C20-(SUM(H9,J9)) -> 0
A14: PROPINA POR BANCO: | C14: =SUM(H3,J3) -> 0 | D14: ACUM. PROPINA BANCO: | E14: =SUM(C14,I38)-C58 -> 0
A15: PROPINA EN EFECTIVO: | C15: =SUM(H4,J4) -> 0 | D15: ACUM. PROPINA EFECTIVO: | E15: =SUM(C15,I39)-C59 -> 0 | G15: FACTURAS EN EFECTIVO: | I15: 0
A16: TOTAL EGRESOS: | C16: =SUM(E3:E12) -> 0 | D16: ACUMULADO TRANSFERENCIA: | E16: =SUM(C17,I40) -> 0 | G16: EFECTIVO: | I16: 0
A17: TRANSFERENCIA: | C17: =SUM(H6,J6) -> 0 | D17: ACUMULADO BANCO: | E17: =SUM(C18,I41) -> 0 | G17: TOTAL EFECTIVO REAL ACTUAL: | I17: =SUM(I15,I16) -> 0
A18: BANCO: | C18: =SUM(H7,J7) -> 0 | D18: TOTAL BANCO: | E18: =SUM(C18,I42)-(SUM(E36:E55)) -> 0 | G18: DIFERENCIA: | I18: =+I19-I17 -> 0
A19: EFECTIVO: | C19: =SUM(H8,J8) -> 0 | D19: TOTAL EFECTIVO: | E19: =SUM(C19,E20,E57:E59)-(SUM(E23:E34)) -> 0 | G19: EFECTIVO ACTUAL PLANILLA: | I19: =E19 -> 0
A20: TOTAL VENTA: | C20: =SUM(C16:C19) -> 0 | D20: EFECTIVO ANTERIOR: | E20: =+I43 -> 0
A21: EGRESO DE CAJA MAYOR | G21: CONTEO DE EFECTIVO
A22: NIT | B22: PROVEEDOR | C22: CONCEPTO | D22: DESCRIPCIÓN | E22: EFECTIVO | G22: DENOMINACIÓN | H22: CANTIDAD | I22: EFECTIVO
A23: =IF(B23="","",VLOOKUP(B23,PROVEEDORES!$B:$C,2,FALSE)) | E23: 0 | G23: MONEDAS DE 100 | H23: 0 | I23: =100*H23 -> 0
A24: =IF(B24="","",VLOOKUP(B24,PROVEEDORES!$B:$C,2,FALSE)) | E24: 0 | G24: MONEDAS DE 200 | H24: 0 | I24: =200*H24 -> 0
A25: =IF(B25="","",VLOOKUP(B25,PROVEEDORES!$B:$C,2,FALSE)) | E25: 0 | G25: MONEDAS DE 500 | H25: 0 | I25: =500*H25 -> 0
A26: =IF(B26="","",VLOOKUP(B26,PROVEEDORES!$B:$C,2,FALSE)) | E26: 0 | G26: MONEDAS DE 1.000 | H26: 0 | I26: =1000*H26 -> 0
A27: =IF(B27="","",VLOOKUP(B27,PROVEEDORES!$B:$C,2,FALSE)) | E27: 0 | G27: BILLETES DE 2.000 | H27: 0 | I27: =2000*H27 -> 0
A28: =IF(B28="","",VLOOKUP(B28,PROVEEDORES!$B:$C,2,FALSE)) | E28: 0 | G28: BILLETES DE 5.000 | H28: 0 | I28: =5000*H28 -> 0
A29: =IF(B29="","",VLOOKUP(B29,PROVEEDORES!$B:$C,2,FALSE)) | E29: 0 | G29: BILLETES DE 10.000 | H29: 0 | I29: =10000*H29 -> 0
A30: =IF(B30="","",VLOOKUP(B30,PROVEEDORES!$B:$C,2,FALSE)) | E30: 0 | G30: BILLETES DE 20.000 | H30: 0 | I30: =20000*H30 -> 0
A31: =IF(B31="","",VLOOKUP(B31,PROVEEDORES!$B:$C,2,FALSE)) | E31: 0 | G31: BILLETES DE 50.000 | H31: 0 | I31: =50000*H31 -> 0
A32: =IF(B32="","",VLOOKUP(B32,PROVEEDORES!$B:$C,2,FALSE)) | E32: 0 | G32: BILLETES DE 100.000 | H32: 0 | I32: =100000*H32 -> 0
A33: =IF(B33="","",VLOOKUP(B33,PROVEEDORES!$B:$C,2,FALSE)) | E33: 0 | G33: TOTAL EFECTIVO: | I33: =SUM(I23:I32) -> 0
A34: =IF(B34="","",VLOOKUP(B34,PROVEEDORES!$B:$C,2,FALSE)) | E34: 0 | G34: BASE: | I34: 0
A35: NIT | B35: PROVEEDOR | C35: CONCEPTO | D35: DESCRIPCIÓN | E35: BANCO | G35: TOTAL EFECTIVO MENOS LA BASE: | I35: =I33-I34 -> 0
A36: =IF(B36="","",VLOOKUP(B36,PROVEEDORES!$B:$C,2,FALSE)) | E36: 0
A37: =IF(B37="","",VLOOKUP(B37,PROVEEDORES!$B:$C,2,FALSE)) | E37: 0 | G37: ACUM. DE PROPINA TRANSFERENCIA: | I37: =+'3'!E13 -> 0
A38: =IF(B38="","",VLOOKUP(B38,PROVEEDORES!$B:$C,2,FALSE)) | E38: 0 | G38: ACUMULADO DE PROPINA EN BANCO: | I38: =+'3'!E14 -> 0
A39: =IF(B39="","",VLOOKUP(B39,PROVEEDORES!$B:$C,2,FALSE)) | E39: 0 | G39: ACUMULADO DE PROPINA POR EFECTIVO: | I39: =+'3'!E15 -> 0
A40: =IF(B40="","",VLOOKUP(B40,PROVEEDORES!$B:$C,2,FALSE)) | E40: 0 | G40: ACUMULADO DE TRANSFERENCIA: | I40: =+'3'!E16 -> 0
A41: =IF(B41="","",VLOOKUP(B41,PROVEEDORES!$B:$C,2,FALSE)) | E41: 0 | G41: ACUMULADO DE BANCO: | I41: =+'3'!E17 -> 0
A42: =IF(B42="","",VLOOKUP(B42,PROVEEDORES!$B:$C,2,FALSE)) | E42: 0 | G42: REAL DE BANCO: | I42: =+'3'!E18 -> 0
A43: =IF(B43="","",VLOOKUP(B43,PROVEEDORES!$B:$C,2,FALSE)) | E43: 0 | G43: EFECTIVO ANTERIOR: | I43: =+'3'!E19 -> 0
A44: =IF(B44="","",VLOOKUP(B44,PROVEEDORES!$B:$C,2,FALSE)) | E44: 0
A45: =IF(B45="","",VLOOKUP(B45,PROVEEDORES!$B:$C,2,FALSE)) | E45: 0
A46: =IF(B46="","",VLOOKUP(B46,PROVEEDORES!$B:$C,2,FALSE)) | E46: 0
A47: =IF(B47="","",VLOOKUP(B47,PROVEEDORES!$B:$C,2,FALSE)) | E47: 0
A48: =IF(B48="","",VLOOKUP(B48,PROVEEDORES!$B:$C,2,FALSE)) | E48: 0
A49: =IF(B49="","",VLOOKUP(B49,PROVEEDORES!$B:$C,2,FALSE)) | E49: 0
A50: =IF(B50="","",VLOOKUP(B50,PROVEEDORES!$B:$C,2,FALSE)) | E50: 0
A51: =IF(B51="","",VLOOKUP(B51,PROVEEDORES!$B:$C,2,FALSE)) | E51: 0
A52: =IF(B52="","",VLOOKUP(B52,PROVEEDORES!$B:$C,2,FALSE)) | E52: 0
A53: =IF(B53="","",VLOOKUP(B53,PROVEEDORES!$B:$C,2,FALSE)) | E53: 0
A54: =IF(B54="","",VLOOKUP(B54,PROVEEDORES!$B:$C,2,FALSE)) | E54: 0
A55: =IF(B55="","",VLOOKUP(B55,PROVEEDORES!$B:$C,2,FALSE)) | E55: 0
A56: EGRESO PROPINA | D56: INGRESO DE EFECTIVO
A57: PROPINA TRANSFERENCIA: | C57: 0 | E57: 0
A58: PROPINA BANCO: | C58: 0 | E58: 0
A59: PROPINA EFECTIVO: | C59: 0 | E59: 0

Sheet 5
A1: ='4'!A1+1 -> 5 | B1: =+'1'!B1 -> QUESO Y CAFÉ | D1: =+'4'!D1:E1+1 -> 46147 | G1: CUADRE DE CAJA MAÑANA | I1: CUADRE DE CAJA TARDE
A2: NIT | B2: PROVEEDOR | C2: CONCEPTO | D2: DESCRIPCIÓN | E2: VALOR | G2: PROP. TRANSF.: | H2: 0 | I2: PROP. TRANSF.: | J2: 0
A3: =IF(B3="","",VLOOKUP(B3,PROVEEDORES!$B:$C,2,FALSE)) | E3: 0 | G3: PROP. BANCO: | H3: 0 | I3: PROP. BANCO: | J3: 0
A4: =IF(B4="","",VLOOKUP(B4,PROVEEDORES!$B:$C,2,FALSE)) | E4: 0 | G4: PROP. EFECTIVO: | H4: 0 | I4: PROP. EFECTIVO: | J4: 0
A5: =IF(B5="","",VLOOKUP(B5,PROVEEDORES!$B:$C,2,FALSE)) | E5: 0 | G5: GASTO: | H5: 0 | I5: GASTO: | J5: 0
A6: =IF(B6="","",VLOOKUP(B6,PROVEEDORES!$B:$C,2,FALSE)) | E6: 0 | G6: TRANSFERENCIA: | H6: 0 | I6: TRANSFERENCIA: | J6: 0
A7: =IF(B7="","",VLOOKUP(B7,PROVEEDORES!$B:$C,2,FALSE)) | E7: 0 | G7: BANCO: | H7: 0 | I7: BANCO: | J7: 0
A8: =IF(B8="","",VLOOKUP(B8,PROVEEDORES!$B:$C,2,FALSE)) | E8: 0 | G8: EFECTIVO: | H8: 0 | I8: EFECTIVO: | J8: 0
A9: =IF(B9="","",VLOOKUP(B9,PROVEEDORES!$B:$C,2,FALSE)) | E9: 0 | G9: TOTAL: | H9: =SUM(H5:H8) -> 0 | I9: TOTAL: | J9: =SUM(J5:J8) -> 0
A10: =IF(B10="","",VLOOKUP(B10,PROVEEDORES!$B:$C,2,FALSE)) | E10: 0 | G10: DIFERENCIA: | H10: =+H11-H9 -> 0 | I10: DIFERENCIA: | J10: =+J11-J9 -> 0
A11: =IF(B11="","",VLOOKUP(B11,PROVEEDORES!$B:$C,2,FALSE)) | E11: 0 | G11: TOTAL VENTA: | H11: 0 | I11: TOTAL VENTA: | J11: 0
A12: =IF(B12="","",VLOOKUP(B12,PROVEEDORES!$B:$C,2,FALSE)) | E12: 0
A13: PROPINA TRANSFERENCIA: | C13: =SUM(H2,J2) -> 0 | D13: ACUM. PROPINA TRANFERENCIA: | E13: =SUM(C13,I37)-C57 -> 0 | G13: DIFERENCIA PLANILLA VS CUADRE DE CAJA | I13: =+C20-(SUM(H9,J9)) -> 0
A14: PROPINA POR BANCO: | C14: =SUM(H3,J3) -> 0 | D14: ACUM. PROPINA BANCO: | E14: =SUM(C14,I38)-C58 -> 0
A15: PROPINA EN EFECTIVO: | C15: =SUM(H4,J4) -> 0 | D15: ACUM. PROPINA EFECTIVO: | E15: =SUM(C15,I39)-C59 -> 0 | G15: FACTURAS EN EFECTIVO: | I15: 0
A16: TOTAL EGRESOS: | C16: =SUM(E3:E12) -> 0 | D16: ACUMULADO TRANSFERENCIA: | E16: =SUM(C17,I40) -> 0 | G16: EFECTIVO: | I16: 0
A17: TRANSFERENCIA: | C17: =SUM(H6,J6) -> 0 | D17: ACUMULADO BANCO: | E17: =SUM(C18,I41) -> 0 | G17: TOTAL EFECTIVO REAL ACTUAL: | I17: =SUM(I15,I16) -> 0
A18: BANCO: | C18: =SUM(H7,J7) -> 0 | D18: TOTAL BANCO: | E18: =SUM(C18,I42)-(SUM(E36:E55)) -> 0 | G18: DIFERENCIA: | I18: =+I19-I17 -> 0
A19: EFECTIVO: | C19: =SUM(H8,J8) -> 0 | D19: TOTAL EFECTIVO: | E19: =SUM(C19,E20,E57:E59)-(SUM(E23:E34)) -> 0 | G19: EFECTIVO ACTUAL PLANILLA: | I19: =E19 -> 0
A20: TOTAL VENTA: | C20: =SUM(C16:C19) -> 0 | D20: EFECTIVO ANTERIOR: | E20: =+I43 -> 0
A21: EGRESO DE CAJA MAYOR | G21: CONTEO DE EFECTIVO
A22: NIT | B22: PROVEEDOR | C22: CONCEPTO | D22: DESCRIPCIÓN | E22: EFECTIVO | G22: DENOMINACIÓN | H22: CANTIDAD | I22: EFECTIVO
A23: =IF(B23="","",VLOOKUP(B23,PROVEEDORES!$B:$C,2,FALSE)) | E23: 0 | G23: MONEDAS DE 100 | H23: 0 | I23: =100*H23 -> 0
A24: =IF(B24="","",VLOOKUP(B24,PROVEEDORES!$B:$C,2,FALSE)) | E24: 0 | G24: MONEDAS DE 200 | H24: 0 | I24: =200*H24 -> 0
A25: =IF(B25="","",VLOOKUP(B25,PROVEEDORES!$B:$C,2,FALSE)) | E25: 0 | G25: MONEDAS DE 500 | H25: 0 | I25: =500*H25 -> 0
A26: =IF(B26="","",VLOOKUP(B26,PROVEEDORES!$B:$C,2,FALSE)) | E26: 0 | G26: MONEDAS DE 1.000 | H26: 0 | I26: =1000*H26 -> 0
A27: =IF(B27="","",VLOOKUP(B27,PROVEEDORES!$B:$C,2,FALSE)) | E27: 0 | G27: BILLETES DE 2.000 | H27: 0 | I27: =2000*H27 -> 0
A28: =IF(B28="","",VLOOKUP(B28,PROVEEDORES!$B:$C,2,FALSE)) | E28: 0 | G28: BILLETES DE 5.000 | H28: 0 | I28: =5000*H28 -> 0
A29: =IF(B29="","",VLOOKUP(B29,PROVEEDORES!$B:$C,2,FALSE)) | E29: 0 | G29: BILLETES DE 10.000 | H29: 0 | I29: =10000*H29 -> 0
A30: =IF(B30="","",VLOOKUP(B30,PROVEEDORES!$B:$C,2,FALSE)) | E30: 0 | G30: BILLETES DE 20.000 | H30: 0 | I30: =20000*H30 -> 0
A31: =IF(B31="","",VLOOKUP(B31,PROVEEDORES!$B:$C,2,FALSE)) | E31: 0 | G31: BILLETES DE 50.000 | H31: 0 | I31: =50000*H31 -> 0
A32: =IF(B32="","",VLOOKUP(B32,PROVEEDORES!$B:$C,2,FALSE)) | E32: 0 | G32: BILLETES DE 100.000 | H32: 0 | I32: =100000*H32 -> 0
A33: =IF(B33="","",VLOOKUP(B33,PROVEEDORES!$B:$C,2,FALSE)) | E33: 0 | G33: TOTAL EFECTIVO: | I33: =SUM(I23:I32) -> 0
A34: =IF(B34="","",VLOOKUP(B34,PROVEEDORES!$B:$C,2,FALSE)) | E34: 0 | G34: BASE: | I34: 0
A35: NIT | B35: PROVEEDOR | C35: CONCEPTO | D35: DESCRIPCIÓN | E35: BANCO | G35: TOTAL EFECTIVO MENOS LA BASE: | I35: =I33-I34 -> 0
A36: =IF(B36="","",VLOOKUP(B36,PROVEEDORES!$B:$C,2,FALSE)) | E36: 0
A37: =IF(B37="","",VLOOKUP(B37,PROVEEDORES!$B:$C,2,FALSE)) | E37: 0 | G37: ACUM. DE PROPINA TRANSFERENCIA: | I37: =+'4'!E13 -> 0
A38: =IF(B38="","",VLOOKUP(B38,PROVEEDORES!$B:$C,2,FALSE)) | E38: 0 | G38: ACUMULADO DE PROPINA EN BANCO: | I38: =+'4'!E14 -> 0
A39: =IF(B39="","",VLOOKUP(B39,PROVEEDORES!$B:$C,2,FALSE)) | E39: 0 | G39: ACUMULADO DE PROPINA POR EFECTIVO: | I39: =+'4'!E15 -> 0
A40: =IF(B40="","",VLOOKUP(B40,PROVEEDORES!$B:$C,2,FALSE)) | E40: 0 | G40: ACUMULADO DE TRANSFERENCIA: | I40: =+'4'!E16 -> 0
A41: =IF(B41="","",VLOOKUP(B41,PROVEEDORES!$B:$C,2,FALSE)) | E41: 0 | G41: ACUMULADO DE BANCO: | I41: =+'4'!E17 -> 0
A42: =IF(B42="","",VLOOKUP(B42,PROVEEDORES!$B:$C,2,FALSE)) | E42: 0 | G42: REAL DE BANCO: | I42: =+'4'!E18 -> 0
A43: =IF(B43="","",VLOOKUP(B43,PROVEEDORES!$B:$C,2,FALSE)) | E43: 0 | G43: EFECTIVO ANTERIOR: | I43: =+'4'!E19 -> 0
A44: =IF(B44="","",VLOOKUP(B44,PROVEEDORES!$B:$C,2,FALSE)) | E44: 0
A45: =IF(B45="","",VLOOKUP(B45,PROVEEDORES!$B:$C,2,FALSE)) | E45: 0
A46: =IF(B46="","",VLOOKUP(B46,PROVEEDORES!$B:$C,2,FALSE)) | E46: 0
A47: =IF(B47="","",VLOOKUP(B47,PROVEEDORES!$B:$C,2,FALSE)) | E47: 0
A48: =IF(B48="","",VLOOKUP(B48,PROVEEDORES!$B:$C,2,FALSE)) | E48: 0
A49: =IF(B49="","",VLOOKUP(B49,PROVEEDORES!$B:$C,2,FALSE)) | E49: 0
A50: =IF(B50="","",VLOOKUP(B50,PROVEEDORES!$B:$C,2,FALSE)) | E50: 0
A51: =IF(B51="","",VLOOKUP(B51,PROVEEDORES!$B:$C,2,FALSE)) | E51: 0
A52: =IF(B52="","",VLOOKUP(B52,PROVEEDORES!$B:$C,2,FALSE)) | E52: 0
A53: =IF(B53="","",VLOOKUP(B53,PROVEEDORES!$B:$C,2,FALSE)) | E53: 0
A54: =IF(B54="","",VLOOKUP(B54,PROVEEDORES!$B:$C,2,FALSE)) | E54: 0
A55: =IF(B55="","",VLOOKUP(B55,PROVEEDORES!$B:$C,2,FALSE)) | E55: 0
A56: EGRESO PROPINA | D56: INGRESO DE EFECTIVO
A57: PROPINA TRANSFERENCIA: | C57: 0 | E57: 0
A58: PROPINA BANCO: | C58: 0 | E58: 0
A59: PROPINA EFECTIVO: | C59: 0 | E59: 0

Sheet 6
A1: ='5'!A1+1 -> 6 | B1: =+'1'!B1 -> QUESO Y CAFÉ | D1: =+'5'!D1:E1+1 -> 46148 | G1: CUADRE DE CAJA MAÑANA | I1: CUADRE DE CAJA TARDE
A2: NIT | B2: PROVEEDOR | C2: CONCEPTO | D2: DESCRIPCIÓN | E2: VALOR | G2: PROP. TRANSF.: | H2: 0 | I2: PROP. TRANSF.: | J2: 0
A3: =IF(B3="","",VLOOKUP(B3,PROVEEDORES!$B:$C,2,FALSE)) | E3: 0 | G3: PROP. BANCO: | H3: 0 | I3: PROP. BANCO: | J3: 0
A4: =IF(B4="","",VLOOKUP(B4,PROVEEDORES!$B:$C,2,FALSE)) | E4: 0 | G4: PROP. EFECTIVO: | H4: 0 | I4: PROP. EFECTIVO: | J4: 0
A5: =IF(B5="","",VLOOKUP(B5,PROVEEDORES!$B:$C,2,FALSE)) | E5: 0 | G5: GASTO: | H5: 0 | I5: GASTO: | J5: 0
A6: =IF(B6="","",VLOOKUP(B6,PROVEEDORES!$B:$C,2,FALSE)) | E6: 0 | G6: TRANSFERENCIA: | H6: 0 | I6: TRANSFERENCIA: | J6: 0
A7: =IF(B7="","",VLOOKUP(B7,PROVEEDORES!$B:$C,2,FALSE)) | E7: 0 | G7: BANCO: | H7: 0 | I7: BANCO: | J7: 0
A8: =IF(B8="","",VLOOKUP(B8,PROVEEDORES!$B:$C,2,FALSE)) | E8: 0 | G8: EFECTIVO: | H8: 0 | I8: EFECTIVO: | J8: 0
A9: =IF(B9="","",VLOOKUP(B9,PROVEEDORES!$B:$C,2,FALSE)) | E9: 0 | G9: TOTAL: | H9: =SUM(H5:H8) -> 0 | I9: TOTAL: | J9: =SUM(J5:J8) -> 0
A10: =IF(B10="","",VLOOKUP(B10,PROVEEDORES!$B:$C,2,FALSE)) | E10: 0 | G10: DIFERENCIA: | H10: =+H11-H9 -> 0 | I10: DIFERENCIA: | J10: =+J11-J9 -> 0
A11: =IF(B11="","",VLOOKUP(B11,PROVEEDORES!$B:$C,2,FALSE)) | E11: 0 | G11: TOTAL VENTA: | H11: 0 | I11: TOTAL VENTA: | J11: 0
A12: =IF(B12="","",VLOOKUP(B12,PROVEEDORES!$B:$C,2,FALSE)) | E12: 0
A13: PROPINA TRANSFERENCIA: | C13: =SUM(H2,J2) -> 0 | D13: ACUM. PROPINA TRANFERENCIA: | E13: =SUM(C13,I37)-C57 -> 0 | G13: DIFERENCIA PLANILLA VS CUADRE DE CAJA | I13: =+C20-(SUM(H9,J9)) -> 0
A14: PROPINA POR BANCO: | C14: =SUM(H3,J3) -> 0 | D14: ACUM. PROPINA BANCO: | E14: =SUM(C14,I38)-C58 -> 0
A15: PROPINA EN EFECTIVO: | C15: =SUM(H4,J4) -> 0 | D15: ACUM. PROPINA EFECTIVO: | E15: =SUM(C15,I39)-C59 -> 0 | G15: FACTURAS EN EFECTIVO: | I15: 0
A16: TOTAL EGRESOS: | C16: =SUM(E3:E12) -> 0 | D16: ACUMULADO TRANSFERENCIA: | E16: =SUM(C17,I40) -> 0 | G16: EFECTIVO: | I16: 0
A17: TRANSFERENCIA: | C17: =SUM(H6,J6) -> 0 | D17: ACUMULADO BANCO: | E17: =SUM(C18,I41) -> 0 | G17: TOTAL EFECTIVO REAL ACTUAL: | I17: =SUM(I15,I16) -> 0
A18: BANCO: | C18: =SUM(H7,J7) -> 0 | D18: TOTAL BANCO: | E18: =SUM(C18,I42)-(SUM(E36:E55)) -> 0 | G18: DIFERENCIA: | I18: =+I19-I17 -> 0
A19: EFECTIVO: | C19: =SUM(H8,J8) -> 0 | D19: TOTAL EFECTIVO: | E19: =SUM(C19,E20,E57:E59)-(SUM(E23:E34)) -> 0 | G19: EFECTIVO ACTUAL PLANILLA: | I19: =E19 -> 0
A20: TOTAL VENTA: | C20: =SUM(C16:C19) -> 0 | D20: EFECTIVO ANTERIOR: | E20: =+I43 -> 0
A21: EGRESO DE CAJA MAYOR | G21: CONTEO DE EFECTIVO
A22: NIT | B22: PROVEEDOR | C22: CONCEPTO | D22: DESCRIPCIÓN | E22: EFECTIVO | G22: DENOMINACIÓN | H22: CANTIDAD | I22: EFECTIVO
A23: =IF(B23="","",VLOOKUP(B23,PROVEEDORES!$B:$C,2,FALSE)) | E23: 0 | G23: MONEDAS DE 100 | H23: 0 | I23: =100*H23 -> 0
A24: =IF(B24="","",VLOOKUP(B24,PROVEEDORES!$B:$C,2,FALSE)) | E24: 0 | G24: MONEDAS DE 200 | H24: 0 | I24: =200*H24 -> 0
A25: =IF(B25="","",VLOOKUP(B25,PROVEEDORES!$B:$C,2,FALSE)) | E25: 0 | G25: MONEDAS DE 500 | H25: 0 | I25: =500*H25 -> 0
A26: =IF(B26="","",VLOOKUP(B26,PROVEEDORES!$B:$C,2,FALSE)) | E26: 0 | G26: MONEDAS DE 1.000 | H26: 0 | I26: =1000*H26 -> 0
A27: =IF(B27="","",VLOOKUP(B27,PROVEEDORES!$B:$C,2,FALSE)) | E27: 0 | G27: BILLETES DE 2.000 | H27: 0 | I27: =2000*H27 -> 0
A28: =IF(B28="","",VLOOKUP(B28,PROVEEDORES!$B:$C,2,FALSE)) | E28: 0 | G28: BILLETES DE 5.000 | H28: 0 | I28: =5000*H28 -> 0
A29: =IF(B29="","",VLOOKUP(B29,PROVEEDORES!$B:$C,2,FALSE)) | E29: 0 | G29: BILLETES DE 10.000 | H29: 0 | I29: =10000*H29 -> 0
A30: =IF(B30="","",VLOOKUP(B30,PROVEEDORES!$B:$C,2,FALSE)) | E30: 0 | G30: BILLETES DE 20.000 | H30: 0 | I30: =20000*H30 -> 0
A31: =IF(B31="","",VLOOKUP(B31,PROVEEDORES!$B:$C,2,FALSE)) | E31: 0 | G31: BILLETES DE 50.000 | H31: 0 | I31: =50000*H31 -> 0
A32: =IF(B32="","",VLOOKUP(B32,PROVEEDORES!$B:$C,2,FALSE)) | E32: 0 | G32: BILLETES DE 100.000 | H32: 0 | I32: =100000*H32 -> 0
A33: =IF(B33="","",VLOOKUP(B33,PROVEEDORES!$B:$C,2,FALSE)) | E33: 0 | G33: TOTAL EFECTIVO: | I33: =SUM(I23:I32) -> 0
A34: =IF(B34="","",VLOOKUP(B34,PROVEEDORES!$B:$C,2,FALSE)) | E34: 0 | G34: BASE: | I34: 0
A35: NIT | B35: PROVEEDOR | C35: CONCEPTO | D35: DESCRIPCIÓN | E35: BANCO | G35: TOTAL EFECTIVO MENOS LA BASE: | I35: =I33-I34 -> 0
A36: =IF(B36="","",VLOOKUP(B36,PROVEEDORES!$B:$C,2,FALSE)) | E36: 0
A37: =IF(B37="","",VLOOKUP(B37,PROVEEDORES!$B:$C,2,FALSE)) | E37: 0 | G37: ACUM. DE PROPINA TRANSFERENCIA: | I37: =+'5'!E13 -> 0
A38: =IF(B38="","",VLOOKUP(B38,PROVEEDORES!$B:$C,2,FALSE)) | E38: 0 | G38: ACUMULADO DE PROPINA EN BANCO: | I38: =+'5'!E14 -> 0
A39: =IF(B39="","",VLOOKUP(B39,PROVEEDORES!$B:$C,2,FALSE)) | E39: 0 | G39: ACUMULADO DE PROPINA POR EFECTIVO: | I39: =+'5'!E15 -> 0
A40: =IF(B40="","",VLOOKUP(B40,PROVEEDORES!$B:$C,2,FALSE)) | E40: 0 | G40: ACUMULADO DE TRANSFERENCIA: | I40: =+'5'!E16 -> 0
A41: =IF(B41="","",VLOOKUP(B41,PROVEEDORES!$B:$C,2,FALSE)) | E41: 0 | G41: ACUMULADO DE BANCO: | I41: =+'5'!E17 -> 0
A42: =IF(B42="","",VLOOKUP(B42,PROVEEDORES!$B:$C,2,FALSE)) | E42: 0 | G42: REAL DE BANCO: | I42: =+'5'!E18 -> 0
A43: =IF(B43="","",VLOOKUP(B43,PROVEEDORES!$B:$C,2,FALSE)) | E43: 0 | G43: EFECTIVO ANTERIOR: | I43: =+'5'!E19 -> 0
A44: =IF(B44="","",VLOOKUP(B44,PROVEEDORES!$B:$C,2,FALSE)) | E44: 0
A45: =IF(B45="","",VLOOKUP(B45,PROVEEDORES!$B:$C,2,FALSE)) | E45: 0
A46: =IF(B46="","",VLOOKUP(B46,PROVEEDORES!$B:$C,2,FALSE)) | E46: 0
A47: =IF(B47="","",VLOOKUP(B47,PROVEEDORES!$B:$C,2,FALSE)) | E47: 0
A48: =IF(B48="","",VLOOKUP(B48,PROVEEDORES!$B:$C,2,FALSE)) | E48: 0
A49: =IF(B49="","",VLOOKUP(B49,PROVEEDORES!$B:$C,2,FALSE)) | E49: 0
A50: =IF(B50="","",VLOOKUP(B50,PROVEEDORES!$B:$C,2,FALSE)) | E50: 0
A51: =IF(B51="","",VLOOKUP(B51,PROVEEDORES!$B:$C,2,FALSE)) | E51: 0
A52: =IF(B52="","",VLOOKUP(B52,PROVEEDORES!$B:$C,2,FALSE)) | E52: 0
A53: =IF(B53="","",VLOOKUP(B53,PROVEEDORES!$B:$C,2,FALSE)) | E53: 0
A54: =IF(B54="","",VLOOKUP(B54,PROVEEDORES!$B:$C,2,FALSE)) | E54: 0
A55: =IF(B55="","",VLOOKUP(B55,PROVEEDORES!$B:$C,2,FALSE)) | E55: 0
A56: EGRESO PROPINA | D56: INGRESO DE EFECTIVO
A57: PROPINA TRANSFERENCIA: | C57: 0 | E57: 0
A58: PROPINA BANCO: | C58: 0 | E58: 0
A59: PROPINA EFECTIVO: | C59: 0 | E59: 0

Sheet 7
A1: ='6'!A1+1 -> 7 | B1: =+'1'!B1 -> QUESO Y CAFÉ | D1: =+'6'!D1:E1+1 -> 46149 | G1: CUADRE DE CAJA MAÑANA | I1: CUADRE DE CAJA TARDE
A2: NIT | B2: PROVEEDOR | C2: CONCEPTO | D2: DESCRIPCIÓN | E2: VALOR | G2: PROP. TRANSF.: | H2: 0 | I2: PROP. TRANSF.: | J2: 0
A3: =IF(B3="","",VLOOKUP(B3,PROVEEDORES!$B:$C,2,FALSE)) | E3: 0 | G3: PROP. BANCO: | H3: 0 | I3: PROP. BANCO: | J3: 0
A4: =IF(B4="","",VLOOKUP(B4,PROVEEDORES!$B:$C,2,FALSE)) | E4: 0 | G4: PROP. EFECTIVO: | H4: 0 | I4: PROP. EFECTIVO: | J4: 0
A5: =IF(B5="","",VLOOKUP(B5,PROVEEDORES!$B:$C,2,FALSE)) | E5: 0 | G5: GASTO: | H5: 0 | I5: GASTO: | J5: 0
A6: =IF(B6="","",VLOOKUP(B6,PROVEEDORES!$B:$C,2,FALSE)) | E6: 0 | G6: TRANSFERENCIA: | H6: 0 | I6: TRANSFERENCIA: | J6: 0
A7: =IF(B7="","",VLOOKUP(B7,PROVEEDORES!$B:$C,2,FALSE)) | E7: 0 | G7: BANCO: | H7: 0 | I7: BANCO: | J7: 0
A8: =IF(B8="","",VLOOKUP(B8,PROVEEDORES!$B:$C,2,FALSE)) | E8: 0 | G8: EFECTIVO: | H8: 0 | I8: EFECTIVO: | J8: 0
A9: =IF(B9="","",VLOOKUP(B9,PROVEEDORES!$B:$C,2,FALSE)) | E9: 0 | G9: TOTAL: | H9: =SUM(H5:H8) -> 0 | I9: TOTAL: | J9: =SUM(J5:J8) -> 0
A10: =IF(B10="","",VLOOKUP(B10,PROVEEDORES!$B:$C,2,FALSE)) | E10: 0 | G10: DIFERENCIA: | H10: =+H11-H9 -> 0 | I10: DIFERENCIA: | J10: =+J11-J9 -> 0
A11: =IF(B11="","",VLOOKUP(B11,PROVEEDORES!$B:$C,2,FALSE)) | E11: 0 | G11: TOTAL VENTA: | H11: 0 | I11: TOTAL VENTA: | J11: 0
A12: =IF(B12="","",VLOOKUP(B12,PROVEEDORES!$B:$C,2,FALSE)) | E12: 0
A13: PROPINA TRANSFERENCIA: | C13: =SUM(H2,J2) -> 0 | D13: ACUM. PROPINA TRANFERENCIA: | E13: =SUM(C13,I37)-C57 -> 0 | G13: DIFERENCIA PLANILLA VS CUADRE DE CAJA | I13: =+C20-(SUM(H9,J9)) -> 0
A14: PROPINA POR BANCO: | C14: =SUM(H3,J3) -> 0 | D14: ACUM. PROPINA BANCO: | E14: =SUM(C14,I38)-C58 -> 0
A15: PROPINA EN EFECTIVO: | C15: =SUM(H4,J4) -> 0 | D15: ACUM. PROPINA EFECTIVO: | E15: =SUM(C15,I39)-C59 -> 0 | G15: FACTURAS EN EFECTIVO: | I15: 0
A16: TOTAL EGRESOS: | C16: =SUM(E3:E12) -> 0 | D16: ACUMULADO TRANSFERENCIA: | E16: =SUM(C17,I40) -> 0 | G16: EFECTIVO: | I16: 0
A17: TRANSFERENCIA: | C17: =SUM(H6,J6) -> 0 | D17: ACUMULADO BANCO: | E17: =SUM(C18,I41) -> 0 | G17: TOTAL EFECTIVO REAL ACTUAL: | I17: =SUM(I15,I16) -> 0
A18: BANCO: | C18: =SUM(H7,J7) -> 0 | D18: TOTAL BANCO: | E18: =SUM(C18,I42)-(SUM(E36:E55)) -> 0 | G18: DIFERENCIA: | I18: =+I19-I17 -> 0
A19: EFECTIVO: | C19: =SUM(H8,J8) -> 0 | D19: TOTAL EFECTIVO: | E19: =SUM(C19,E20,E57:E59)-(SUM(E23:E34)) -> 0 | G19: EFECTIVO ACTUAL PLANILLA: | I19: =E19 -> 0
A20: TOTAL VENTA: | C20: =SUM(C16:C19) -> 0 | D20: EFECTIVO ANTERIOR: | E20: =+I43 -> 0
A21: EGRESO DE CAJA MAYOR | G21: CONTEO DE EFECTIVO
A22: NIT | B22: PROVEEDOR | C22: CONCEPTO | D22: DESCRIPCIÓN | E22: EFECTIVO | G22: DENOMINACIÓN | H22: CANTIDAD | I22: EFECTIVO
A23: =IF(B23="","",VLOOKUP(B23,PROVEEDORES!$B:$C,2,FALSE)) | E23: 0 | G23: MONEDAS DE 100 | H23: 0 | I23: =100*H23 -> 0
A24: =IF(B24="","",VLOOKUP(B24,PROVEEDORES!$B:$C,2,FALSE)) | E24: 0 | G24: MONEDAS DE 200 | H24: 0 | I24: =200*H24 -> 0
A25: =IF(B25="","",VLOOKUP(B25,PROVEEDORES!$B:$C,2,FALSE)) | E25: 0 | G25: MONEDAS DE 500 | H25: 0 | I25: =500*H25 -> 0
A26: =IF(B26="","",VLOOKUP(B26,PROVEEDORES!$B:$C,2,FALSE)) | E26: 0 | G26: MONEDAS DE 1.000 | H26: 0 | I26: =1000*H26 -> 0
A27: =IF(B27="","",VLOOKUP(B27,PROVEEDORES!$B:$C,2,FALSE)) | E27: 0 | G27: BILLETES DE 2.000 | H27: 0 | I27: =2000*H27 -> 0
A28: =IF(B28="","",VLOOKUP(B28,PROVEEDORES!$B:$C,2,FALSE)) | E28: 0 | G28: BILLETES DE 5.000 | H28: 0 | I28: =5000*H28 -> 0
A29: =IF(B29="","",VLOOKUP(B29,PROVEEDORES!$B:$C,2,FALSE)) | E29: 0 | G29: BILLETES DE 10.000 | H29: 0 | I29: =10000*H29 -> 0
A30: =IF(B30="","",VLOOKUP(B30,PROVEEDORES!$B:$C,2,FALSE)) | E30: 0 | G30: BILLETES DE 20.000 | H30: 0 | I30: =20000*H30 -> 0
A31: =IF(B31="","",VLOOKUP(B31,PROVEEDORES!$B:$C,2,FALSE)) | E31: 0 | G31: BILLETES DE 50.000 | H31: 0 | I31: =50000*H31 -> 0
A32: =IF(B32="","",VLOOKUP(B32,PROVEEDORES!$B:$C,2,FALSE)) | E32: 0 | G32: BILLETES DE 100.000 | H32: 0 | I32: =100000*H32 -> 0
A33: =IF(B33="","",VLOOKUP(B33,PROVEEDORES!$B:$C,2,FALSE)) | E33: 0 | G33: TOTAL EFECTIVO: | I33: =SUM(I23:I32) -> 0
A34: =IF(B34="","",VLOOKUP(B34,PROVEEDORES!$B:$C,2,FALSE)) | E34: 0 | G34: BASE: | I34: 0
A35: NIT | B35: PROVEEDOR | C35: CONCEPTO | D35: DESCRIPCIÓN | E35: BANCO | G35: TOTAL EFECTIVO MENOS LA BASE: | I35: =I33-I34 -> 0
A36: =IF(B36="","",VLOOKUP(B36,PROVEEDORES!$B:$C,2,FALSE)) | E36: 0
A37: =IF(B37="","",VLOOKUP(B37,PROVEEDORES!$B:$C,2,FALSE)) | E37: 0 | G37: ACUM. DE PROPINA TRANSFERENCIA: | I37: =+'6'!E13 -> 0
A38: =IF(B38="","",VLOOKUP(B38,PROVEEDORES!$B:$C,2,FALSE)) | E38: 0 | G38: ACUMULADO DE PROPINA EN BANCO: | I38: =+'6'!E14 -> 0
A39: =IF(B39="","",VLOOKUP(B39,PROVEEDORES!$B:$C,2,FALSE)) | E39: 0 | G39: ACUMULADO DE PROPINA POR EFECTIVO: | I39: =+'6'!E15 -> 0
A40: =IF(B40="","",VLOOKUP(B40,PROVEEDORES!$B:$C,2,FALSE)) | E40: 0 | G40: ACUMULADO DE TRANSFERENCIA: | I40: =+'6'!E16 -> 0
A41: =IF(B41="","",VLOOKUP(B41,PROVEEDORES!$B:$C,2,FALSE)) | E41: 0 | G41: ACUMULADO DE BANCO: | I41: =+'6'!E17 -> 0
A42: =IF(B42="","",VLOOKUP(B42,PROVEEDORES!$B:$C,2,FALSE)) | E42: 0 | G42: REAL DE BANCO: | I42: =+'6'!E18 -> 0
A43: =IF(B43="","",VLOOKUP(B43,PROVEEDORES!$B:$C,2,FALSE)) | E43: 0 | G43: EFECTIVO ANTERIOR: | I43: =+'6'!E19 -> 0
A44: =IF(B44="","",VLOOKUP(B44,PROVEEDORES!$B:$C,2,FALSE)) | E44: 0
A45: =IF(B45="","",VLOOKUP(B45,PROVEEDORES!$B:$C,2,FALSE)) | E45: 0
A46: =IF(B46="","",VLOOKUP(B46,PROVEEDORES!$B:$C,2,FALSE)) | E46: 0
A47: =IF(B47="","",VLOOKUP(B47,PROVEEDORES!$B:$C,2,FALSE)) | E47: 0
A48: =IF(B48="","",VLOOKUP(B48,PROVEEDORES!$B:$C,2,FALSE)) | E48: 0
A49: =IF(B49="","",VLOOKUP(B49,PROVEEDORES!$B:$C,2,FALSE)) | E49: 0
A50: =IF(B50="","",VLOOKUP(B50,PROVEEDORES!$B:$C,2,FALSE)) | E50: 0
A51: =IF(B51="","",VLOOKUP(B51,PROVEEDORES!$B:$C,2,FALSE)) | E51: 0
A52: =IF(B52="","",VLOOKUP(B52,PROVEEDORES!$B:$C,2,FALSE)) | E52: 0
A53: =IF(B53="","",VLOOKUP(B53,PROVEEDORES!$B:$C,2,FALSE)) | E53: 0
A54: =IF(B54="","",VLOOKUP(B54,PROVEEDORES!$B:$C,2,FALSE)) | E54: 0
A55: =IF(B55="","",VLOOKUP(B55,PROVEEDORES!$B:$C,2,FALSE)) | E55: 0
A56: EGRESO PROPINA | D56: INGRESO DE EFECTIVO
A57: PROPINA TRANSFERENCIA: | C57: 0 | E57: 0
A58: PROPINA BANCO: | C58: 0 | E58: 0
A59: PROPINA EFECTIVO: | C59: 0 | E59: 0

Sheet 8
A1: ='7'!A1+1 -> 8 | B1: =+'1'!B1 -> QUESO Y CAFÉ | D1: =+'7'!D1:E1+1 -> 46150 | G1: CUADRE DE CAJA MAÑANA | I1: CUADRE DE CAJA TARDE
A2: NIT | B2: PROVEEDOR | C2: CONCEPTO | D2: DESCRIPCIÓN | E2: VALOR | G2: PROP. TRANSF.: | H2: 0 | I2: PROP. TRANSF.: | J2: 0
A3: =IF(B3="","",VLOOKUP(B3,PROVEEDORES!$B:$C,2,FALSE)) | E3: 0 | G3: PROP. BANCO: | H3: 0 | I3: PROP. BANCO: | J3: 0
A4: =IF(B4="","",VLOOKUP(B4,PROVEEDORES!$B:$C,2,FALSE)) | E4: 0 | G4: PROP. EFECTIVO: | H4: 0 | I4: PROP. EFECTIVO: | J4: 0
A5: =IF(B5="","",VLOOKUP(B5,PROVEEDORES!$B:$C,2,FALSE)) | E5: 0 | G5: GASTO: | H5: 0 | I5: GASTO: | J5: 0
A6: =IF(B6="","",VLOOKUP(B6,PROVEEDORES!$B:$C,2,FALSE)) | E6: 0 | G6: TRANSFERENCIA: | H6: 0 | I6: TRANSFERENCIA: | J6: 0
A7: =IF(B7="","",VLOOKUP(B7,PROVEEDORES!$B:$C,2,FALSE)) | E7: 0 | G7: BANCO: | H7: 0 | I7: BANCO: | J7: 0
A8: =IF(B8="","",VLOOKUP(B8,PROVEEDORES!$B:$C,2,FALSE)) | E8: 0 | G8: EFECTIVO: | H8: 0 | I8: EFECTIVO: | J8: 0
A9: =IF(B9="","",VLOOKUP(B9,PROVEEDORES!$B:$C,2,FALSE)) | E9: 0 | G9: TOTAL: | H9: =SUM(H5:H8) -> 0 | I9: TOTAL: | J9: =SUM(J5:J8) -> 0
A10: =IF(B10="","",VLOOKUP(B10,PROVEEDORES!$B:$C,2,FALSE)) | E10: 0 | G10: DIFERENCIA: | H10: =+H11-H9 -> 0 | I10: DIFERENCIA: | J10: =+J11-J9 -> 0
A11: =IF(B11="","",VLOOKUP(B11,PROVEEDORES!$B:$C,2,FALSE)) | E11: 0 | G11: TOTAL VENTA: | H11: 0 | I11: TOTAL VENTA: | J11: 0
A12: =IF(B12="","",VLOOKUP(B12,PROVEEDORES!$B:$C,2,FALSE)) | E12: 0
A13: PROPINA TRANSFERENCIA: | C13: =SUM(H2,J2) -> 0 | D13: ACUM. PROPINA TRANFERENCIA: | E13: =SUM(C13,I37)-C57 -> 0 | G13: DIFERENCIA PLANILLA VS CUADRE DE CAJA | I13: =+C20-(SUM(H9,J9)) -> 0
A14: PROPINA POR BANCO: | C14: =SUM(H3,J3) -> 0 | D14: ACUM. PROPINA BANCO: | E14: =SUM(C14,I38)-C58 -> 0
A15: PROPINA EN EFECTIVO: | C15: =SUM(H4,J4) -> 0 | D15: ACUM. PROPINA EFECTIVO: | E15: =SUM(C15,I39)-C59 -> 0 | G15: FACTURAS EN EFECTIVO: | I15: 0
A16: TOTAL EGRESOS: | C16: =SUM(E3:E12) -> 0 | D16: ACUMULADO TRANSFERENCIA: | E16: =SUM(C17,I40) -> 0 | G16: EFECTIVO: | I16: 0
A17: TRANSFERENCIA: | C17: =SUM(H6,J6) -> 0 | D17: ACUMULADO BANCO: | E17: =SUM(C18,I41) -> 0 | G17: TOTAL EFECTIVO REAL ACTUAL: | I17: =SUM(I15,I16) -> 0
A18: BANCO: | C18: =SUM(H7,J7) -> 0 | D18: TOTAL BANCO: | E18: =SUM(C18,I42)-(SUM(E36:E55)) -> 0 | G18: DIFERENCIA: | I18: =+I19-I17 -> 0
A19: EFECTIVO: | C19: =SUM(H8,J8) -> 0 | D19: TOTAL EFECTIVO: | E19: =SUM(C19,E20,E57:E59)-(SUM(E23:E34)) -> 0 | G19: EFECTIVO ACTUAL PLANILLA: | I19: =E19 -> 0
A20: TOTAL VENTA: | C20: =SUM(C16:C19) -> 0 | D20: EFECTIVO ANTERIOR: | E20: =+I43 -> 0
A21: EGRESO DE CAJA MAYOR | G21: CONTEO DE EFECTIVO
A22: NIT | B22: PROVEEDOR | C22: CONCEPTO | D22: DESCRIPCIÓN | E22: EFECTIVO | G22: DENOMINACIÓN | H22: CANTIDAD | I22: EFECTIVO
A23: =IF(B23="","",VLOOKUP(B23,PROVEEDORES!$B:$C,2,FALSE)) | E23: 0 | G23: MONEDAS DE 100 | H23: 0 | I23: =100*H23 -> 0
A24: =IF(B24="","",VLOOKUP(B24,PROVEEDORES!$B:$C,2,FALSE)) | E24: 0 | G24: MONEDAS DE 200 | H24: 0 | I24: =200*H24 -> 0
A25: =IF(B25="","",VLOOKUP(B25,PROVEEDORES!$B:$C,2,FALSE)) | E25: 0 | G25: MONEDAS DE 500 | H25: 0 | I25: =500*H25 -> 0
A26: =IF(B26="","",VLOOKUP(B26,PROVEEDORES!$B:$C,2,FALSE)) | E26: 0 | G26: MONEDAS DE 1.000 | H26: 0 | I26: =1000*H26 -> 0
A27: =IF(B27="","",VLOOKUP(B27,PROVEEDORES!$B:$C,2,FALSE)) | E27: 0 | G27: BILLETES DE 2.000 | H27: 0 | I27: =2000*H27 -> 0
A28: =IF(B28="","",VLOOKUP(B28,PROVEEDORES!$B:$C,2,FALSE)) | E28: 0 | G28: BILLETES DE 5.000 | H28: 0 | I28: =5000*H28 -> 0
A29: =IF(B29="","",VLOOKUP(B29,PROVEEDORES!$B:$C,2,FALSE)) | E29: 0 | G29: BILLETES DE 10.000 | H29: 0 | I29: =10000*H29 -> 0
A30: =IF(B30="","",VLOOKUP(B30,PROVEEDORES!$B:$C,2,FALSE)) | E30: 0 | G30: BILLETES DE 20.000 | H30: 0 | I30: =20000*H30 -> 0
A31: =IF(B31="","",VLOOKUP(B31,PROVEEDORES!$B:$C,2,FALSE)) | E31: 0 | G31: BILLETES DE 50.000 | H31: 0 | I31: =50000*H31 -> 0
A32: =IF(B32="","",VLOOKUP(B32,PROVEEDORES!$B:$C,2,FALSE)) | E32: 0 | G32: BILLETES DE 100.000 | H32: 0 | I32: =100000*H32 -> 0
A33: =IF(B33="","",VLOOKUP(B33,PROVEEDORES!$B:$C,2,FALSE)) | E33: 0 | G33: TOTAL EFECTIVO: | I33: =SUM(I23:I32) -> 0
A34: =IF(B34="","",VLOOKUP(B34,PROVEEDORES!$B:$C,2,FALSE)) | E34: 0 | G34: BASE: | I34: 0
A35: NIT | B35: PROVEEDOR | C35: CONCEPTO | D35: DESCRIPCIÓN | E35: BANCO | G35: TOTAL EFECTIVO MENOS LA BASE: | I35: =I33-I34 -> 0
A36: =IF(B36="","",VLOOKUP(B36,PROVEEDORES!$B:$C,2,FALSE)) | E36: 0
A37: =IF(B37="","",VLOOKUP(B37,PROVEEDORES!$B:$C,2,FALSE)) | E37: 0 | G37: ACUM. DE PROPINA TRANSFERENCIA: | I37: =+'7'!E13 -> 0
A38: =IF(B38="","",VLOOKUP(B38,PROVEEDORES!$B:$C,2,FALSE)) | E38: 0 | G38: ACUMULADO DE PROPINA EN BANCO: | I38: =+'7'!E14 -> 0
A39: =IF(B39="","",VLOOKUP(B39,PROVEEDORES!$B:$C,2,FALSE)) | E39: 0 | G39: ACUMULADO DE PROPINA POR EFECTIVO: | I39: =+'7'!E15 -> 0
A40: =IF(B40="","",VLOOKUP(B40,PROVEEDORES!$B:$C,2,FALSE)) | E40: 0 | G40: ACUMULADO DE TRANSFERENCIA: | I40: =+'7'!E16 -> 0
A41: =IF(B41="","",VLOOKUP(B41,PROVEEDORES!$B:$C,2,FALSE)) | E41: 0 | G41: ACUMULADO DE BANCO: | I41: =+'7'!E17 -> 0
A42: =IF(B42="","",VLOOKUP(B42,PROVEEDORES!$B:$C,2,FALSE)) | E42: 0 | G42: REAL DE BANCO: | I42: =+'7'!E18 -> 0
A43: =IF(B43="","",VLOOKUP(B43,PROVEEDORES!$B:$C,2,FALSE)) | E43: 0 | G43: EFECTIVO ANTERIOR: | I43: =+'7'!E19 -> 0
A44: =IF(B44="","",VLOOKUP(B44,PROVEEDORES!$B:$C,2,FALSE)) | E44: 0
A45: =IF(B45="","",VLOOKUP(B45,PROVEEDORES!$B:$C,2,FALSE)) | E45: 0
A46: =IF(B46="","",VLOOKUP(B46,PROVEEDORES!$B:$C,2,FALSE)) | E46: 0
A47: =IF(B47="","",VLOOKUP(B47,PROVEEDORES!$B:$C,2,FALSE)) | E47: 0
A48: =IF(B48="","",VLOOKUP(B48,PROVEEDORES!$B:$C,2,FALSE)) | E48: 0
A49: =IF(B49="","",VLOOKUP(B49,PROVEEDORES!$B:$C,2,FALSE)) | E49: 0
A50: =IF(B50="","",VLOOKUP(B50,PROVEEDORES!$B:$C,2,FALSE)) | E50: 0
A51: =IF(B51="","",VLOOKUP(B51,PROVEEDORES!$B:$C,2,FALSE)) | E51: 0
A52: =IF(B52="","",VLOOKUP(B52,PROVEEDORES!$B:$C,2,FALSE)) | E52: 0
A53: =IF(B53="","",VLOOKUP(B53,PROVEEDORES!$B:$C,2,FALSE)) | E53: 0
A54: =IF(B54="","",VLOOKUP(B54,PROVEEDORES!$B:$C,2,FALSE)) | E54: 0
A55: =IF(B55="","",VLOOKUP(B55,PROVEEDORES!$B:$C,2,FALSE)) | E55: 0
A56: EGRESO PROPINA | D56: INGRESO DE EFECTIVO
A57: PROPINA TRANSFERENCIA: | C57: 0 | E57: 0
A58: PROPINA BANCO: | C58: 0 | E58: 0
A59: PROPINA EFECTIVO: | C59: 0 | E59: 0

Sheet 9
A1: ='8'!A1+1 -> 9 | B1: =+'1'!B1 -> QUESO Y CAFÉ | D1: =+'8'!D1:E1+1 -> 46151 | G1: CUADRE DE CAJA MAÑANA | I1: CUADRE DE CAJA TARDE
A2: NIT | B2: PROVEEDOR | C2: CONCEPTO | D2: DESCRIPCIÓN | E2: VALOR | G2: PROP. TRANSF.: | H2: 0 | I2: PROP. TRANSF.: | J2: 0
A3: =IF(B3="","",VLOOKUP(B3,PROVEEDORES!$B:$C,2,FALSE)) | E3: 0 | G3: PROP. BANCO: | H3: 0 | I3: PROP. BANCO: | J3: 0
A4: =IF(B4="","",VLOOKUP(B4,PROVEEDORES!$B:$C,2,FALSE)) | E4: 0 | G4: PROP. EFECTIVO: | H4: 0 | I4: PROP. EFECTIVO: | J4: 0
A5: =IF(B5="","",VLOOKUP(B5,PROVEEDORES!$B:$C,2,FALSE)) | E5: 0 | G5: GASTO: | H5: 0 | I5: GASTO: | J5: 0
A6: =IF(B6="","",VLOOKUP(B6,PROVEEDORES!$B:$C,2,FALSE)) | E6: 0 | G6: TRANSFERENCIA: | H6: 0 | I6: TRANSFERENCIA: | J6: 0
A7: =IF(B7="","",VLOOKUP(B7,PROVEEDORES!$B:$C,2,FALSE)) | E7: 0 | G7: BANCO: | H7: 0 | I7: BANCO: | J7: 0
A8: =IF(B8="","",VLOOKUP(B8,PROVEEDORES!$B:$C,2,FALSE)) | E8: 0 | G8: EFECTIVO: | H8: 0 | I8: EFECTIVO: | J8: 0
A9: =IF(B9="","",VLOOKUP(B9,PROVEEDORES!$B:$C,2,FALSE)) | E9: 0 | G9: TOTAL: | H9: =SUM(H5:H8) -> 0 | I9: TOTAL: | J9: =SUM(J5:J8) -> 0
A10: =IF(B10="","",VLOOKUP(B10,PROVEEDORES!$B:$C,2,FALSE)) | E10: 0 | G10: DIFERENCIA: | H10: =+H11-H9 -> 0 | I10: DIFERENCIA: | J10: =+J11-J9 -> 0
A11: =IF(B11="","",VLOOKUP(B11,PROVEEDORES!$B:$C,2,FALSE)) | E11: 0 | G11: TOTAL VENTA: | H11: 0 | I11: TOTAL VENTA: | J11: 0
A12: =IF(B12="","",VLOOKUP(B12,PROVEEDORES!$B:$C,2,FALSE)) | E12: 0
A13: PROPINA TRANSFERENCIA: | C13: =SUM(H2,J2) -> 0 | D13: ACUM. PROPINA TRANFERENCIA: | E13: =SUM(C13,I37)-C57 -> 0 | G13: DIFERENCIA PLANILLA VS CUADRE DE CAJA | I13: =+C20-(SUM(H9,J9)) -> 0
A14: PROPINA POR BANCO: | C14: =SUM(H3,J3) -> 0 | D14: ACUM. PROPINA BANCO: | E14: =SUM(C14,I38)-C58 -> 0
A15: PROPINA EN EFECTIVO: | C15: =SUM(H4,J4) -> 0 | D15: ACUM. PROPINA EFECTIVO: | E15: =SUM(C15,I39)-C59 -> 0 | G15: FACTURAS EN EFECTIVO: | I15: 0
A16: TOTAL EGRESOS: | C16: =SUM(E3:E12) -> 0 | D16: ACUMULADO TRANSFERENCIA: | E16: =SUM(C17,I40) -> 0 | G16: EFECTIVO: | I16: 0
A17: TRANSFERENCIA: | C17: =SUM(H6,J6) -> 0 | D17: ACUMULADO BANCO: | E17: =SUM(C18,I41) -> 0 | G17: TOTAL EFECTIVO REAL ACTUAL: | I17: =SUM(I15,I16) -> 0
A18: BANCO: | C18: =SUM(H7,J7) -> 0 | D18: TOTAL BANCO: | E18: =SUM(C18,I42)-(SUM(E36:E55)) -> 0 | G18: DIFERENCIA: | I18: =+I19-I17 -> 0
A19: EFECTIVO: | C19: =SUM(H8,J8) -> 0 | D19: TOTAL EFECTIVO: | E19: =SUM(C19,E20,E57:E59)-(SUM(E23:E34)) -> 0 | G19: EFECTIVO ACTUAL PLANILLA: | I19: =E19 -> 0
A20: TOTAL VENTA: | C20: =SUM(C16:C19) -> 0 | D20: EFECTIVO ANTERIOR: | E20: =+I43 -> 0
A21: EGRESO DE CAJA MAYOR | G21: CONTEO DE EFECTIVO
A22: NIT | B22: PROVEEDOR | C22: CONCEPTO | D22: DESCRIPCIÓN | E22: EFECTIVO | G22: DENOMINACIÓN | H22: CANTIDAD | I22: EFECTIVO
A23: =IF(B23="","",VLOOKUP(B23,PROVEEDORES!$B:$C,2,FALSE)) | E23: 0 | G23: MONEDAS DE 100 | H23: 0 | I23: =100*H23 -> 0
A24: =IF(B24="","",VLOOKUP(B24,PROVEEDORES!$B:$C,2,FALSE)) | E24: 0 | G24: MONEDAS DE 200 | H24: 0 | I24: =200*H24 -> 0
A25: =IF(B25="","",VLOOKUP(B25,PROVEEDORES!$B:$C,2,FALSE)) | E25: 0 | G25: MONEDAS DE 500 | H25: 0 | I25: =500*H25 -> 0
A26: =IF(B26="","",VLOOKUP(B26,PROVEEDORES!$B:$C,2,FALSE)) | E26: 0 | G26: MONEDAS DE 1.000 | H26: 0 | I26: =1000*H26 -> 0
A27: =IF(B27="","",VLOOKUP(B27,PROVEEDORES!$B:$C,2,FALSE)) | E27: 0 | G27: BILLETES DE 2.000 | H27: 0 | I27: =2000*H27 -> 0
A28: =IF(B28="","",VLOOKUP(B28,PROVEEDORES!$B:$C,2,FALSE)) | E28: 0 | G28: BILLETES DE 5.000 | H28: 0 | I28: =5000*H28 -> 0
A29: =IF(B29="","",VLOOKUP(B29,PROVEEDORES!$B:$C,2,FALSE)) | E29: 0 | G29: BILLETES DE 10.000 | H29: 0 | I29: =10000*H29 -> 0
A30: =IF(B30="","",VLOOKUP(B30,PROVEEDORES!$B:$C,2,FALSE)) | E30: 0 | G30: BILLETES DE 20.000 | H30: 0 | I30: =20000*H30 -> 0
A31: =IF(B31="","",VLOOKUP(B31,PROVEEDORES!$B:$C,2,FALSE)) | E31: 0 | G31: BILLETES DE 50.000 | H31: 0 | I31: =50000*H31 -> 0
A32: =IF(B32="","",VLOOKUP(B32,PROVEEDORES!$B:$C,2,FALSE)) | E32: 0 | G32: BILLETES DE 100.000 | H32: 0 | I32: =100000*H32 -> 0
A33: =IF(B33="","",VLOOKUP(B33,PROVEEDORES!$B:$C,2,FALSE)) | E33: 0 | G33: TOTAL EFECTIVO: | I33: =SUM(I23:I32) -> 0
A34: =IF(B34="","",VLOOKUP(B34,PROVEEDORES!$B:$C,2,FALSE)) | E34: 0 | G34: BASE: | I34: 0
A35: NIT | B35: PROVEEDOR | C35: CONCEPTO | D35: DESCRIPCIÓN | E35: BANCO | G35: TOTAL EFECTIVO MENOS LA BASE: | I35: =I33-I34 -> 0
A36: =IF(B36="","",VLOOKUP(B36,PROVEEDORES!$B:$C,2,FALSE)) | E36: 0
A37: =IF(B37="","",VLOOKUP(B37,PROVEEDORES!$B:$C,2,FALSE)) | E37: 0 | G37: ACUM. DE PROPINA TRANSFERENCIA: | I37: =+'8'!E13 -> 0
A38: =IF(B38="","",VLOOKUP(B38,PROVEEDORES!$B:$C,2,FALSE)) | E38: 0 | G38: ACUMULADO DE PROPINA EN BANCO: | I38: =+'8'!E14 -> 0
A39: =IF(B39="","",VLOOKUP(B39,PROVEEDORES!$B:$C,2,FALSE)) | E39: 0 | G39: ACUMULADO DE PROPINA POR EFECTIVO: | I39: =+'8'!E15 -> 0
A40: =IF(B40="","",VLOOKUP(B40,PROVEEDORES!$B:$C,2,FALSE)) | E40: 0 | G40: ACUMULADO DE TRANSFERENCIA: | I40: =+'8'!E16 -> 0
A41: =IF(B41="","",VLOOKUP(B41,PROVEEDORES!$B:$C,2,FALSE)) | E41: 0 | G41: ACUMULADO DE BANCO: | I41: =+'8'!E17 -> 0
A42: =IF(B42="","",VLOOKUP(B42,PROVEEDORES!$B:$C,2,FALSE)) | E42: 0 | G42: REAL DE BANCO: | I42: =+'8'!E18 -> 0
A43: =IF(B43="","",VLOOKUP(B43,PROVEEDORES!$B:$C,2,FALSE)) | E43: 0 | G43: EFECTIVO ANTERIOR: | I43: =+'8'!E19 -> 0
A44: =IF(B44="","",VLOOKUP(B44,PROVEEDORES!$B:$C,2,FALSE)) | E44: 0
A45: =IF(B45="","",VLOOKUP(B45,PROVEEDORES!$B:$C,2,FALSE)) | E45: 0
A46: =IF(B46="","",VLOOKUP(B46,PROVEEDORES!$B:$C,2,FALSE)) | E46: 0
A47: =IF(B47="","",VLOOKUP(B47,PROVEEDORES!$B:$C,2,FALSE)) | E47: 0
A48: =IF(B48="","",VLOOKUP(B48,PROVEEDORES!$B:$C,2,FALSE)) | E48: 0
A49: =IF(B49="","",VLOOKUP(B49,PROVEEDORES!$B:$C,2,FALSE)) | E49: 0
A50: =IF(B50="","",VLOOKUP(B50,PROVEEDORES!$B:$C,2,FALSE)) | E50: 0
A51: =IF(B51="","",VLOOKUP(B51,PROVEEDORES!$B:$C,2,FALSE)) | E51: 0
A52: =IF(B52="","",VLOOKUP(B52,PROVEEDORES!$B:$C,2,FALSE)) | E52: 0
A53: =IF(B53="","",VLOOKUP(B53,PROVEEDORES!$B:$C,2,FALSE)) | E53: 0
A54: =IF(B54="","",VLOOKUP(B54,PROVEEDORES!$B:$C,2,FALSE)) | E54: 0
A55: =IF(B55="","",VLOOKUP(B55,PROVEEDORES!$B:$C,2,FALSE)) | E55: 0
A56: EGRESO PROPINA | D56: INGRESO DE EFECTIVO
A57: PROPINA TRANSFERENCIA: | C57: 0 | E57: 0
A58: PROPINA BANCO: | C58: 0 | E58: 0
A59: PROPINA EFECTIVO: | C59: 0 | E59: 0

Sheet 10
A1: ='9'!A1+1 -> 10 | B1: =+'1'!B1 -> QUESO Y CAFÉ | D1: =+'9'!D1:E1+1 -> 46152 | G1: CUADRE DE CAJA MAÑANA | I1: CUADRE DE CAJA TARDE
A2: NIT | B2: PROVEEDOR | C2: CONCEPTO | D2: DESCRIPCIÓN | E2: VALOR | G2: PROP. TRANSF.: | H2: 0 | I2: PROP. TRANSF.: | J2: 0
A3: =IF(B3="","",VLOOKUP(B3,PROVEEDORES!$B:$C,2,FALSE)) | E3: 0 | G3: PROP. BANCO: | H3: 0 | I3: PROP. BANCO: | J3: 0
A4: =IF(B4="","",VLOOKUP(B4,PROVEEDORES!$B:$C,2,FALSE)) | E4: 0 | G4: PROP. EFECTIVO: | H4: 0 | I4: PROP. EFECTIVO: | J4: 0
A5: =IF(B5="","",VLOOKUP(B5,PROVEEDORES!$B:$C,2,FALSE)) | E5: 0 | G5: GASTO: | H5: 0 | I5: GASTO: | J5: 0
A6: =IF(B6="","",VLOOKUP(B6,PROVEEDORES!$B:$C,2,FALSE)) | E6: 0 | G6: TRANSFERENCIA: | H6: 0 | I6: TRANSFERENCIA: | J6: 0
A7: =IF(B7="","",VLOOKUP(B7,PROVEEDORES!$B:$C,2,FALSE)) | E7: 0 | G7: BANCO: | H7: 0 | I7: BANCO: | J7: 0
A8: =IF(B8="","",VLOOKUP(B8,PROVEEDORES!$B:$C,2,FALSE)) | E8: 0 | G8: EFECTIVO: | H8: 0 | I8: EFECTIVO: | J8: 0
A9: =IF(B9="","",VLOOKUP(B9,PROVEEDORES!$B:$C,2,FALSE)) | E9: 0 | G9: TOTAL: | H9: =SUM(H5:H8) -> 0 | I9: TOTAL: | J9: =SUM(J5:J8) -> 0
A10: =IF(B10="","",VLOOKUP(B10,PROVEEDORES!$B:$C,2,FALSE)) | E10: 0 | G10: DIFERENCIA: | H10: =+H11-H9 -> 0 | I10: DIFERENCIA: | J10: =+J11-J9 -> 0
A11: =IF(B11="","",VLOOKUP(B11,PROVEEDORES!$B:$C,2,FALSE)) | E11: 0 | G11: TOTAL VENTA: | H11: 0 | I11: TOTAL VENTA: | J11: 0
A12: =IF(B12="","",VLOOKUP(B12,PROVEEDORES!$B:$C,2,FALSE)) | E12: 0
A13: PROPINA TRANSFERENCIA: | C13: =SUM(H2,J2) -> 0 | D13: ACUM. PROPINA TRANFERENCIA: | E13: =SUM(C13,I37)-C57 -> 0 | G13: DIFERENCIA PLANILLA VS CUADRE DE CAJA | I13: =+C20-(SUM(H9,J9)) -> 0
A14: PROPINA POR BANCO: | C14: =SUM(H3,J3) -> 0 | D14: ACUM. PROPINA BANCO: | E14: =SUM(C14,I38)-C58 -> 0
A15: PROPINA EN EFECTIVO: | C15: =SUM(H4,J4) -> 0 | D15: ACUM. PROPINA EFECTIVO: | E15: =SUM(C15,I39)-C59 -> 0 | G15: FACTURAS EN EFECTIVO: | I15: 0
A16: TOTAL EGRESOS: | C16: =SUM(E3:E12) -> 0 | D16: ACUMULADO TRANSFERENCIA: | E16: =SUM(C17,I40) -> 0 | G16: EFECTIVO: | I16: 0
A17: TRANSFERENCIA: | C17: =SUM(H6,J6) -> 0 | D17: ACUMULADO BANCO: | E17: =SUM(C18,I41) -> 0 | G17: TOTAL EFECTIVO REAL ACTUAL: | I17: =SUM(I15,I16) -> 0
A18: BANCO: | C18: =SUM(H7,J7) -> 0 | D18: TOTAL BANCO: | E18: =SUM(C18,I42)-(SUM(E36:E55)) -> 0 | G18: DIFERENCIA: | I18: =+I19-I17 -> 0
A19: EFECTIVO: | C19: =SUM(H8,J8) -> 0 | D19: TOTAL EFECTIVO: | E19: =SUM(C19,E20,E57:E59)-(SUM(E23:E34)) -> 0 | G19: EFECTIVO ACTUAL PLANILLA: | I19: =E19 -> 0
A20: TOTAL VENTA: | C20: =SUM(C16:C19) -> 0 | D20: EFECTIVO ANTERIOR: | E20: =+I43 -> 0
A21: EGRESO DE CAJA MAYOR | G21: CONTEO DE EFECTIVO
A22: NIT | B22: PROVEEDOR | C22: CONCEPTO | D22: DESCRIPCIÓN | E22: EFECTIVO | G22: DENOMINACIÓN | H22: CANTIDAD | I22: EFECTIVO
A23: =IF(B23="","",VLOOKUP(B23,PROVEEDORES!$B:$C,2,FALSE)) | E23: 0 | G23: MONEDAS DE 100 | H23: 0 | I23: =100*H23 -> 0
A24: =IF(B24="","",VLOOKUP(B24,PROVEEDORES!$B:$C,2,FALSE)) | E24: 0 | G24: MONEDAS DE 200 | H24: 0 | I24: =200*H24 -> 0
A25: =IF(B25="","",VLOOKUP(B25,PROVEEDORES!$B:$C,2,FALSE)) | E25: 0 | G25: MONEDAS DE 500 | H25: 0 | I25: =500*H25 -> 0
A26: =IF(B26="","",VLOOKUP(B26,PROVEEDORES!$B:$C,2,FALSE)) | E26: 0 | G26: MONEDAS DE 1.000 | H26: 0 | I26: =1000*H26 -> 0
A27: =IF(B27="","",VLOOKUP(B27,PROVEEDORES!$B:$C,2,FALSE)) | E27: 0 | G27: BILLETES DE 2.000 | H27: 0 | I27: =2000*H27 -> 0
A28: =IF(B28="","",VLOOKUP(B28,PROVEEDORES!$B:$C,2,FALSE)) | E28: 0 | G28: BILLETES DE 5.000 | H28: 0 | I28: =5000*H28 -> 0
A29: =IF(B29="","",VLOOKUP(B29,PROVEEDORES!$B:$C,2,FALSE)) | E29: 0 | G29: BILLETES DE 10.000 | H29: 0 | I29: =10000*H29 -> 0
A30: =IF(B30="","",VLOOKUP(B30,PROVEEDORES!$B:$C,2,FALSE)) | E30: 0 | G30: BILLETES DE 20.000 | H30: 0 | I30: =20000*H30 -> 0
A31: =IF(B31="","",VLOOKUP(B31,PROVEEDORES!$B:$C,2,FALSE)) | E31: 0 | G31: BILLETES DE 50.000 | H31: 0 | I31: =50000*H31 -> 0
A32: =IF(B32="","",VLOOKUP(B32,PROVEEDORES!$B:$C,2,FALSE)) | E32: 0 | G32: BILLETES DE 100.000 | H32: 0 | I32: =100000*H32 -> 0
A33: =IF(B33="","",VLOOKUP(B33,PROVEEDORES!$B:$C,2,FALSE)) | E33: 0 | G33: TOTAL EFECTIVO: | I33: =SUM(I23:I32) -> 0
A34: =IF(B34="","",VLOOKUP(B34,PROVEEDORES!$B:$C,2,FALSE)) | E34: 0 | G34: BASE: | I34: 0
A35: NIT | B35: PROVEEDOR | C35: CONCEPTO | D35: DESCRIPCIÓN | E35: BANCO | G35: TOTAL EFECTIVO MENOS LA BASE: | I35: =I33-I34 -> 0
A36: =IF(B36="","",VLOOKUP(B36,PROVEEDORES!$B:$C,2,FALSE)) | E36: 0
A37: =IF(B37="","",VLOOKUP(B37,PROVEEDORES!$B:$C,2,FALSE)) | E37: 0 | G37: ACUM. DE PROPINA TRANSFERENCIA: | I37: =+'9'!E13 -> 0
A38: =IF(B38="","",VLOOKUP(B38,PROVEEDORES!$B:$C,2,FALSE)) | E38: 0 | G38: ACUMULADO DE PROPINA EN BANCO: | I38: =+'9'!E14 -> 0
A39: =IF(B39="","",VLOOKUP(B39,PROVEEDORES!$B:$C,2,FALSE)) | E39: 0 | G39: ACUMULADO DE PROPINA POR EFECTIVO: | I39: =+'9'!E15 -> 0
A40: =IF(B40="","",VLOOKUP(B40,PROVEEDORES!$B:$C,2,FALSE)) | E40: 0 | G40: ACUMULADO DE TRANSFERENCIA: | I40: =+'9'!E16 -> 0
A41: =IF(B41="","",VLOOKUP(B41,PROVEEDORES!$B:$C,2,FALSE)) | E41: 0 | G41: ACUMULADO DE BANCO: | I41: =+'9'!E17 -> 0
A42: =IF(B42="","",VLOOKUP(B42,PROVEEDORES!$B:$C,2,FALSE)) | E42: 0 | G42: REAL DE BANCO: | I42: =+'9'!E18 -> 0
A43: =IF(B43="","",VLOOKUP(B43,PROVEEDORES!$B:$C,2,FALSE)) | E43: 0 | G43: EFECTIVO ANTERIOR: | I43: =+'9'!E19 -> 0
A44: =IF(B44="","",VLOOKUP(B44,PROVEEDORES!$B:$C,2,FALSE)) | E44: 0
A45: =IF(B45="","",VLOOKUP(B45,PROVEEDORES!$B:$C,2,FALSE)) | E45: 0
A46: =IF(B46="","",VLOOKUP(B46,PROVEEDORES!$B:$C,2,FALSE)) | E46: 0
A47: =IF(B47="","",VLOOKUP(B47,PROVEEDORES!$B:$C,2,FALSE)) | E47: 0
A48: =IF(B48="","",VLOOKUP(B48,PROVEEDORES!$B:$C,2,FALSE)) | E48: 0
A49: =IF(B49="","",VLOOKUP(B49,PROVEEDORES!$B:$C,2,FALSE)) | E49: 0
A50: =IF(B50="","",VLOOKUP(B50,PROVEEDORES!$B:$C,2,FALSE)) | E50: 0
A51: =IF(B51="","",VLOOKUP(B51,PROVEEDORES!$B:$C,2,FALSE)) | E51: 0
A52: =IF(B52="","",VLOOKUP(B52,PROVEEDORES!$B:$C,2,FALSE)) | E52: 0
A53: =IF(B53="","",VLOOKUP(B53,PROVEEDORES!$B:$C,2,FALSE)) | E53: 0
A54: =IF(B54="","",VLOOKUP(B54,PROVEEDORES!$B:$C,2,FALSE)) | E54: 0
A55: =IF(B55="","",VLOOKUP(B55,PROVEEDORES!$B:$C,2,FALSE)) | E55: 0
A56: EGRESO PROPINA | D56: INGRESO DE EFECTIVO
A57: PROPINA TRANSFERENCIA: | C57: 0 | E57: 0
A58: PROPINA BANCO: | C58: 0 | E58: 0
A59: PROPINA EFECTIVO: | C59: 0 | E59: 0

Sheet 11
A1: ='10'!A1+1 -> 11 | B1: =+'1'!B1 -> QUESO Y CAFÉ | D1: =+'10'!D1:E1+1 -> 46153 | G1: CUADRE DE CAJA MAÑANA | I1: CUADRE DE CAJA TARDE
A2: NIT | B2: PROVEEDOR | C2: CONCEPTO | D2: DESCRIPCIÓN | E2: VALOR | G2: PROP. TRANSF.: | H2: 0 | I2: PROP. TRANSF.: | J2: 0
A3: =IF(B3="","",VLOOKUP(B3,PROVEEDORES!$B:$C,2,FALSE)) | E3: 0 | G3: PROP. BANCO: | H3: 0 | I3: PROP. BANCO: | J3: 0
A4: =IF(B4="","",VLOOKUP(B4,PROVEEDORES!$B:$C,2,FALSE)) | E4: 0 | G4: PROP. EFECTIVO: | H4: 0 | I4: PROP. EFECTIVO: | J4: 0
A5: =IF(B5="","",VLOOKUP(B5,PROVEEDORES!$B:$C,2,FALSE)) | E5: 0 | G5: GASTO: | H5: 0 | I5: GASTO: | J5: 0
A6: =IF(B6="","",VLOOKUP(B6,PROVEEDORES!$B:$C,2,FALSE)) | E6: 0 | G6: TRANSFERENCIA: | H6: 0 | I6: TRANSFERENCIA: | J6: 0
A7: =IF(B7="","",VLOOKUP(B7,PROVEEDORES!$B:$C,2,FALSE)) | E7: 0 | G7: BANCO: | H7: 0 | I7: BANCO: | J7: 0
A8: =IF(B8="","",VLOOKUP(B8,PROVEEDORES!$B:$C,2,FALSE)) | E8: 0 | G8: EFECTIVO: | H8: 0 | I8: EFECTIVO: | J8: 0
A9: =IF(B9="","",VLOOKUP(B9,PROVEEDORES!$B:$C,2,FALSE)) | E9: 0 | G9: TOTAL: | H9: =SUM(H5:H8) -> 0 | I9: TOTAL: | J9: =SUM(J5:J8) -> 0
A10: =IF(B10="","",VLOOKUP(B10,PROVEEDORES!$B:$C,2,FALSE)) | E10: 0 | G10: DIFERENCIA: | H10: =+H11-H9 -> 0 | I10: DIFERENCIA: | J10: =+J11-J9 -> 0
A11: =IF(B11="","",VLOOKUP(B11,PROVEEDORES!$B:$C,2,FALSE)) | E11: 0 | G11: TOTAL VENTA: | H11: 0 | I11: TOTAL VENTA: | J11: 0
A12: =IF(B12="","",VLOOKUP(B12,PROVEEDORES!$B:$C,2,FALSE)) | E12: 0
A13: PROPINA TRANSFERENCIA: | C13: =SUM(H2,J2) -> 0 | D13: ACUM. PROPINA TRANFERENCIA: | E13: =SUM(C13,I37)-C57 -> 0 | G13: DIFERENCIA PLANILLA VS CUADRE DE CAJA | I13: =+C20-(SUM(H9,J9)) -> 0
A14: PROPINA POR BANCO: | C14: =SUM(H3,J3) -> 0 | D14: ACUM. PROPINA BANCO: | E14: =SUM(C14,I38)-C58 -> 0
A15: PROPINA EN EFECTIVO: | C15: =SUM(H4,J4) -> 0 | D15: ACUM. PROPINA EFECTIVO: | E15: =SUM(C15,I39)-C59 -> 0 | G15: FACTURAS EN EFECTIVO: | I15: 0
A16: TOTAL EGRESOS: | C16: =SUM(E3:E12) -> 0 | D16: ACUMULADO TRANSFERENCIA: | E16: =SUM(C17,I40) -> 0 | G16: EFECTIVO: | I16: 0
A17: TRANSFERENCIA: | C17: =SUM(H6,J6) -> 0 | D17: ACUMULADO BANCO: | E17: =SUM(C18,I41) -> 0 | G17: TOTAL EFECTIVO REAL ACTUAL: | I17: =SUM(I15,I16) -> 0
A18: BANCO: | C18: =SUM(H7,J7) -> 0 | D18: TOTAL BANCO: | E18: =SUM(C18,I42)-(SUM(E36:E55)) -> 0 | G18: DIFERENCIA: | I18: =+I19-I17 -> 0
A19: EFECTIVO: | C19: =SUM(H8,J8) -> 0 | D19: TOTAL EFECTIVO: | E19: =SUM(C19,E20,E57:E59)-(SUM(E23:E34)) -> 0 | G19: EFECTIVO ACTUAL PLANILLA: | I19: =E19 -> 0
A20: TOTAL VENTA: | C20: =SUM(C16:C19) -> 0 | D20: EFECTIVO ANTERIOR: | E20: =+I43 -> 0
A21: EGRESO DE CAJA MAYOR | G21: CONTEO DE EFECTIVO
A22: NIT | B22: PROVEEDOR | C22: CONCEPTO | D22: DESCRIPCIÓN | E22: EFECTIVO | G22: DENOMINACIÓN | H22: CANTIDAD | I22: EFECTIVO
A23: =IF(B23="","",VLOOKUP(B23,PROVEEDORES!$B:$C,2,FALSE)) | E23: 0 | G23: MONEDAS DE 100 | H23: 0 | I23: =100*H23 -> 0
A24: =IF(B24="","",VLOOKUP(B24,PROVEEDORES!$B:$C,2,FALSE)) | E24: 0 | G24: MONEDAS DE 200 | H24: 0 | I24: =200*H24 -> 0
A25: =IF(B25="","",VLOOKUP(B25,PROVEEDORES!$B:$C,2,FALSE)) | E25: 0 | G25: MONEDAS DE 500 | H25: 0 | I25: =500*H25 -> 0
A26: =IF(B26="","",VLOOKUP(B26,PROVEEDORES!$B:$C,2,FALSE)) | E26: 0 | G26: MONEDAS DE 1.000 | H26: 0 | I26: =1000*H26 -> 0
A27: =IF(B27="","",VLOOKUP(B27,PROVEEDORES!$B:$C,2,FALSE)) | E27: 0 | G27: BILLETES DE 2.000 | H27: 0 | I27: =2000*H27 -> 0
A28: =IF(B28="","",VLOOKUP(B28,PROVEEDORES!$B:$C,2,FALSE)) | E28: 0 | G28: BILLETES DE 5.000 | H28: 0 | I28: =5000*H28 -> 0
A29: =IF(B29="","",VLOOKUP(B29,PROVEEDORES!$B:$C,2,FALSE)) | E29: 0 | G29: BILLETES DE 10.000 | H29: 0 | I29: =10000*H29 -> 0
A30: =IF(B30="","",VLOOKUP(B30,PROVEEDORES!$B:$C,2,FALSE)) | E30: 0 | G30: BILLETES DE 20.000 | H30: 0 | I30: =20000*H30 -> 0
A31: =IF(B31="","",VLOOKUP(B31,PROVEEDORES!$B:$C,2,FALSE)) | E31: 0 | G31: BILLETES DE 50.000 | H31: 0 | I31: =50000*H31 -> 0
A32: =IF(B32="","",VLOOKUP(B32,PROVEEDORES!$B:$C,2,FALSE)) | E32: 0 | G32: BILLETES DE 100.000 | H32: 0 | I32: =100000*H32 -> 0
A33: =IF(B33="","",VLOOKUP(B33,PROVEEDORES!$B:$C,2,FALSE)) | E33: 0 | G33: TOTAL EFECTIVO: | I33: =SUM(I23:I32) -> 0
A34: =IF(B34="","",VLOOKUP(B34,PROVEEDORES!$B:$C,2,FALSE)) | E34: 0 | G34: BASE: | I34: 0
A35: NIT | B35: PROVEEDOR | C35: CONCEPTO | D35: DESCRIPCIÓN | E35: BANCO | G35: TOTAL EFECTIVO MENOS LA BASE: | I35: =I33-I34 -> 0
A36: =IF(B36="","",VLOOKUP(B36,PROVEEDORES!$B:$C,2,FALSE)) | E36: 0
A37: =IF(B37="","",VLOOKUP(B37,PROVEEDORES!$B:$C,2,FALSE)) | E37: 0 | G37: ACUM. DE PROPINA TRANSFERENCIA: | I37: =+'10'!E13 -> 0
A38: =IF(B38="","",VLOOKUP(B38,PROVEEDORES!$B:$C,2,FALSE)) | E38: 0 | G38: ACUMULADO DE PROPINA EN BANCO: | I38: =+'10'!E14 -> 0
A39: =IF(B39="","",VLOOKUP(B39,PROVEEDORES!$B:$C,2,FALSE)) | E39: 0 | G39: ACUMULADO DE PROPINA POR EFECTIVO: | I39: =+'10'!E15 -> 0
A40: =IF(B40="","",VLOOKUP(B40,PROVEEDORES!$B:$C,2,FALSE)) | E40: 0 | G40: ACUMULADO DE TRANSFERENCIA: | I40: =+'10'!E16 -> 0
A41: =IF(B41="","",VLOOKUP(B41,PROVEEDORES!$B:$C,2,FALSE)) | E41: 0 | G41: ACUMULADO DE BANCO: | I41: =+'10'!E17 -> 0
A42: =IF(B42="","",VLOOKUP(B42,PROVEEDORES!$B:$C,2,FALSE)) | E42: 0 | G42: REAL DE BANCO: | I42: =+'10'!E18 -> 0
A43: =IF(B43="","",VLOOKUP(B43,PROVEEDORES!$B:$C,2,FALSE)) | E43: 0 | G43: EFECTIVO ANTERIOR: | I43: =+'10'!E19 -> 0
A44: =IF(B44="","",VLOOKUP(B44,PROVEEDORES!$B:$C,2,FALSE)) | E44: 0
A45: =IF(B45="","",VLOOKUP(B45,PROVEEDORES!$B:$C,2,FALSE)) | E45: 0
A46: =IF(B46="","",VLOOKUP(B46,PROVEEDORES!$B:$C,2,FALSE)) | E46: 0
A47: =IF(B47="","",VLOOKUP(B47,PROVEEDORES!$B:$C,2,FALSE)) | E47: 0
A48: =IF(B48="","",VLOOKUP(B48,PROVEEDORES!$B:$C,2,FALSE)) | E48: 0
A49: =IF(B49="","",VLOOKUP(B49,PROVEEDORES!$B:$C,2,FALSE)) | E49: 0
A50: =IF(B50="","",VLOOKUP(B50,PROVEEDORES!$B:$C,2,FALSE)) | E50: 0
A51: =IF(B51="","",VLOOKUP(B51,PROVEEDORES!$B:$C,2,FALSE)) | E51: 0
A52: =IF(B52="","",VLOOKUP(B52,PROVEEDORES!$B:$C,2,FALSE)) | E52: 0
A53: =IF(B53="","",VLOOKUP(B53,PROVEEDORES!$B:$C,2,FALSE)) | E53: 0
A54: =IF(B54="","",VLOOKUP(B54,PROVEEDORES!$B:$C,2,FALSE)) | E54: 0
A55: =IF(B55="","",VLOOKUP(B55,PROVEEDORES!$B:$C,2,FALSE)) | E55: 0
A56: EGRESO PROPINA | D56: INGRESO DE EFECTIVO
A57: PROPINA TRANSFERENCIA: | C57: 0 | E57: 0
A58: PROPINA BANCO: | C58: 0 | E58: 0
A59: PROPINA EFECTIVO: | C59: 0 | E59: 0

Sheet 12
A1: ='11'!A1+1 -> 12 | B1: =+'1'!B1 -> QUESO Y CAFÉ | D1: =+'11'!D1:E1+1 -> 46154 | G1: CUADRE DE CAJA MAÑANA | I1: CUADRE DE CAJA TARDE
A2: NIT | B2: PROVEEDOR | C2: CONCEPTO | D2: DESCRIPCIÓN | E2: VALOR | G2: PROP. TRANSF.: | H2: 0 | I2: PROP. TRANSF.: | J2: 0
A3: =IF(B3="","",VLOOKUP(B3,PROVEEDORES!$B:$C,2,FALSE)) | E3: 0 | G3: PROP. BANCO: | H3: 0 | I3: PROP. BANCO: | J3: 0
A4: =IF(B4="","",VLOOKUP(B4,PROVEEDORES!$B:$C,2,FALSE)) | E4: 0 | G4: PROP. EFECTIVO: | H4: 0 | I4: PROP. EFECTIVO: | J4: 0
A5: =IF(B5="","",VLOOKUP(B5,PROVEEDORES!$B:$C,2,FALSE)) | E5: 0 | G5: GASTO: | H5: 0 | I5: GASTO: | J5: 0
A6: =IF(B6="","",VLOOKUP(B6,PROVEEDORES!$B:$C,2,FALSE)) | E6: 0 | G6: TRANSFERENCIA: | H6: 0 | I6: TRANSFERENCIA: | J6: 0
A7: =IF(B7="","",VLOOKUP(B7,PROVEEDORES!$B:$C,2,FALSE)) | E7: 0 | G7: BANCO: | H7: 0 | I7: BANCO: | J7: 0
A8: =IF(B8="","",VLOOKUP(B8,PROVEEDORES!$B:$C,2,FALSE)) | E8: 0 | G8: EFECTIVO: | H8: 0 | I8: EFECTIVO: | J8: 0
A9: =IF(B9="","",VLOOKUP(B9,PROVEEDORES!$B:$C,2,FALSE)) | E9: 0 | G9: TOTAL: | H9: =SUM(H5:H8) -> 0 | I9: TOTAL: | J9: =SUM(J5:J8) -> 0
A10: =IF(B10="","",VLOOKUP(B10,PROVEEDORES!$B:$C,2,FALSE)) | E10: 0 | G10: DIFERENCIA: | H10: =+H11-H9 -> 0 | I10: DIFERENCIA: | J10: =+J11-J9 -> 0
A11: =IF(B11="","",VLOOKUP(B11,PROVEEDORES!$B:$C,2,FALSE)) | E11: 0 | G11: TOTAL VENTA: | H11: 0 | I11: TOTAL VENTA: | J11: 0
A12: =IF(B12="","",VLOOKUP(B12,PROVEEDORES!$B:$C,2,FALSE)) | E12: 0
A13: PROPINA TRANSFERENCIA: | C13: =SUM(H2,J2) -> 0 | D13: ACUM. PROPINA TRANFERENCIA: | E13: =SUM(C13,I37)-C57 -> 0 | G13: DIFERENCIA PLANILLA VS CUADRE DE CAJA | I13: =+C20-(SUM(H9,J9)) -> 0
A14: PROPINA POR BANCO: | C14: =SUM(H3,J3) -> 0 | D14: ACUM. PROPINA BANCO: | E14: =SUM(C14,I38)-C58 -> 0
A15: PROPINA EN EFECTIVO: | C15: =SUM(H4,J4) -> 0 | D15: ACUM. PROPINA EFECTIVO: | E15: =SUM(C15,I39)-C59 -> 0 | G15: FACTURAS EN EFECTIVO: | I15: 0
A16: TOTAL EGRESOS: | C16: =SUM(E3:E12) -> 0 | D16: ACUMULADO TRANSFERENCIA: | E16: =SUM(C17,I40) -> 0 | G16: EFECTIVO: | I16: 0
A17: TRANSFERENCIA: | C17: =SUM(H6,J6) -> 0 | D17: ACUMULADO BANCO: | E17: =SUM(C18,I41) -> 0 | G17: TOTAL EFECTIVO REAL ACTUAL: | I17: =SUM(I15,I16) -> 0
A18: BANCO: | C18: =SUM(H7,J7) -> 0 | D18: TOTAL BANCO: | E18: =SUM(C18,I42)-(SUM(E36:E55)) -> 0 | G18: DIFERENCIA: | I18: =+I19-I17 -> 0
A19: EFECTIVO: | C19: =SUM(H8,J8) -> 0 | D19: TOTAL EFECTIVO: | E19: =SUM(C19,E20,E57:E59)-(SUM(E23:E34)) -> 0 | G19: EFECTIVO ACTUAL PLANILLA: | I19: =E19 -> 0
A20: TOTAL VENTA: | C20: =SUM(C16:C19) -> 0 | D20: EFECTIVO ANTERIOR: | E20: =+I43 -> 0
A21: EGRESO DE CAJA MAYOR | G21: CONTEO DE EFECTIVO
A22: NIT | B22: PROVEEDOR | C22: CONCEPTO | D22: DESCRIPCIÓN | E22: EFECTIVO | G22: DENOMINACIÓN | H22: CANTIDAD | I22: EFECTIVO
A23: =IF(B23="","",VLOOKUP(B23,PROVEEDORES!$B:$C,2,FALSE)) | E23: 0 | G23: MONEDAS DE 100 | H23: 0 | I23: =100*H23 -> 0
A24: =IF(B24="","",VLOOKUP(B24,PROVEEDORES!$B:$C,2,FALSE)) | E24: 0 | G24: MONEDAS DE 200 | H24: 0 | I24: =200*H24 -> 0
A25: =IF(B25="","",VLOOKUP(B25,PROVEEDORES!$B:$C,2,FALSE)) | E25: 0 | G25: MONEDAS DE 500 | H25: 0 | I25: =500*H25 -> 0
A26: =IF(B26="","",VLOOKUP(B26,PROVEEDORES!$B:$C,2,FALSE)) | E26: 0 | G26: MONEDAS DE 1.000 | H26: 0 | I26: =1000*H26 -> 0
A27: =IF(B27="","",VLOOKUP(B27,PROVEEDORES!$B:$C,2,FALSE)) | E27: 0 | G27: BILLETES DE 2.000 | H27: 0 | I27: =2000*H27 -> 0
A28: =IF(B28="","",VLOOKUP(B28,PROVEEDORES!$B:$C,2,FALSE)) | E28: 0 | G28: BILLETES DE 5.000 | H28: 0 | I28: =5000*H28 -> 0
A29: =IF(B29="","",VLOOKUP(B29,PROVEEDORES!$B:$C,2,FALSE)) | E29: 0 | G29: BILLETES DE 10.000 | H29: 0 | I29: =10000*H29 -> 0
A30: =IF(B30="","",VLOOKUP(B30,PROVEEDORES!$B:$C,2,FALSE)) | E30: 0 | G30: BILLETES DE 20.000 | H30: 0 | I30: =20000*H30 -> 0
A31: =IF(B31="","",VLOOKUP(B31,PROVEEDORES!$B:$C,2,FALSE)) | E31: 0 | G31: BILLETES DE 50.000 | H31: 0 | I31: =50000*H31 -> 0
A32: =IF(B32="","",VLOOKUP(B32,PROVEEDORES!$B:$C,2,FALSE)) | E32: 0 | G32: BILLETES DE 100.000 | H32: 0 | I32: =100000*H32 -> 0
A33: =IF(B33="","",VLOOKUP(B33,PROVEEDORES!$B:$C,2,FALSE)) | E33: 0 | G33: TOTAL EFECTIVO: | I33: =SUM(I23:I32) -> 0
A34: =IF(B34="","",VLOOKUP(B34,PROVEEDORES!$B:$C,2,FALSE)) | E34: 0 | G34: BASE: | I34: 0
A35: NIT | B35: PROVEEDOR | C35: CONCEPTO | D35: DESCRIPCIÓN | E35: BANCO | G35: TOTAL EFECTIVO MENOS LA BASE: | I35: =I33-I34 -> 0
A36: =IF(B36="","",VLOOKUP(B36,PROVEEDORES!$B:$C,2,FALSE)) | E36: 0
A37: =IF(B37="","",VLOOKUP(B37,PROVEEDORES!$B:$C,2,FALSE)) | E37: 0 | G37: ACUM. DE PROPINA TRANSFERENCIA: | I37: =+'11'!E13 -> 0
A38: =IF(B38="","",VLOOKUP(B38,PROVEEDORES!$B:$C,2,FALSE)) | E38: 0 | G38: ACUMULADO DE PROPINA EN BANCO: | I38: =+'11'!E14 -> 0
A39: =IF(B39="","",VLOOKUP(B39,PROVEEDORES!$B:$C,2,FALSE)) | E39: 0 | G39: ACUMULADO DE PROPINA POR EFECTIVO: | I39: =+'11'!E15 -> 0
A40: =IF(B40="","",VLOOKUP(B40,PROVEEDORES!$B:$C,2,FALSE)) | E40: 0 | G40: ACUMULADO DE TRANSFERENCIA: | I40: =+'11'!E16 -> 0
A41: =IF(B41="","",VLOOKUP(B41,PROVEEDORES!$B:$C,2,FALSE)) | E41: 0 | G41: ACUMULADO DE BANCO: | I41: =+'11'!E17 -> 0
A42: =IF(B42="","",VLOOKUP(B42,PROVEEDORES!$B:$C,2,FALSE)) | E42: 0 | G42: REAL DE BANCO: | I42: =+'11'!E18 -> 0
A43: =IF(B43="","",VLOOKUP(B43,PROVEEDORES!$B:$C,2,FALSE)) | E43: 0 | G43: EFECTIVO ANTERIOR: | I43: =+'11'!E19 -> 0
A44: =IF(B44="","",VLOOKUP(B44,PROVEEDORES!$B:$C,2,FALSE)) | E44: 0
A45: =IF(B45="","",VLOOKUP(B45,PROVEEDORES!$B:$C,2,FALSE)) | E45: 0
A46: =IF(B46="","",VLOOKUP(B46,PROVEEDORES!$B:$C,2,FALSE)) | E46: 0
A47: =IF(B47="","",VLOOKUP(B47,PROVEEDORES!$B:$C,2,FALSE)) | E47: 0
A48: =IF(B48="","",VLOOKUP(B48,PROVEEDORES!$B:$C,2,FALSE)) | E48: 0
A49: =IF(B49="","",VLOOKUP(B49,PROVEEDORES!$B:$C,2,FALSE)) | E49: 0
A50: =IF(B50="","",VLOOKUP(B50,PROVEEDORES!$B:$C,2,FALSE)) | E50: 0
A51: =IF(B51="","",VLOOKUP(B51,PROVEEDORES!$B:$C,2,FALSE)) | E51: 0
A52: =IF(B52="","",VLOOKUP(B52,PROVEEDORES!$B:$C,2,FALSE)) | E52: 0
A53: =IF(B53="","",VLOOKUP(B53,PROVEEDORES!$B:$C,2,FALSE)) | E53: 0
A54: =IF(B54="","",VLOOKUP(B54,PROVEEDORES!$B:$C,2,FALSE)) | E54: 0
A55: =IF(B55="","",VLOOKUP(B55,PROVEEDORES!$B:$C,2,FALSE)) | E55: 0
A56: EGRESO PROPINA | D56: INGRESO DE EFECTIVO
A57: PROPINA TRANSFERENCIA: | C57: 0 | E57: 0
A58: PROPINA BANCO: | C58: 0 | E58: 0
A59: PROPINA EFECTIVO: | C59: 0 | E59: 0

Sheet 13
A1: ='12'!A1+1 -> 13 | B1: =+'1'!B1 -> QUESO Y CAFÉ | D1: =+'12'!D1:E1+1 -> 46155 | G1: CUADRE DE CAJA MAÑANA | I1: CUADRE DE CAJA TARDE
A2: NIT | B2: PROVEEDOR | C2: CONCEPTO | D2: DESCRIPCIÓN | E2: VALOR | G2: PROP. TRANSF.: | H2: 0 | I2: PROP. TRANSF.: | J2: 0
A3: =IF(B3="","",VLOOKUP(B3,PROVEEDORES!$B:$C,2,FALSE)) | E3: 0 | G3: PROP. BANCO: | H3: 0 | I3: PROP. BANCO: | J3: 0
A4: =IF(B4="","",VLOOKUP(B4,PROVEEDORES!$B:$C,2,FALSE)) | E4: 0 | G4: PROP. EFECTIVO: | H4: 0 | I4: PROP. EFECTIVO: | J4: 0
A5: =IF(B5="","",VLOOKUP(B5,PROVEEDORES!$B:$C,2,FALSE)) | E5: 0 | G5: GASTO: | H5: 0 | I5: GASTO: | J5: 0
A6: =IF(B6="","",VLOOKUP(B6,PROVEEDORES!$B:$C,2,FALSE)) | E6: 0 | G6: TRANSFERENCIA: | H6: 0 | I6: TRANSFERENCIA: | J6: 0
A7: =IF(B7="","",VLOOKUP(B7,PROVEEDORES!$B:$C,2,FALSE)) | E7: 0 | G7: BANCO: | H7: 0 | I7: BANCO: | J7: 0
A8: =IF(B8="","",VLOOKUP(B8,PROVEEDORES!$B:$C,2,FALSE)) | E8: 0 | G8: EFECTIVO: | H8: 0 | I8: EFECTIVO: | J8: 0
A9: =IF(B9="","",VLOOKUP(B9,PROVEEDORES!$B:$C,2,FALSE)) | E9: 0 | G9: TOTAL: | H9: =SUM(H5:H8) -> 0 | I9: TOTAL: | J9: =SUM(J5:J8) -> 0
A10: =IF(B10="","",VLOOKUP(B10,PROVEEDORES!$B:$C,2,FALSE)) | E10: 0 | G10: DIFERENCIA: | H10: =+H11-H9 -> 0 | I10: DIFERENCIA: | J10: =+J11-J9 -> 0
A11: =IF(B11="","",VLOOKUP(B11,PROVEEDORES!$B:$C,2,FALSE)) | E11: 0 | G11: TOTAL VENTA: | H11: 0 | I11: TOTAL VENTA: | J11: 0
A12: =IF(B12="","",VLOOKUP(B12,PROVEEDORES!$B:$C,2,FALSE)) | E12: 0
A13: PROPINA TRANSFERENCIA: | C13: =SUM(H2,J2) -> 0 | D13: ACUM. PROPINA TRANFERENCIA: | E13: =SUM(C13,I37)-C57 -> 0 | G13: DIFERENCIA PLANILLA VS CUADRE DE CAJA | I13: =+C20-(SUM(H9,J9)) -> 0
A14: PROPINA POR BANCO: | C14: =SUM(H3,J3) -> 0 | D14: ACUM. PROPINA BANCO: | E14: =SUM(C14,I38)-C58 -> 0
A15: PROPINA EN EFECTIVO: | C15: =SUM(H4,J4) -> 0 | D15: ACUM. PROPINA EFECTIVO: | E15: =SUM(C15,I39)-C59 -> 0 | G15: FACTURAS EN EFECTIVO: | I15: 0
A16: TOTAL EGRESOS: | C16: =SUM(E3:E12) -> 0 | D16: ACUMULADO TRANSFERENCIA: | E16: =SUM(C17,I40) -> 0 | G16: EFECTIVO: | I16: 0
A17: TRANSFERENCIA: | C17: =SUM(H6,J6) -> 0 | D17: ACUMULADO BANCO: | E17: =SUM(C18,I41) -> 0 | G17: TOTAL EFECTIVO REAL ACTUAL: | I17: =SUM(I15,I16) -> 0
A18: BANCO: | C18: =SUM(H7,J7) -> 0 | D18: TOTAL BANCO: | E18: =SUM(C18,I42)-(SUM(E36:E55)) -> 0 | G18: DIFERENCIA: | I18: =+I19-I17 -> 0
A19: EFECTIVO: | C19: =SUM(H8,J8) -> 0 | D19: TOTAL EFECTIVO: | E19: =SUM(C19,E20,E57:E59)-(SUM(E23:E34)) -> 0 | G19: EFECTIVO ACTUAL PLANILLA: | I19: =E19 -> 0
A20: TOTAL VENTA: | C20: =SUM(C16:C19) -> 0 | D20: EFECTIVO ANTERIOR: | E20: =+I43 -> 0
A21: EGRESO DE CAJA MAYOR | G21: CONTEO DE EFECTIVO
A22: NIT | B22: PROVEEDOR | C22: CONCEPTO | D22: DESCRIPCIÓN | E22: EFECTIVO | G22: DENOMINACIÓN | H22: CANTIDAD | I22: EFECTIVO
A23: =IF(B23="","",VLOOKUP(B23,PROVEEDORES!$B:$C,2,FALSE)) | E23: 0 | G23: MONEDAS DE 100 | H23: 0 | I23: =100*H23 -> 0
A24: =IF(B24="","",VLOOKUP(B24,PROVEEDORES!$B:$C,2,FALSE)) | E24: 0 | G24: MONEDAS DE 200 | H24: 0 | I24: =200*H24 -> 0
A25: =IF(B25="","",VLOOKUP(B25,PROVEEDORES!$B:$C,2,FALSE)) | E25: 0 | G25: MONEDAS DE 500 | H25: 0 | I25: =500*H25 -> 0
A26: =IF(B26="","",VLOOKUP(B26,PROVEEDORES!$B:$C,2,FALSE)) | E26: 0 | G26: MONEDAS DE 1.000 | H26: 0 | I26: =1000*H26 -> 0
A27: =IF(B27="","",VLOOKUP(B27,PROVEEDORES!$B:$C,2,FALSE)) | E27: 0 | G27: BILLETES DE 2.000 | H27: 0 | I27: =2000*H27 -> 0
A28: =IF(B28="","",VLOOKUP(B28,PROVEEDORES!$B:$C,2,FALSE)) | E28: 0 | G28: BILLETES DE 5.000 | H28: 0 | I28: =5000*H28 -> 0
A29: =IF(B29="","",VLOOKUP(B29,PROVEEDORES!$B:$C,2,FALSE)) | E29: 0 | G29: BILLETES DE 10.000 | H29: 0 | I29: =10000*H29 -> 0
A30: =IF(B30="","",VLOOKUP(B30,PROVEEDORES!$B:$C,2,FALSE)) | E30: 0 | G30: BILLETES DE 20.000 | H30: 0 | I30: =20000*H30 -> 0
A31: =IF(B31="","",VLOOKUP(B31,PROVEEDORES!$B:$C,2,FALSE)) | E31: 0 | G31: BILLETES DE 50.000 | H31: 0 | I31: =50000*H31 -> 0
A32: =IF(B32="","",VLOOKUP(B32,PROVEEDORES!$B:$C,2,FALSE)) | E32: 0 | G32: BILLETES DE 100.000 | H32: 0 | I32: =100000*H32 -> 0
A33: =IF(B33="","",VLOOKUP(B33,PROVEEDORES!$B:$C,2,FALSE)) | E33: 0 | G33: TOTAL EFECTIVO: | I33: =SUM(I23:I32) -> 0
A34: =IF(B34="","",VLOOKUP(B34,PROVEEDORES!$B:$C,2,FALSE)) | E34: 0 | G34: BASE: | I34: 0
A35: NIT | B35: PROVEEDOR | C35: CONCEPTO | D35: DESCRIPCIÓN | E35: BANCO | G35: TOTAL EFECTIVO MENOS LA BASE: | I35: =I33-I34 -> 0
A36: =IF(B36="","",VLOOKUP(B36,PROVEEDORES!$B:$C,2,FALSE)) | E36: 0
A37: =IF(B37="","",VLOOKUP(B37,PROVEEDORES!$B:$C,2,FALSE)) | E37: 0 | G37: ACUM. DE PROPINA TRANSFERENCIA: | I37: =+'12'!E13 -> 0
A38: =IF(B38="","",VLOOKUP(B38,PROVEEDORES!$B:$C,2,FALSE)) | E38: 0 | G38: ACUMULADO DE PROPINA EN BANCO: | I38: =+'12'!E14 -> 0
A39: =IF(B39="","",VLOOKUP(B39,PROVEEDORES!$B:$C,2,FALSE)) | E39: 0 | G39: ACUMULADO DE PROPINA POR EFECTIVO: | I39: =+'12'!E15 -> 0
A40: =IF(B40="","",VLOOKUP(B40,PROVEEDORES!$B:$C,2,FALSE)) | E40: 0 | G40: ACUMULADO DE TRANSFERENCIA: | I40: =+'12'!E16 -> 0
A41: =IF(B41="","",VLOOKUP(B41,PROVEEDORES!$B:$C,2,FALSE)) | E41: 0 | G41: ACUMULADO DE BANCO: | I41: =+'12'!E17 -> 0
A42: =IF(B42="","",VLOOKUP(B42,PROVEEDORES!$B:$C,2,FALSE)) | E42: 0 | G42: REAL DE BANCO: | I42: =+'12'!E18 -> 0
A43: =IF(B43="","",VLOOKUP(B43,PROVEEDORES!$B:$C,2,FALSE)) | E43: 0 | G43: EFECTIVO ANTERIOR: | I43: =+'12'!E19 -> 0
A44: =IF(B44="","",VLOOKUP(B44,PROVEEDORES!$B:$C,2,FALSE)) | E44: 0
A45: =IF(B45="","",VLOOKUP(B45,PROVEEDORES!$B:$C,2,FALSE)) | E45: 0
A46: =IF(B46="","",VLOOKUP(B46,PROVEEDORES!$B:$C,2,FALSE)) | E46: 0
A47: =IF(B47="","",VLOOKUP(B47,PROVEEDORES!$B:$C,2,FALSE)) | E47: 0
A48: =IF(B48="","",VLOOKUP(B48,PROVEEDORES!$B:$C,2,FALSE)) | E48: 0
A49: =IF(B49="","",VLOOKUP(B49,PROVEEDORES!$B:$C,2,FALSE)) | E49: 0
A50: =IF(B50="","",VLOOKUP(B50,PROVEEDORES!$B:$C,2,FALSE)) | E50: 0
A51: =IF(B51="","",VLOOKUP(B51,PROVEEDORES!$B:$C,2,FALSE)) | E51: 0
A52: =IF(B52="","",VLOOKUP(B52,PROVEEDORES!$B:$C,2,FALSE)) | E52: 0
A53: =IF(B53="","",VLOOKUP(B53,PROVEEDORES!$B:$C,2,FALSE)) | E53: 0
A54: =IF(B54="","",VLOOKUP(B54,PROVEEDORES!$B:$C,2,FALSE)) | E54: 0
A55: =IF(B55="","",VLOOKUP(B55,PROVEEDORES!$B:$C,2,FALSE)) | E55: 0
A56: EGRESO PROPINA | D56: INGRESO DE EFECTIVO
A57: PROPINA TRANSFERENCIA: | C57: 0 | E57: 0
A58: PROPINA BANCO: | C58: 0 | E58: 0
A59: PROPINA EFECTIVO: | C59: 0 | E59: 0

Sheet 14
A1: ='13'!A1+1 -> 14 | B1: =+'1'!B1 -> QUESO Y CAFÉ | D1: =+'13'!D1:E1+1 -> 46156 | G1: CUADRE DE CAJA MAÑANA | I1: CUADRE DE CAJA TARDE
A2: NIT | B2: PROVEEDOR | C2: CONCEPTO | D2: DESCRIPCIÓN | E2: VALOR | G2: PROP. TRANSF.: | H2: 0 | I2: PROP. TRANSF.: | J2: 0
A3: =IF(B3="","",VLOOKUP(B3,PROVEEDORES!$B:$C,2,FALSE)) | E3: 0 | G3: PROP. BANCO: | H3: 0 | I3: PROP. BANCO: | J3: 0
A4: =IF(B4="","",VLOOKUP(B4,PROVEEDORES!$B:$C,2,FALSE)) | E4: 0 | G4: PROP. EFECTIVO: | H4: 0 | I4: PROP. EFECTIVO: | J4: 0
A5: =IF(B5="","",VLOOKUP(B5,PROVEEDORES!$B:$C,2,FALSE)) | E5: 0 | G5: GASTO: | H5: 0 | I5: GASTO: | J5: 0
A6: =IF(B6="","",VLOOKUP(B6,PROVEEDORES!$B:$C,2,FALSE)) | E6: 0 | G6: TRANSFERENCIA: | H6: 0 | I6: TRANSFERENCIA: | J6: 0
A7: =IF(B7="","",VLOOKUP(B7,PROVEEDORES!$B:$C,2,FALSE)) | E7: 0 | G7: BANCO: | H7: 0 | I7: BANCO: | J7: 0
A8: =IF(B8="","",VLOOKUP(B8,PROVEEDORES!$B:$C,2,FALSE)) | E8: 0 | G8: EFECTIVO: | H8: 0 | I8: EFECTIVO: | J8: 0
A9: =IF(B9="","",VLOOKUP(B9,PROVEEDORES!$B:$C,2,FALSE)) | E9: 0 | G9: TOTAL: | H9: =SUM(H5:H8) -> 0 | I9: TOTAL: | J9: =SUM(J5:J8) -> 0
A10: =IF(B10="","",VLOOKUP(B10,PROVEEDORES!$B:$C,2,FALSE)) | E10: 0 | G10: DIFERENCIA: | H10: =+H11-H9 -> 0 | I10: DIFERENCIA: | J10: =+J11-J9 -> 0
A11: =IF(B11="","",VLOOKUP(B11,PROVEEDORES!$B:$C,2,FALSE)) | E11: 0 | G11: TOTAL VENTA: | H11: 0 | I11: TOTAL VENTA: | J11: 0
A12: =IF(B12="","",VLOOKUP(B12,PROVEEDORES!$B:$C,2,FALSE)) | E12: 0
A13: PROPINA TRANSFERENCIA: | C13: =SUM(H2,J2) -> 0 | D13: ACUM. PROPINA TRANFERENCIA: | E13: =SUM(C13,I37)-C57 -> 0 | G13: DIFERENCIA PLANILLA VS CUADRE DE CAJA | I13: =+C20-(SUM(H9,J9)) -> 0
A14: PROPINA POR BANCO: | C14: =SUM(H3,J3) -> 0 | D14: ACUM. PROPINA BANCO: | E14: =SUM(C14,I38)-C58 -> 0
A15: PROPINA EN EFECTIVO: | C15: =SUM(H4,J4) -> 0 | D15: ACUM. PROPINA EFECTIVO: | E15: =SUM(C15,I39)-C59 -> 0 | G15: FACTURAS EN EFECTIVO: | I15: 0
A16: TOTAL EGRESOS: | C16: =SUM(E3:E12) -> 0 | D16: ACUMULADO TRANSFERENCIA: | E16: =SUM(C17,I40) -> 0 | G16: EFECTIVO: | I16: 0
A17: TRANSFERENCIA: | C17: =SUM(H6,J6) -> 0 | D17: ACUMULADO BANCO: | E17: =SUM(C18,I41) -> 0 | G17: TOTAL EFECTIVO REAL ACTUAL: | I17: =SUM(I15,I16) -> 0
A18: BANCO: | C18: =SUM(H7,J7) -> 0 | D18: TOTAL BANCO: | E18: =SUM(C18,I42)-(SUM(E36:E55)) -> 0 | G18: DIFERENCIA: | I18: =+I19-I17 -> 0
A19: EFECTIVO: | C19: =SUM(H8,J8) -> 0 | D19: TOTAL EFECTIVO: | E19: =SUM(C19,E20,E57:E59)-(SUM(E23:E34)) -> 0 | G19: EFECTIVO ACTUAL PLANILLA: | I19: =E19 -> 0
A20: TOTAL VENTA: | C20: =SUM(C16:C19) -> 0 | D20: EFECTIVO ANTERIOR: | E20: =+I43 -> 0
A21: EGRESO DE CAJA MAYOR | G21: CONTEO DE EFECTIVO
A22: NIT | B22: PROVEEDOR | C22: CONCEPTO | D22: DESCRIPCIÓN | E22: EFECTIVO | G22: DENOMINACIÓN | H22: CANTIDAD | I22: EFECTIVO
A23: =IF(B23="","",VLOOKUP(B23,PROVEEDORES!$B:$C,2,FALSE)) | E23: 0 | G23: MONEDAS DE 100 | H23: 0 | I23: =100*H23 -> 0
A24: =IF(B24="","",VLOOKUP(B24,PROVEEDORES!$B:$C,2,FALSE)) | E24: 0 | G24: MONEDAS DE 200 | H24: 0 | I24: =200*H24 -> 0
A25: =IF(B25="","",VLOOKUP(B25,PROVEEDORES!$B:$C,2,FALSE)) | E25: 0 | G25: MONEDAS DE 500 | H25: 0 | I25: =500*H25 -> 0
A26: =IF(B26="","",VLOOKUP(B26,PROVEEDORES!$B:$C,2,FALSE)) | E26: 0 | G26: MONEDAS DE 1.000 | H26: 0 | I26: =1000*H26 -> 0
A27: =IF(B27="","",VLOOKUP(B27,PROVEEDORES!$B:$C,2,FALSE)) | E27: 0 | G27: BILLETES DE 2.000 | H27: 0 | I27: =2000*H27 -> 0
A28: =IF(B28="","",VLOOKUP(B28,PROVEEDORES!$B:$C,2,FALSE)) | E28: 0 | G28: BILLETES DE 5.000 | H28: 0 | I28: =5000*H28 -> 0
A29: =IF(B29="","",VLOOKUP(B29,PROVEEDORES!$B:$C,2,FALSE)) | E29: 0 | G29: BILLETES DE 10.000 | H29: 0 | I29: =10000*H29 -> 0
A30: =IF(B30="","",VLOOKUP(B30,PROVEEDORES!$B:$C,2,FALSE)) | E30: 0 | G30: BILLETES DE 20.000 | H30: 0 | I30: =20000*H30 -> 0
A31: =IF(B31="","",VLOOKUP(B31,PROVEEDORES!$B:$C,2,FALSE)) | E31: 0 | G31: BILLETES DE 50.000 | H31: 0 | I31: =50000*H31 -> 0
A32: =IF(B32="","",VLOOKUP(B32,PROVEEDORES!$B:$C,2,FALSE)) | E32: 0 | G32: BILLETES DE 100.000 | H32: 0 | I32: =100000*H32 -> 0
A33: =IF(B33="","",VLOOKUP(B33,PROVEEDORES!$B:$C,2,FALSE)) | E33: 0 | G33: TOTAL EFECTIVO: | I33: =SUM(I23:I32) -> 0
A34: =IF(B34="","",VLOOKUP(B34,PROVEEDORES!$B:$C,2,FALSE)) | E34: 0 | G34: BASE: | I34: 0
A35: NIT | B35: PROVEEDOR | C35: CONCEPTO | D35: DESCRIPCIÓN | E35: BANCO | G35: TOTAL EFECTIVO MENOS LA BASE: | I35: =I33-I34 -> 0
A36: =IF(B36="","",VLOOKUP(B36,PROVEEDORES!$B:$C,2,FALSE)) | E36: 0
A37: =IF(B37="","",VLOOKUP(B37,PROVEEDORES!$B:$C,2,FALSE)) | E37: 0 | G37: ACUM. DE PROPINA TRANSFERENCIA: | I37: =+'13'!E13 -> 0
A38: =IF(B38="","",VLOOKUP(B38,PROVEEDORES!$B:$C,2,FALSE)) | E38: 0 | G38: ACUMULADO DE PROPINA EN BANCO: | I38: =+'13'!E14 -> 0
A39: =IF(B39="","",VLOOKUP(B39,PROVEEDORES!$B:$C,2,FALSE)) | E39: 0 | G39: ACUMULADO DE PROPINA POR EFECTIVO: | I39: =+'13'!E15 -> 0
A40: =IF(B40="","",VLOOKUP(B40,PROVEEDORES!$B:$C,2,FALSE)) | E40: 0 | G40: ACUMULADO DE TRANSFERENCIA: | I40: =+'13'!E16 -> 0
A41: =IF(B41="","",VLOOKUP(B41,PROVEEDORES!$B:$C,2,FALSE)) | E41: 0 | G41: ACUMULADO DE BANCO: | I41: =+'13'!E17 -> 0
A42: =IF(B42="","",VLOOKUP(B42,PROVEEDORES!$B:$C,2,FALSE)) | E42: 0 | G42: REAL DE BANCO: | I42: =+'13'!E18 -> 0
A43: =IF(B43="","",VLOOKUP(B43,PROVEEDORES!$B:$C,2,FALSE)) | E43: 0 | G43: EFECTIVO ANTERIOR: | I43: =+'13'!E19 -> 0
A44: =IF(B44="","",VLOOKUP(B44,PROVEEDORES!$B:$C,2,FALSE)) | E44: 0
A45: =IF(B45="","",VLOOKUP(B45,PROVEEDORES!$B:$C,2,FALSE)) | E45: 0
A46: =IF(B46="","",VLOOKUP(B46,PROVEEDORES!$B:$C,2,FALSE)) | E46: 0
A47: =IF(B47="","",VLOOKUP(B47,PROVEEDORES!$B:$C,2,FALSE)) | E47: 0
A48: =IF(B48="","",VLOOKUP(B48,PROVEEDORES!$B:$C,2,FALSE)) | E48: 0
A49: =IF(B49="","",VLOOKUP(B49,PROVEEDORES!$B:$C,2,FALSE)) | E49: 0
A50: =IF(B50="","",VLOOKUP(B50,PROVEEDORES!$B:$C,2,FALSE)) | E50: 0
A51: =IF(B51="","",VLOOKUP(B51,PROVEEDORES!$B:$C,2,FALSE)) | E51: 0
A52: =IF(B52="","",VLOOKUP(B52,PROVEEDORES!$B:$C,2,FALSE)) | E52: 0
A53: =IF(B53="","",VLOOKUP(B53,PROVEEDORES!$B:$C,2,FALSE)) | E53: 0
A54: =IF(B54="","",VLOOKUP(B54,PROVEEDORES!$B:$C,2,FALSE)) | E54: 0
A55: =IF(B55="","",VLOOKUP(B55,PROVEEDORES!$B:$C,2,FALSE)) | E55: 0
A56: EGRESO PROPINA | D56: INGRESO DE EFECTIVO
A57: PROPINA TRANSFERENCIA: | C57: 0 | E57: 0
A58: PROPINA BANCO: | C58: 0 | E58: 0
A59: PROPINA EFECTIVO: | C59: 0 | E59: 0

Sheet 15
A1: ='14'!A1+1 -> 15 | B1: =+'1'!B1 -> QUESO Y CAFÉ | D1: =+'14'!D1:E1+1 -> 46157 | G1: CUADRE DE CAJA MAÑANA | I1: CUADRE DE CAJA TARDE
A2: NIT | B2: PROVEEDOR | C2: CONCEPTO | D2: DESCRIPCIÓN | E2: VALOR | G2: PROP. TRANSF.: | H2: 0 | I2: PROP. TRANSF.: | J2: 0
A3: =IF(B3="","",VLOOKUP(B3,PROVEEDORES!$B:$C,2,FALSE)) | E3: 0 | G3: PROP. BANCO: | H3: 0 | I3: PROP. BANCO: | J3: 0
A4: =IF(B4="","",VLOOKUP(B4,PROVEEDORES!$B:$C,2,FALSE)) | E4: 0 | G4: PROP. EFECTIVO: | H4: 0 | I4: PROP. EFECTIVO: | J4: 0
A5: =IF(B5="","",VLOOKUP(B5,PROVEEDORES!$B:$C,2,FALSE)) | E5: 0 | G5: GASTO: | H5: 0 | I5: GASTO: | J5: 0
A6: =IF(B6="","",VLOOKUP(B6,PROVEEDORES!$B:$C,2,FALSE)) | E6: 0 | G6: TRANSFERENCIA: | H6: 0 | I6: TRANSFERENCIA: | J6: 0
A7: =IF(B7="","",VLOOKUP(B7,PROVEEDORES!$B:$C,2,FALSE)) | E7: 0 | G7: BANCO: | H7: 0 | I7: BANCO: | J7: 0
A8: =IF(B8="","",VLOOKUP(B8,PROVEEDORES!$B:$C,2,FALSE)) | E8: 0 | G8: EFECTIVO: | H8: 0 | I8: EFECTIVO: | J8: 0
A9: =IF(B9="","",VLOOKUP(B9,PROVEEDORES!$B:$C,2,FALSE)) | E9: 0 | G9: TOTAL: | H9: =SUM(H5:H8) -> 0 | I9: TOTAL: | J9: =SUM(J5:J8) -> 0
A10: =IF(B10="","",VLOOKUP(B10,PROVEEDORES!$B:$C,2,FALSE)) | E10: 0 | G10: DIFERENCIA: | H10: =+H11-H9 -> 0 | I10: DIFERENCIA: | J10: =+J11-J9 -> 0
A11: =IF(B11="","",VLOOKUP(B11,PROVEEDORES!$B:$C,2,FALSE)) | E11: 0 | G11: TOTAL VENTA: | H11: 0 | I11: TOTAL VENTA: | J11: 0
A12: =IF(B12="","",VLOOKUP(B12,PROVEEDORES!$B:$C,2,FALSE)) | E12: 0
A13: PROPINA TRANSFERENCIA: | C13: =SUM(H2,J2) -> 0 | D13: ACUM. PROPINA TRANFERENCIA: | E13: =SUM(C13,I37)-C57 -> 0 | G13: DIFERENCIA PLANILLA VS CUADRE DE CAJA | I13: =+C20-(SUM(H9,J9)) -> 0
A14: PROPINA POR BANCO: | C14: =SUM(H3,J3) -> 0 | D14: ACUM. PROPINA BANCO: | E14: =SUM(C14,I38)-C58 -> 0
A15: PROPINA EN EFECTIVO: | C15: =SUM(H4,J4) -> 0 | D15: ACUM. PROPINA EFECTIVO: | E15: =SUM(C15,I39)-C59 -> 0 | G15: FACTURAS EN EFECTIVO: | I15: 0
A16: TOTAL EGRESOS: | C16: =SUM(E3:E12) -> 0 | D16: ACUMULADO TRANSFERENCIA: | E16: =SUM(C17,I40) -> 0 | G16: EFECTIVO: | I16: 0
A17: TRANSFERENCIA: | C17: =SUM(H6,J6) -> 0 | D17: ACUMULADO BANCO: | E17: =SUM(C18,I41) -> 0 | G17: TOTAL EFECTIVO REAL ACTUAL: | I17: =SUM(I15,I16) -> 0
A18: BANCO: | C18: =SUM(H7,J7) -> 0 | D18: TOTAL BANCO: | E18: =SUM(C18,I42)-(SUM(E36:E55)) -> 0 | G18: DIFERENCIA: | I18: =+I19-I17 -> 0
A19: EFECTIVO: | C19: =SUM(H8,J8) -> 0 | D19: TOTAL EFECTIVO: | E19: =SUM(C19,E20,E57:E59)-(SUM(E23:E34)) -> 0 | G19: EFECTIVO ACTUAL PLANILLA: | I19: =E19 -> 0
A20: TOTAL VENTA: | C20: =SUM(C16:C19) -> 0 | D20: EFECTIVO ANTERIOR: | E20: =+I43 -> 0
A21: EGRESO DE CAJA MAYOR | G21: CONTEO DE EFECTIVO
A22: NIT | B22: PROVEEDOR | C22: CONCEPTO | D22: DESCRIPCIÓN | E22: EFECTIVO | G22: DENOMINACIÓN | H22: CANTIDAD | I22: EFECTIVO
A23: =IF(B23="","",VLOOKUP(B23,PROVEEDORES!$B:$C,2,FALSE)) | E23: 0 | G23: MONEDAS DE 100 | H23: 0 | I23: =100*H23 -> 0
A24: =IF(B24="","",VLOOKUP(B24,PROVEEDORES!$B:$C,2,FALSE)) | E24: 0 | G24: MONEDAS DE 200 | H24: 0 | I24: =200*H24 -> 0
A25: =IF(B25="","",VLOOKUP(B25,PROVEEDORES!$B:$C,2,FALSE)) | E25: 0 | G25: MONEDAS DE 500 | H25: 0 | I25: =500*H25 -> 0
A26: =IF(B26="","",VLOOKUP(B26,PROVEEDORES!$B:$C,2,FALSE)) | E26: 0 | G26: MONEDAS DE 1.000 | H26: 0 | I26: =1000*H26 -> 0
A27: =IF(B27="","",VLOOKUP(B27,PROVEEDORES!$B:$C,2,FALSE)) | E27: 0 | G27: BILLETES DE 2.000 | H27: 0 | I27: =2000*H27 -> 0
A28: =IF(B28="","",VLOOKUP(B28,PROVEEDORES!$B:$C,2,FALSE)) | E28: 0 | G28: BILLETES DE 5.000 | H28: 0 | I28: =5000*H28 -> 0
A29: =IF(B29="","",VLOOKUP(B29,PROVEEDORES!$B:$C,2,FALSE)) | E29: 0 | G29: BILLETES DE 10.000 | H29: 0 | I29: =10000*H29 -> 0
A30: =IF(B30="","",VLOOKUP(B30,PROVEEDORES!$B:$C,2,FALSE)) | E30: 0 | G30: BILLETES DE 20.000 | H30: 0 | I30: =20000*H30 -> 0
A31: =IF(B31="","",VLOOKUP(B31,PROVEEDORES!$B:$C,2,FALSE)) | E31: 0 | G31: BILLETES DE 50.000 | H31: 0 | I31: =50000*H31 -> 0
A32: =IF(B32="","",VLOOKUP(B32,PROVEEDORES!$B:$C,2,FALSE)) | E32: 0 | G32: BILLETES DE 100.000 | H32: 0 | I32: =100000*H32 -> 0
A33: =IF(B33="","",VLOOKUP(B33,PROVEEDORES!$B:$C,2,FALSE)) | E33: 0 | G33: TOTAL EFECTIVO: | I33: =SUM(I23:I32) -> 0
A34: =IF(B34="","",VLOOKUP(B34,PROVEEDORES!$B:$C,2,FALSE)) | E34: 0 | G34: BASE: | I34: 0
A35: NIT | B35: PROVEEDOR | C35: CONCEPTO | D35: DESCRIPCIÓN | E35: BANCO | G35: TOTAL EFECTIVO MENOS LA BASE: | I35: =I33-I34 -> 0
A36: =IF(B36="","",VLOOKUP(B36,PROVEEDORES!$B:$C,2,FALSE)) | E36: 0
A37: =IF(B37="","",VLOOKUP(B37,PROVEEDORES!$B:$C,2,FALSE)) | E37: 0 | G37: ACUM. DE PROPINA TRANSFERENCIA: | I37: =+'14'!E13 -> 0
A38: =IF(B38="","",VLOOKUP(B38,PROVEEDORES!$B:$C,2,FALSE)) | E38: 0 | G38: ACUMULADO DE PROPINA EN BANCO: | I38: =+'14'!E14 -> 0
A39: =IF(B39="","",VLOOKUP(B39,PROVEEDORES!$B:$C,2,FALSE)) | E39: 0 | G39: ACUMULADO DE PROPINA POR EFECTIVO: | I39: =+'14'!E15 -> 0
A40: =IF(B40="","",VLOOKUP(B40,PROVEEDORES!$B:$C,2,FALSE)) | E40: 0 | G40: ACUMULADO DE TRANSFERENCIA: | I40: =+'14'!E16 -> 0
A41: =IF(B41="","",VLOOKUP(B41,PROVEEDORES!$B:$C,2,FALSE)) | E41: 0 | G41: ACUMULADO DE BANCO: | I41: =+'14'!E17 -> 0
A42: =IF(B42="","",VLOOKUP(B42,PROVEEDORES!$B:$C,2,FALSE)) | E42: 0 | G42: REAL DE BANCO: | I42: =+'14'!E18 -> 0
A43: =IF(B43="","",VLOOKUP(B43,PROVEEDORES!$B:$C,2,FALSE)) | E43: 0 | G43: EFECTIVO ANTERIOR: | I43: =+'14'!E19 -> 0
A44: =IF(B44="","",VLOOKUP(B44,PROVEEDORES!$B:$C,2,FALSE)) | E44: 0
A45: =IF(B45="","",VLOOKUP(B45,PROVEEDORES!$B:$C,2,FALSE)) | E45: 0
A46: =IF(B46="","",VLOOKUP(B46,PROVEEDORES!$B:$C,2,FALSE)) | E46: 0
A47: =IF(B47="","",VLOOKUP(B47,PROVEEDORES!$B:$C,2,FALSE)) | E47: 0
A48: =IF(B48="","",VLOOKUP(B48,PROVEEDORES!$B:$C,2,FALSE)) | E48: 0
A49: =IF(B49="","",VLOOKUP(B49,PROVEEDORES!$B:$C,2,FALSE)) | E49: 0
A50: =IF(B50="","",VLOOKUP(B50,PROVEEDORES!$B:$C,2,FALSE)) | E50: 0
A51: =IF(B51="","",VLOOKUP(B51,PROVEEDORES!$B:$C,2,FALSE)) | E51: 0
A52: =IF(B52="","",VLOOKUP(B52,PROVEEDORES!$B:$C,2,FALSE)) | E52: 0
A53: =IF(B53="","",VLOOKUP(B53,PROVEEDORES!$B:$C,2,FALSE)) | E53: 0
A54: =IF(B54="","",VLOOKUP(B54,PROVEEDORES!$B:$C,2,FALSE)) | E54: 0
A55: =IF(B55="","",VLOOKUP(B55,PROVEEDORES!$B:$C,2,FALSE)) | E55: 0
A56: EGRESO PROPINA | D56: INGRESO DE EFECTIVO
A57: PROPINA TRANSFERENCIA: | C57: 0 | E57: 0
A58: PROPINA BANCO: | C58: 0 | E58: 0
A59: PROPINA EFECTIVO: | C59: 0 | E59: 0

Sheet 16
A1: ='15'!A1+1 -> 16 | B1: =+'1'!B1 -> QUESO Y CAFÉ | D1: =+'15'!D1:E1+1 -> 46158 | G1: CUADRE DE CAJA MAÑANA | I1: CUADRE DE CAJA TARDE
A2: NIT | B2: PROVEEDOR | C2: CONCEPTO | D2: DESCRIPCIÓN | E2: VALOR | G2: PROP. TRANSF.: | H2: 0 | I2: PROP. TRANSF.: | J2: 0
A3: =IF(B3="","",VLOOKUP(B3,PROVEEDORES!$B:$C,2,FALSE)) | E3: 0 | G3: PROP. BANCO: | H3: 0 | I3: PROP. BANCO: | J3: 0
A4: =IF(B4="","",VLOOKUP(B4,PROVEEDORES!$B:$C,2,FALSE)) | E4: 0 | G4: PROP. EFECTIVO: | H4: 0 | I4: PROP. EFECTIVO: | J4: 0
A5: =IF(B5="","",VLOOKUP(B5,PROVEEDORES!$B:$C,2,FALSE)) | E5: 0 | G5: GASTO: | H5: 0 | I5: GASTO: | J5: 0
A6: =IF(B6="","",VLOOKUP(B6,PROVEEDORES!$B:$C,2,FALSE)) | E6: 0 | G6: TRANSFERENCIA: | H6: 0 | I6: TRANSFERENCIA: | J6: 0
A7: =IF(B7="","",VLOOKUP(B7,PROVEEDORES!$B:$C,2,FALSE)) | E7: 0 | G7: BANCO: | H7: 0 | I7: BANCO: | J7: 0
A8: =IF(B8="","",VLOOKUP(B8,PROVEEDORES!$B:$C,2,FALSE)) | E8: 0 | G8: EFECTIVO: | H8: 0 | I8: EFECTIVO: | J8: 0
A9: =IF(B9="","",VLOOKUP(B9,PROVEEDORES!$B:$C,2,FALSE)) | E9: 0 | G9: TOTAL: | H9: =SUM(H5:H8) -> 0 | I9: TOTAL: | J9: =SUM(J5:J8) -> 0
A10: =IF(B10="","",VLOOKUP(B10,PROVEEDORES!$B:$C,2,FALSE)) | E10: 0 | G10: DIFERENCIA: | H10: =+H11-H9 -> 0 | I10: DIFERENCIA: | J10: =+J11-J9 -> 0
A11: =IF(B11="","",VLOOKUP(B11,PROVEEDORES!$B:$C,2,FALSE)) | E11: 0 | G11: TOTAL VENTA: | H11: 0 | I11: TOTAL VENTA: | J11: 0
A12: =IF(B12="","",VLOOKUP(B12,PROVEEDORES!$B:$C,2,FALSE)) | E12: 0
A13: PROPINA TRANSFERENCIA: | C13: =SUM(H2,J2) -> 0 | D13: ACUM. PROPINA TRANFERENCIA: | E13: =SUM(C13,I37)-C57 -> 0 | G13: DIFERENCIA PLANILLA VS CUADRE DE CAJA | I13: =+C20-(SUM(H9,J9)) -> 0
A14: PROPINA POR BANCO: | C14: =SUM(H3,J3) -> 0 | D14: ACUM. PROPINA BANCO: | E14: =SUM(C14,I38)-C58 -> 0
A15: PROPINA EN EFECTIVO: | C15: =SUM(H4,J4) -> 0 | D15: ACUM. PROPINA EFECTIVO: | E15: =SUM(C15,I39)-C59 -> 0 | G15: FACTURAS EN EFECTIVO: | I15: 0
A16: TOTAL EGRESOS: | C16: =SUM(E3:E12) -> 0 | D16: ACUMULADO TRANSFERENCIA: | E16: =SUM(C17,I40) -> 0 | G16: EFECTIVO: | I16: 0
A17: TRANSFERENCIA: | C17: =SUM(H6,J6) -> 0 | D17: ACUMULADO BANCO: | E17: =SUM(C18,I41) -> 0 | G17: TOTAL EFECTIVO REAL ACTUAL: | I17: =SUM(I15,I16) -> 0
A18: BANCO: | C18: =SUM(H7,J7) -> 0 | D18: TOTAL BANCO: | E18: =SUM(C18,I42)-(SUM(E36:E55)) -> 0 | G18: DIFERENCIA: | I18: =+I19-I17 -> 0
A19: EFECTIVO: | C19: =SUM(H8,J8) -> 0 | D19: TOTAL EFECTIVO: | E19: =SUM(C19,E20,E57:E59)-(SUM(E23:E34)) -> 0 | G19: EFECTIVO ACTUAL PLANILLA: | I19: =E19 -> 0
A20: TOTAL VENTA: | C20: =SUM(C16:C19) -> 0 | D20: EFECTIVO ANTERIOR: | E20: =+I43 -> 0
A21: EGRESO DE CAJA MAYOR | G21: CONTEO DE EFECTIVO
A22: NIT | B22: PROVEEDOR | C22: CONCEPTO | D22: DESCRIPCIÓN | E22: EFECTIVO | G22: DENOMINACIÓN | H22: CANTIDAD | I22: EFECTIVO
A23: =IF(B23="","",VLOOKUP(B23,PROVEEDORES!$B:$C,2,FALSE)) | E23: 0 | G23: MONEDAS DE 100 | H23: 0 | I23: =100*H23 -> 0
A24: =IF(B24="","",VLOOKUP(B24,PROVEEDORES!$B:$C,2,FALSE)) | E24: 0 | G24: MONEDAS DE 200 | H24: 0 | I24: =200*H24 -> 0
A25: =IF(B25="","",VLOOKUP(B25,PROVEEDORES!$B:$C,2,FALSE)) | E25: 0 | G25: MONEDAS DE 500 | H25: 0 | I25: =500*H25 -> 0
A26: =IF(B26="","",VLOOKUP(B26,PROVEEDORES!$B:$C,2,FALSE)) | E26: 0 | G26: MONEDAS DE 1.000 | H26: 0 | I26: =1000*H26 -> 0
A27: =IF(B27="","",VLOOKUP(B27,PROVEEDORES!$B:$C,2,FALSE)) | E27: 0 | G27: BILLETES DE 2.000 | H27: 0 | I27: =2000*H27 -> 0
A28: =IF(B28="","",VLOOKUP(B28,PROVEEDORES!$B:$C,2,FALSE)) | E28: 0 | G28: BILLETES DE 5.000 | H28: 0 | I28: =5000*H28 -> 0
A29: =IF(B29="","",VLOOKUP(B29,PROVEEDORES!$B:$C,2,FALSE)) | E29: 0 | G29: BILLETES DE 10.000 | H29: 0 | I29: =10000*H29 -> 0
A30: =IF(B30="","",VLOOKUP(B30,PROVEEDORES!$B:$C,2,FALSE)) | E30: 0 | G30: BILLETES DE 20.000 | H30: 0 | I30: =20000*H30 -> 0
A31: =IF(B31="","",VLOOKUP(B31,PROVEEDORES!$B:$C,2,FALSE)) | E31: 0 | G31: BILLETES DE 50.000 | H31: 0 | I31: =50000*H31 -> 0
A32: =IF(B32="","",VLOOKUP(B32,PROVEEDORES!$B:$C,2,FALSE)) | E32: 0 | G32: BILLETES DE 100.000 | H32: 0 | I32: =100000*H32 -> 0
A33: =IF(B33="","",VLOOKUP(B33,PROVEEDORES!$B:$C,2,FALSE)) | E33: 0 | G33: TOTAL EFECTIVO: | I33: =SUM(I23:I32) -> 0
A34: =IF(B34="","",VLOOKUP(B34,PROVEEDORES!$B:$C,2,FALSE)) | E34: 0 | G34: BASE: | I34: 0
A35: NIT | B35: PROVEEDOR | C35: CONCEPTO | D35: DESCRIPCIÓN | E35: BANCO | G35: TOTAL EFECTIVO MENOS LA BASE: | I35: =I33-I34 -> 0
A36: =IF(B36="","",VLOOKUP(B36,PROVEEDORES!$B:$C,2,FALSE)) | E36: 0
A37: =IF(B37="","",VLOOKUP(B37,PROVEEDORES!$B:$C,2,FALSE)) | E37: 0 | G37: ACUM. DE PROPINA TRANSFERENCIA: | I37: =+'15'!E13 -> 0
A38: =IF(B38="","",VLOOKUP(B38,PROVEEDORES!$B:$C,2,FALSE)) | E38: 0 | G38: ACUMULADO DE PROPINA EN BANCO: | I38: =+'15'!E14 -> 0
A39: =IF(B39="","",VLOOKUP(B39,PROVEEDORES!$B:$C,2,FALSE)) | E39: 0 | G39: ACUMULADO DE PROPINA POR EFECTIVO: | I39: =+'15'!E15 -> 0
A40: =IF(B40="","",VLOOKUP(B40,PROVEEDORES!$B:$C,2,FALSE)) | E40: 0 | G40: ACUMULADO DE TRANSFERENCIA: | I40: =+'15'!E16 -> 0
A41: =IF(B41="","",VLOOKUP(B41,PROVEEDORES!$B:$C,2,FALSE)) | E41: 0 | G41: ACUMULADO DE BANCO: | I41: =+'15'!E17 -> 0
A42: =IF(B42="","",VLOOKUP(B42,PROVEEDORES!$B:$C,2,FALSE)) | E42: 0 | G42: REAL DE BANCO: | I42: =+'15'!E18 -> 0
A43: =IF(B43="","",VLOOKUP(B43,PROVEEDORES!$B:$C,2,FALSE)) | E43: 0 | G43: EFECTIVO ANTERIOR: | I43: =+'15'!E19 -> 0
A44: =IF(B44="","",VLOOKUP(B44,PROVEEDORES!$B:$C,2,FALSE)) | E44: 0
A45: =IF(B45="","",VLOOKUP(B45,PROVEEDORES!$B:$C,2,FALSE)) | E45: 0
A46: =IF(B46="","",VLOOKUP(B46,PROVEEDORES!$B:$C,2,FALSE)) | E46: 0
A47: =IF(B47="","",VLOOKUP(B47,PROVEEDORES!$B:$C,2,FALSE)) | E47: 0
A48: =IF(B48="","",VLOOKUP(B48,PROVEEDORES!$B:$C,2,FALSE)) | E48: 0
A49: =IF(B49="","",VLOOKUP(B49,PROVEEDORES!$B:$C,2,FALSE)) | E49: 0
A50: =IF(B50="","",VLOOKUP(B50,PROVEEDORES!$B:$C,2,FALSE)) | E50: 0
A51: =IF(B51="","",VLOOKUP(B51,PROVEEDORES!$B:$C,2,FALSE)) | E51: 0
A52: =IF(B52="","",VLOOKUP(B52,PROVEEDORES!$B:$C,2,FALSE)) | E52: 0
A53: =IF(B53="","",VLOOKUP(B53,PROVEEDORES!$B:$C,2,FALSE)) | E53: 0
A54: =IF(B54="","",VLOOKUP(B54,PROVEEDORES!$B:$C,2,FALSE)) | E54: 0
A55: =IF(B55="","",VLOOKUP(B55,PROVEEDORES!$B:$C,2,FALSE)) | E55: 0
A56: EGRESO PROPINA | D56: INGRESO DE EFECTIVO
A57: PROPINA TRANSFERENCIA: | C57: 0 | E57: 0
A58: PROPINA BANCO: | C58: 0 | E58: 0
A59: PROPINA EFECTIVO: | C59: 0 | E59: 0

Sheet 17
A1: ='16'!A1+1 -> 17 | B1: =+'1'!B1 -> QUESO Y CAFÉ | D1: =+'16'!D1:E1+1 -> 46159 | G1: CUADRE DE CAJA MAÑANA | I1: CUADRE DE CAJA TARDE
A2: NIT | B2: PROVEEDOR | C2: CONCEPTO | D2: DESCRIPCIÓN | E2: VALOR | G2: PROP. TRANSF.: | H2: 0 | I2: PROP. TRANSF.: | J2: 0
A3: =IF(B3="","",VLOOKUP(B3,PROVEEDORES!$B:$C,2,FALSE)) | E3: 0 | G3: PROP. BANCO: | H3: 0 | I3: PROP. BANCO: | J3: 0
A4: =IF(B4="","",VLOOKUP(B4,PROVEEDORES!$B:$C,2,FALSE)) | E4: 0 | G4: PROP. EFECTIVO: | H4: 0 | I4: PROP. EFECTIVO: | J4: 0
A5: =IF(B5="","",VLOOKUP(B5,PROVEEDORES!$B:$C,2,FALSE)) | E5: 0 | G5: GASTO: | H5: 0 | I5: GASTO: | J5: 0
A6: =IF(B6="","",VLOOKUP(B6,PROVEEDORES!$B:$C,2,FALSE)) | E6: 0 | G6: TRANSFERENCIA: | H6: 0 | I6: TRANSFERENCIA: | J6: 0
A7: =IF(B7="","",VLOOKUP(B7,PROVEEDORES!$B:$C,2,FALSE)) | E7: 0 | G7: BANCO: | H7: 0 | I7: BANCO: | J7: 0
A8: =IF(B8="","",VLOOKUP(B8,PROVEEDORES!$B:$C,2,FALSE)) | E8: 0 | G8: EFECTIVO: | H8: 0 | I8: EFECTIVO: | J8: 0
A9: =IF(B9="","",VLOOKUP(B9,PROVEEDORES!$B:$C,2,FALSE)) | E9: 0 | G9: TOTAL: | H9: =SUM(H5:H8) -> 0 | I9: TOTAL: | J9: =SUM(J5:J8) -> 0
A10: =IF(B10="","",VLOOKUP(B10,PROVEEDORES!$B:$C,2,FALSE)) | E10: 0 | G10: DIFERENCIA: | H10: =+H11-H9 -> 0 | I10: DIFERENCIA: | J10: =+J11-J9 -> 0
A11: =IF(B11="","",VLOOKUP(B11,PROVEEDORES!$B:$C,2,FALSE)) | E11: 0 | G11: TOTAL VENTA: | H11: 0 | I11: TOTAL VENTA: | J11: 0
A12: =IF(B12="","",VLOOKUP(B12,PROVEEDORES!$B:$C,2,FALSE)) | E12: 0
A13: PROPINA TRANSFERENCIA: | C13: =SUM(H2,J2) -> 0 | D13: ACUM. PROPINA TRANFERENCIA: | E13: =SUM(C13,I37)-C57 -> 0 | G13: DIFERENCIA PLANILLA VS CUADRE DE CAJA | I13: =+C20-(SUM(H9,J9)) -> 0
A14: PROPINA POR BANCO: | C14: =SUM(H3,J3) -> 0 | D14: ACUM. PROPINA BANCO: | E14: =SUM(C14,I38)-C58 -> 0
A15: PROPINA EN EFECTIVO: | C15: =SUM(H4,J4) -> 0 | D15: ACUM. PROPINA EFECTIVO: | E15: =SUM(C15,I39)-C59 -> 0 | G15: FACTURAS EN EFECTIVO: | I15: 0
A16: TOTAL EGRESOS: | C16: =SUM(E3:E12) -> 0 | D16: ACUMULADO TRANSFERENCIA: | E16: =SUM(C17,I40) -> 0 | G16: EFECTIVO: | I16: 0
A17: TRANSFERENCIA: | C17: =SUM(H6,J6) -> 0 | D17: ACUMULADO BANCO: | E17: =SUM(C18,I41) -> 0 | G17: TOTAL EFECTIVO REAL ACTUAL: | I17: =SUM(I15,I16) -> 0
A18: BANCO: | C18: =SUM(H7,J7) -> 0 | D18: TOTAL BANCO: | E18: =SUM(C18,I42)-(SUM(E36:E55)) -> 0 | G18: DIFERENCIA: | I18: =+I19-I17 -> 0
A19: EFECTIVO: | C19: =SUM(H8,J8) -> 0 | D19: TOTAL EFECTIVO: | E19: =SUM(C19,E20,E57:E59)-(SUM(E23:E34)) -> 0 | G19: EFECTIVO ACTUAL PLANILLA: | I19: =E19 -> 0
A20: TOTAL VENTA: | C20: =SUM(C16:C19) -> 0 | D20: EFECTIVO ANTERIOR: | E20: =+I43 -> 0
A21: EGRESO DE CAJA MAYOR | G21: CONTEO DE EFECTIVO
A22: NIT | B22: PROVEEDOR | C22: CONCEPTO | D22: DESCRIPCIÓN | E22: EFECTIVO | G22: DENOMINACIÓN | H22: CANTIDAD | I22: EFECTIVO
A23: =IF(B23="","",VLOOKUP(B23,PROVEEDORES!$B:$C,2,FALSE)) | E23: 0 | G23: MONEDAS DE 100 | H23: 0 | I23: =100*H23 -> 0
A24: =IF(B24="","",VLOOKUP(B24,PROVEEDORES!$B:$C,2,FALSE)) | E24: 0 | G24: MONEDAS DE 200 | H24: 0 | I24: =200*H24 -> 0
A25: =IF(B25="","",VLOOKUP(B25,PROVEEDORES!$B:$C,2,FALSE)) | E25: 0 | G25: MONEDAS DE 500 | H25: 0 | I25: =500*H25 -> 0
A26: =IF(B26="","",VLOOKUP(B26,PROVEEDORES!$B:$C,2,FALSE)) | E26: 0 | G26: MONEDAS DE 1.000 | H26: 0 | I26: =1000*H26 -> 0
A27: =IF(B27="","",VLOOKUP(B27,PROVEEDORES!$B:$C,2,FALSE)) | E27: 0 | G27: BILLETES DE 2.000 | H27: 0 | I27: =2000*H27 -> 0
A28: =IF(B28="","",VLOOKUP(B28,PROVEEDORES!$B:$C,2,FALSE)) | E28: 0 | G28: BILLETES DE 5.000 | H28: 0 | I28: =5000*H28 -> 0
A29: =IF(B29="","",VLOOKUP(B29,PROVEEDORES!$B:$C,2,FALSE)) | E29: 0 | G29: BILLETES DE 10.000 | H29: 0 | I29: =10000*H29 -> 0
A30: =IF(B30="","",VLOOKUP(B30,PROVEEDORES!$B:$C,2,FALSE)) | E30: 0 | G30: BILLETES DE 20.000 | H30: 0 | I30: =20000*H30 -> 0
A31: =IF(B31="","",VLOOKUP(B31,PROVEEDORES!$B:$C,2,FALSE)) | E31: 0 | G31: BILLETES DE 50.000 | H31: 0 | I31: =50000*H31 -> 0
A32: =IF(B32="","",VLOOKUP(B32,PROVEEDORES!$B:$C,2,FALSE)) | E32: 0 | G32: BILLETES DE 100.000 | H32: 0 | I32: =100000*H32 -> 0
A33: =IF(B33="","",VLOOKUP(B33,PROVEEDORES!$B:$C,2,FALSE)) | E33: 0 | G33: TOTAL EFECTIVO: | I33: =SUM(I23:I32) -> 0
A34: =IF(B34="","",VLOOKUP(B34,PROVEEDORES!$B:$C,2,FALSE)) | E34: 0 | G34: BASE: | I34: 0
A35: NIT | B35: PROVEEDOR | C35: CONCEPTO | D35: DESCRIPCIÓN | E35: BANCO | G35: TOTAL EFECTIVO MENOS LA BASE: | I35: =I33-I34 -> 0
A36: =IF(B36="","",VLOOKUP(B36,PROVEEDORES!$B:$C,2,FALSE)) | E36: 0
A37: =IF(B37="","",VLOOKUP(B37,PROVEEDORES!$B:$C,2,FALSE)) | E37: 0 | G37: ACUM. DE PROPINA TRANSFERENCIA: | I37: =+'16'!E13 -> 0
A38: =IF(B38="","",VLOOKUP(B38,PROVEEDORES!$B:$C,2,FALSE)) | E38: 0 | G38: ACUMULADO DE PROPINA EN BANCO: | I38: =+'16'!E14 -> 0
A39: =IF(B39="","",VLOOKUP(B39,PROVEEDORES!$B:$C,2,FALSE)) | E39: 0 | G39: ACUMULADO DE PROPINA POR EFECTIVO: | I39: =+'16'!E15 -> 0
A40: =IF(B40="","",VLOOKUP(B40,PROVEEDORES!$B:$C,2,FALSE)) | E40: 0 | G40: ACUMULADO DE TRANSFERENCIA: | I40: =+'16'!E16 -> 0
A41: =IF(B41="","",VLOOKUP(B41,PROVEEDORES!$B:$C,2,FALSE)) | E41: 0 | G41: ACUMULADO DE BANCO: | I41: =+'16'!E17 -> 0
A42: =IF(B42="","",VLOOKUP(B42,PROVEEDORES!$B:$C,2,FALSE)) | E42: 0 | G42: REAL DE BANCO: | I42: =+'16'!E18 -> 0
A43: =IF(B43="","",VLOOKUP(B43,PROVEEDORES!$B:$C,2,FALSE)) | E43: 0 | G43: EFECTIVO ANTERIOR: | I43: =+'16'!E19 -> 0
A44: =IF(B44="","",VLOOKUP(B44,PROVEEDORES!$B:$C,2,FALSE)) | E44: 0
A45: =IF(B45="","",VLOOKUP(B45,PROVEEDORES!$B:$C,2,FALSE)) | E45: 0
A46: =IF(B46="","",VLOOKUP(B46,PROVEEDORES!$B:$C,2,FALSE)) | E46: 0
A47: =IF(B47="","",VLOOKUP(B47,PROVEEDORES!$B:$C,2,FALSE)) | E47: 0
A48: =IF(B48="","",VLOOKUP(B48,PROVEEDORES!$B:$C,2,FALSE)) | E48: 0
A49: =IF(B49="","",VLOOKUP(B49,PROVEEDORES!$B:$C,2,FALSE)) | E49: 0
A50: =IF(B50="","",VLOOKUP(B50,PROVEEDORES!$B:$C,2,FALSE)) | E50: 0
A51: =IF(B51="","",VLOOKUP(B51,PROVEEDORES!$B:$C,2,FALSE)) | E51: 0
A52: =IF(B52="","",VLOOKUP(B52,PROVEEDORES!$B:$C,2,FALSE)) | E52: 0
A53: =IF(B53="","",VLOOKUP(B53,PROVEEDORES!$B:$C,2,FALSE)) | E53: 0
A54: =IF(B54="","",VLOOKUP(B54,PROVEEDORES!$B:$C,2,FALSE)) | E54: 0
A55: =IF(B55="","",VLOOKUP(B55,PROVEEDORES!$B:$C,2,FALSE)) | E55: 0
A56: EGRESO PROPINA | D56: INGRESO DE EFECTIVO
A57: PROPINA TRANSFERENCIA: | C57: 0 | E57: 0
A58: PROPINA BANCO: | C58: 0 | E58: 0
A59: PROPINA EFECTIVO: | C59: 0 | E59: 0

Sheet 18
A1: ='17'!A1+1 -> 18 | B1: =+'1'!B1 -> QUESO Y CAFÉ | D1: =+'17'!D1:E1+1 -> 46160 | G1: CUADRE DE CAJA MAÑANA | I1: CUADRE DE CAJA TARDE
A2: NIT | B2: PROVEEDOR | C2: CONCEPTO | D2: DESCRIPCIÓN | E2: VALOR | G2: PROP. TRANSF.: | H2: 0 | I2: PROP. TRANSF.: | J2: 0
A3: =IF(B3="","",VLOOKUP(B3,PROVEEDORES!$B:$C,2,FALSE)) | E3: 0 | G3: PROP. BANCO: | H3: 0 | I3: PROP. BANCO: | J3: 0
A4: =IF(B4="","",VLOOKUP(B4,PROVEEDORES!$B:$C,2,FALSE)) | E4: 0 | G4: PROP. EFECTIVO: | H4: 0 | I4: PROP. EFECTIVO: | J4: 0
A5: =IF(B5="","",VLOOKUP(B5,PROVEEDORES!$B:$C,2,FALSE)) | E5: 0 | G5: GASTO: | H5: 0 | I5: GASTO: | J5: 0
A6: =IF(B6="","",VLOOKUP(B6,PROVEEDORES!$B:$C,2,FALSE)) | E6: 0 | G6: TRANSFERENCIA: | H6: 0 | I6: TRANSFERENCIA: | J6: 0
A7: =IF(B7="","",VLOOKUP(B7,PROVEEDORES!$B:$C,2,FALSE)) | E7: 0 | G7: BANCO: | H7: 0 | I7: BANCO: | J7: 0
A8: =IF(B8="","",VLOOKUP(B8,PROVEEDORES!$B:$C,2,FALSE)) | E8: 0 | G8: EFECTIVO: | H8: 0 | I8: EFECTIVO: | J8: 0
A9: =IF(B9="","",VLOOKUP(B9,PROVEEDORES!$B:$C,2,FALSE)) | E9: 0 | G9: TOTAL: | H9: =SUM(H5:H8) -> 0 | I9: TOTAL: | J9: =SUM(J5:J8) -> 0
A10: =IF(B10="","",VLOOKUP(B10,PROVEEDORES!$B:$C,2,FALSE)) | E10: 0 | G10: DIFERENCIA: | H10: =+H11-H9 -> 0 | I10: DIFERENCIA: | J10: =+J11-J9 -> 0
A11: =IF(B11="","",VLOOKUP(B11,PROVEEDORES!$B:$C,2,FALSE)) | E11: 0 | G11: TOTAL VENTA: | H11: 0 | I11: TOTAL VENTA: | J11: 0
A12: =IF(B12="","",VLOOKUP(B12,PROVEEDORES!$B:$C,2,FALSE)) | E12: 0
A13: PROPINA TRANSFERENCIA: | C13: =SUM(H2,J2) -> 0 | D13: ACUM. PROPINA TRANFERENCIA: | E13: =SUM(C13,I37)-C57 -> 0 | G13: DIFERENCIA PLANILLA VS CUADRE DE CAJA | I13: =+C20-(SUM(H9,J9)) -> 0
A14: PROPINA POR BANCO: | C14: =SUM(H3,J3) -> 0 | D14: ACUM. PROPINA BANCO: | E14: =SUM(C14,I38)-C58 -> 0
A15: PROPINA EN EFECTIVO: | C15: =SUM(H4,J4) -> 0 | D15: ACUM. PROPINA EFECTIVO: | E15: =SUM(C15,I39)-C59 -> 0 | G15: FACTURAS EN EFECTIVO: | I15: 0
A16: TOTAL EGRESOS: | C16: =SUM(E3:E12) -> 0 | D16: ACUMULADO TRANSFERENCIA: | E16: =SUM(C17,I40) -> 0 | G16: EFECTIVO: | I16: 0
A17: TRANSFERENCIA: | C17: =SUM(H6,J6) -> 0 | D17: ACUMULADO BANCO: | E17: =SUM(C18,I41) -> 0 | G17: TOTAL EFECTIVO REAL ACTUAL: | I17: =SUM(I15,I16) -> 0
A18: BANCO: | C18: =SUM(H7,J7) -> 0 | D18: TOTAL BANCO: | E18: =SUM(C18,I42)-(SUM(E36:E55)) -> 0 | G18: DIFERENCIA: | I18: =+I19-I17 -> 0
A19: EFECTIVO: | C19: =SUM(H8,J8) -> 0 | D19: TOTAL EFECTIVO: | E19: =SUM(C19,E20,E57:E59)-(SUM(E23:E34)) -> 0 | G19: EFECTIVO ACTUAL PLANILLA: | I19: =E19 -> 0
A20: TOTAL VENTA: | C20: =SUM(C16:C19) -> 0 | D20: EFECTIVO ANTERIOR: | E20: =+I43 -> 0
A21: EGRESO DE CAJA MAYOR | G21: CONTEO DE EFECTIVO
A22: NIT | B22: PROVEEDOR | C22: CONCEPTO | D22: DESCRIPCIÓN | E22: EFECTIVO | G22: DENOMINACIÓN | H22: CANTIDAD | I22: EFECTIVO
A23: =IF(B23="","",VLOOKUP(B23,PROVEEDORES!$B:$C,2,FALSE)) | E23: 0 | G23: MONEDAS DE 100 | H23: 0 | I23: =100*H23 -> 0
A24: =IF(B24="","",VLOOKUP(B24,PROVEEDORES!$B:$C,2,FALSE)) | E24: 0 | G24: MONEDAS DE 200 | H24: 0 | I24: =200*H24 -> 0
A25: =IF(B25="","",VLOOKUP(B25,PROVEEDORES!$B:$C,2,FALSE)) | E25: 0 | G25: MONEDAS DE 500 | H25: 0 | I25: =500*H25 -> 0
A26: =IF(B26="","",VLOOKUP(B26,PROVEEDORES!$B:$C,2,FALSE)) | E26: 0 | G26: MONEDAS DE 1.000 | H26: 0 | I26: =1000*H26 -> 0
A27: =IF(B27="","",VLOOKUP(B27,PROVEEDORES!$B:$C,2,FALSE)) | E27: 0 | G27: BILLETES DE 2.000 | H27: 0 | I27: =2000*H27 -> 0
A28: =IF(B28="","",VLOOKUP(B28,PROVEEDORES!$B:$C,2,FALSE)) | E28: 0 | G28: BILLETES DE 5.000 | H28: 0 | I28: =5000*H28 -> 0
A29: =IF(B29="","",VLOOKUP(B29,PROVEEDORES!$B:$C,2,FALSE)) | E29: 0 | G29: BILLETES DE 10.000 | H29: 0 | I29: =10000*H29 -> 0
A30: =IF(B30="","",VLOOKUP(B30,PROVEEDORES!$B:$C,2,FALSE)) | E30: 0 | G30: BILLETES DE 20.000 | H30: 0 | I30: =20000*H30 -> 0
A31: =IF(B31="","",VLOOKUP(B31,PROVEEDORES!$B:$C,2,FALSE)) | E31: 0 | G31: BILLETES DE 50.000 | H31: 0 | I31: =50000*H31 -> 0
A32: =IF(B32="","",VLOOKUP(B32,PROVEEDORES!$B:$C,2,FALSE)) | E32: 0 | G32: BILLETES DE 100.000 | H32: 0 | I32: =100000*H32 -> 0
A33: =IF(B33="","",VLOOKUP(B33,PROVEEDORES!$B:$C,2,FALSE)) | E33: 0 | G33: TOTAL EFECTIVO: | I33: =SUM(I23:I32) -> 0
A34: =IF(B34="","",VLOOKUP(B34,PROVEEDORES!$B:$C,2,FALSE)) | E34: 0 | G34: BASE: | I34: 0
A35: NIT | B35: PROVEEDOR | C35: CONCEPTO | D35: DESCRIPCIÓN | E35: BANCO | G35: TOTAL EFECTIVO MENOS LA BASE: | I35: =I33-I34 -> 0
A36: =IF(B36="","",VLOOKUP(B36,PROVEEDORES!$B:$C,2,FALSE)) | E36: 0
A37: =IF(B37="","",VLOOKUP(B37,PROVEEDORES!$B:$C,2,FALSE)) | E37: 0 | G37: ACUM. DE PROPINA TRANSFERENCIA: | I37: =+'17'!E13 -> 0
A38: =IF(B38="","",VLOOKUP(B38,PROVEEDORES!$B:$C,2,FALSE)) | E38: 0 | G38: ACUMULADO DE PROPINA EN BANCO: | I38: =+'17'!E14 -> 0
A39: =IF(B39="","",VLOOKUP(B39,PROVEEDORES!$B:$C,2,FALSE)) | E39: 0 | G39: ACUMULADO DE PROPINA POR EFECTIVO: | I39: =+'17'!E15 -> 0
A40: =IF(B40="","",VLOOKUP(B40,PROVEEDORES!$B:$C,2,FALSE)) | E40: 0 | G40: ACUMULADO DE TRANSFERENCIA: | I40: =+'17'!E16 -> 0
A41: =IF(B41="","",VLOOKUP(B41,PROVEEDORES!$B:$C,2,FALSE)) | E41: 0 | G41: ACUMULADO DE BANCO: | I41: =+'17'!E17 -> 0
A42: =IF(B42="","",VLOOKUP(B42,PROVEEDORES!$B:$C,2,FALSE)) | E42: 0 | G42: REAL DE BANCO: | I42: =+'17'!E18 -> 0
A43: =IF(B43="","",VLOOKUP(B43,PROVEEDORES!$B:$C,2,FALSE)) | E43: 0 | G43: EFECTIVO ANTERIOR: | I43: =+'17'!E19 -> 0
A44: =IF(B44="","",VLOOKUP(B44,PROVEEDORES!$B:$C,2,FALSE)) | E44: 0
A45: =IF(B45="","",VLOOKUP(B45,PROVEEDORES!$B:$C,2,FALSE)) | E45: 0
A46: =IF(B46="","",VLOOKUP(B46,PROVEEDORES!$B:$C,2,FALSE)) | E46: 0
A47: =IF(B47="","",VLOOKUP(B47,PROVEEDORES!$B:$C,2,FALSE)) | E47: 0
A48: =IF(B48="","",VLOOKUP(B48,PROVEEDORES!$B:$C,2,FALSE)) | E48: 0
A49: =IF(B49="","",VLOOKUP(B49,PROVEEDORES!$B:$C,2,FALSE)) | E49: 0
A50: =IF(B50="","",VLOOKUP(B50,PROVEEDORES!$B:$C,2,FALSE)) | E50: 0
A51: =IF(B51="","",VLOOKUP(B51,PROVEEDORES!$B:$C,2,FALSE)) | E51: 0
A52: =IF(B52="","",VLOOKUP(B52,PROVEEDORES!$B:$C,2,FALSE)) | E52: 0
A53: =IF(B53="","",VLOOKUP(B53,PROVEEDORES!$B:$C,2,FALSE)) | E53: 0
A54: =IF(B54="","",VLOOKUP(B54,PROVEEDORES!$B:$C,2,FALSE)) | E54: 0
A55: =IF(B55="","",VLOOKUP(B55,PROVEEDORES!$B:$C,2,FALSE)) | E55: 0
A56: EGRESO PROPINA | D56: INGRESO DE EFECTIVO
A57: PROPINA TRANSFERENCIA: | C57: 0 | E57: 0
A58: PROPINA BANCO: | C58: 0 | E58: 0
A59: PROPINA EFECTIVO: | C59: 0 | E59: 0

Sheet 19
A1: ='18'!A1+1 -> 19 | B1: =+'1'!B1 -> QUESO Y CAFÉ | D1: =+'18'!D1:E1+1 -> 46161 | G1: CUADRE DE CAJA MAÑANA | I1: CUADRE DE CAJA TARDE
A2: NIT | B2: PROVEEDOR | C2: CONCEPTO | D2: DESCRIPCIÓN | E2: VALOR | G2: PROP. TRANSF.: | H2: 0 | I2: PROP. TRANSF.: | J2: 0
A3: =IF(B3="","",VLOOKUP(B3,PROVEEDORES!$B:$C,2,FALSE)) | E3: 0 | G3: PROP. BANCO: | H3: 0 | I3: PROP. BANCO: | J3: 0
A4: =IF(B4="","",VLOOKUP(B4,PROVEEDORES!$B:$C,2,FALSE)) | E4: 0 | G4: PROP. EFECTIVO: | H4: 0 | I4: PROP. EFECTIVO: | J4: 0
A5: =IF(B5="","",VLOOKUP(B5,PROVEEDORES!$B:$C,2,FALSE)) | E5: 0 | G5: GASTO: | H5: 0 | I5: GASTO: | J5: 0
A6: =IF(B6="","",VLOOKUP(B6,PROVEEDORES!$B:$C,2,FALSE)) | E6: 0 | G6: TRANSFERENCIA: | H6: 0 | I6: TRANSFERENCIA: | J6: 0
A7: =IF(B7="","",VLOOKUP(B7,PROVEEDORES!$B:$C,2,FALSE)) | E7: 0 | G7: BANCO: | H7: 0 | I7: BANCO: | J7: 0
A8: =IF(B8="","",VLOOKUP(B8,PROVEEDORES!$B:$C,2,FALSE)) | E8: 0 | G8: EFECTIVO: | H8: 0 | I8: EFECTIVO: | J8: 0
A9: =IF(B9="","",VLOOKUP(B9,PROVEEDORES!$B:$C,2,FALSE)) | E9: 0 | G9: TOTAL: | H9: =SUM(H5:H8) -> 0 | I9: TOTAL: | J9: =SUM(J5:J8) -> 0
A10: =IF(B10="","",VLOOKUP(B10,PROVEEDORES!$B:$C,2,FALSE)) | E10: 0 | G10: DIFERENCIA: | H10: =+H11-H9 -> 0 | I10: DIFERENCIA: | J10: =+J11-J9 -> 0
A11: =IF(B11="","",VLOOKUP(B11,PROVEEDORES!$B:$C,2,FALSE)) | E11: 0 | G11: TOTAL VENTA: | H11: 0 | I11: TOTAL VENTA: | J11: 0
A12: =IF(B12="","",VLOOKUP(B12,PROVEEDORES!$B:$C,2,FALSE)) | E12: 0
A13: PROPINA TRANSFERENCIA: | C13: =SUM(H2,J2) -> 0 | D13: ACUM. PROPINA TRANFERENCIA: | E13: =SUM(C13,I37)-C57 -> 0 | G13: DIFERENCIA PLANILLA VS CUADRE DE CAJA | I13: =+C20-(SUM(H9,J9)) -> 0
A14: PROPINA POR BANCO: | C14: =SUM(H3,J3) -> 0 | D14: ACUM. PROPINA BANCO: | E14: =SUM(C14,I38)-C58 -> 0
A15: PROPINA EN EFECTIVO: | C15: =SUM(H4,J4) -> 0 | D15: ACUM. PROPINA EFECTIVO: | E15: =SUM(C15,I39)-C59 -> 0 | G15: FACTURAS EN EFECTIVO: | I15: 0
A16: TOTAL EGRESOS: | C16: =SUM(E3:E12) -> 0 | D16: ACUMULADO TRANSFERENCIA: | E16: =SUM(C17,I40) -> 0 | G16: EFECTIVO: | I16: 0
A17: TRANSFERENCIA: | C17: =SUM(H6,J6) -> 0 | D17: ACUMULADO BANCO: | E17: =SUM(C18,I41) -> 0 | G17: TOTAL EFECTIVO REAL ACTUAL: | I17: =SUM(I15,I16) -> 0
A18: BANCO: | C18: =SUM(H7,J7) -> 0 | D18: TOTAL BANCO: | E18: =SUM(C18,I42)-(SUM(E36:E55)) -> 0 | G18: DIFERENCIA: | I18: =+I19-I17 -> 0
A19: EFECTIVO: | C19: =SUM(H8,J8) -> 0 | D19: TOTAL EFECTIVO: | E19: =SUM(C19,E20,E57:E59)-(SUM(E23:E34)) -> 0 | G19: EFECTIVO ACTUAL PLANILLA: | I19: =E19 -> 0
A20: TOTAL VENTA: | C20: =SUM(C16:C19) -> 0 | D20: EFECTIVO ANTERIOR: | E20: =+I43 -> 0
A21: EGRESO DE CAJA MAYOR | G21: CONTEO DE EFECTIVO
A22: NIT | B22: PROVEEDOR | C22: CONCEPTO | D22: DESCRIPCIÓN | E22: EFECTIVO | G22: DENOMINACIÓN | H22: CANTIDAD | I22: EFECTIVO
A23: =IF(B23="","",VLOOKUP(B23,PROVEEDORES!$B:$C,2,FALSE)) | E23: 0 | G23: MONEDAS DE 100 | H23: 0 | I23: =100*H23 -> 0
A24: =IF(B24="","",VLOOKUP(B24,PROVEEDORES!$B:$C,2,FALSE)) | E24: 0 | G24: MONEDAS DE 200 | H24: 0 | I24: =200*H24 -> 0
A25: =IF(B25="","",VLOOKUP(B25,PROVEEDORES!$B:$C,2,FALSE)) | E25: 0 | G25: MONEDAS DE 500 | H25: 0 | I25: =500*H25 -> 0
A26: =IF(B26="","",VLOOKUP(B26,PROVEEDORES!$B:$C,2,FALSE)) | E26: 0 | G26: MONEDAS DE 1.000 | H26: 0 | I26: =1000*H26 -> 0
A27: =IF(B27="","",VLOOKUP(B27,PROVEEDORES!$B:$C,2,FALSE)) | E27: 0 | G27: BILLETES DE 2.000 | H27: 0 | I27: =2000*H27 -> 0
A28: =IF(B28="","",VLOOKUP(B28,PROVEEDORES!$B:$C,2,FALSE)) | E28: 0 | G28: BILLETES DE 5.000 | H28: 0 | I28: =5000*H28 -> 0
A29: =IF(B29="","",VLOOKUP(B29,PROVEEDORES!$B:$C,2,FALSE)) | E29: 0 | G29: BILLETES DE 10.000 | H29: 0 | I29: =10000*H29 -> 0
A30: =IF(B30="","",VLOOKUP(B30,PROVEEDORES!$B:$C,2,FALSE)) | E30: 0 | G30: BILLETES DE 20.000 | H30: 0 | I30: =20000*H30 -> 0
A31: =IF(B31="","",VLOOKUP(B31,PROVEEDORES!$B:$C,2,FALSE)) | E31: 0 | G31: BILLETES DE 50.000 | H31: 0 | I31: =50000*H31 -> 0
A32: =IF(B32="","",VLOOKUP(B32,PROVEEDORES!$B:$C,2,FALSE)) | E32: 0 | G32: BILLETES DE 100.000 | H32: 0 | I32: =100000*H32 -> 0
A33: =IF(B33="","",VLOOKUP(B33,PROVEEDORES!$B:$C,2,FALSE)) | E33: 0 | G33: TOTAL EFECTIVO: | I33: =SUM(I23:I32) -> 0
A34: =IF(B34="","",VLOOKUP(B34,PROVEEDORES!$B:$C,2,FALSE)) | E34: 0 | G34: BASE: | I34: 0
A35: NIT | B35: PROVEEDOR | C35: CONCEPTO | D35: DESCRIPCIÓN | E35: BANCO | G35: TOTAL EFECTIVO MENOS LA BASE: | I35: =I33-I34 -> 0
A36: =IF(B36="","",VLOOKUP(B36,PROVEEDORES!$B:$C,2,FALSE)) | E36: 0
A37: =IF(B37="","",VLOOKUP(B37,PROVEEDORES!$B:$C,2,FALSE)) | E37: 0 | G37: ACUM. DE PROPINA TRANSFERENCIA: | I37: =+'18'!E13 -> 0
A38: =IF(B38="","",VLOOKUP(B38,PROVEEDORES!$B:$C,2,FALSE)) | E38: 0 | G38: ACUMULADO DE PROPINA EN BANCO: | I38: =+'18'!E14 -> 0
A39: =IF(B39="","",VLOOKUP(B39,PROVEEDORES!$B:$C,2,FALSE)) | E39: 0 | G39: ACUMULADO DE PROPINA POR EFECTIVO: | I39: =+'18'!E15 -> 0
A40: =IF(B40="","",VLOOKUP(B40,PROVEEDORES!$B:$C,2,FALSE)) | E40: 0 | G40: ACUMULADO DE TRANSFERENCIA: | I40: =+'18'!E16 -> 0
A41: =IF(B41="","",VLOOKUP(B41,PROVEEDORES!$B:$C,2,FALSE)) | E41: 0 | G41: ACUMULADO DE BANCO: | I41: =+'18'!E17 -> 0
A42: =IF(B42="","",VLOOKUP(B42,PROVEEDORES!$B:$C,2,FALSE)) | E42: 0 | G42: REAL DE BANCO: | I42: =+'18'!E18 -> 0
A43: =IF(B43="","",VLOOKUP(B43,PROVEEDORES!$B:$C,2,FALSE)) | E43: 0 | G43: EFECTIVO ANTERIOR: | I43: =+'18'!E19 -> 0
A44: =IF(B44="","",VLOOKUP(B44,PROVEEDORES!$B:$C,2,FALSE)) | E44: 0
A45: =IF(B45="","",VLOOKUP(B45,PROVEEDORES!$B:$C,2,FALSE)) | E45: 0
A46: =IF(B46="","",VLOOKUP(B46,PROVEEDORES!$B:$C,2,FALSE)) | E46: 0
A47: =IF(B47="","",VLOOKUP(B47,PROVEEDORES!$B:$C,2,FALSE)) | E47: 0
A48: =IF(B48="","",VLOOKUP(B48,PROVEEDORES!$B:$C,2,FALSE)) | E48: 0
A49: =IF(B49="","",VLOOKUP(B49,PROVEEDORES!$B:$C,2,FALSE)) | E49: 0
A50: =IF(B50="","",VLOOKUP(B50,PROVEEDORES!$B:$C,2,FALSE)) | E50: 0
A51: =IF(B51="","",VLOOKUP(B51,PROVEEDORES!$B:$C,2,FALSE)) | E51: 0
A52: =IF(B52="","",VLOOKUP(B52,PROVEEDORES!$B:$C,2,FALSE)) | E52: 0
A53: =IF(B53="","",VLOOKUP(B53,PROVEEDORES!$B:$C,2,FALSE)) | E53: 0
A54: =IF(B54="","",VLOOKUP(B54,PROVEEDORES!$B:$C,2,FALSE)) | E54: 0
A55: =IF(B55="","",VLOOKUP(B55,PROVEEDORES!$B:$C,2,FALSE)) | E55: 0
A56: EGRESO PROPINA | D56: INGRESO DE EFECTIVO
A57: PROPINA TRANSFERENCIA: | C57: 0 | E57: 0
A58: PROPINA BANCO: | C58: 0 | E58: 0
A59: PROPINA EFECTIVO: | C59: 0 | E59: 0

Sheet 20
A1: ='19'!A1+1 -> 20 | B1: =+'1'!B1 -> QUESO Y CAFÉ | D1: =+'19'!D1:E1+1 -> 46162 | G1: CUADRE DE CAJA MAÑANA | I1: CUADRE DE CAJA TARDE
A2: NIT | B2: PROVEEDOR | C2: CONCEPTO | D2: DESCRIPCIÓN | E2: VALOR | G2: PROP. TRANSF.: | H2: 0 | I2: PROP. TRANSF.: | J2: 0
A3: =IF(B3="","",VLOOKUP(B3,PROVEEDORES!$B:$C,2,FALSE)) | E3: 0 | G3: PROP. BANCO: | H3: 0 | I3: PROP. BANCO: | J3: 0
A4: =IF(B4="","",VLOOKUP(B4,PROVEEDORES!$B:$C,2,FALSE)) | E4: 0 | G4: PROP. EFECTIVO: | H4: 0 | I4: PROP. EFECTIVO: | J4: 0
A5: =IF(B5="","",VLOOKUP(B5,PROVEEDORES!$B:$C,2,FALSE)) | E5: 0 | G5: GASTO: | H5: 0 | I5: GASTO: | J5: 0
A6: =IF(B6="","",VLOOKUP(B6,PROVEEDORES!$B:$C,2,FALSE)) | E6: 0 | G6: TRANSFERENCIA: | H6: 0 | I6: TRANSFERENCIA: | J6: 0
A7: =IF(B7="","",VLOOKUP(B7,PROVEEDORES!$B:$C,2,FALSE)) | E7: 0 | G7: BANCO: | H7: 0 | I7: BANCO: | J7: 0
A8: =IF(B8="","",VLOOKUP(B8,PROVEEDORES!$B:$C,2,FALSE)) | E8: 0 | G8: EFECTIVO: | H8: 0 | I8: EFECTIVO: | J8: 0
A9: =IF(B9="","",VLOOKUP(B9,PROVEEDORES!$B:$C,2,FALSE)) | E9: 0 | G9: TOTAL: | H9: =SUM(H5:H8) -> 0 | I9: TOTAL: | J9: =SUM(J5:J8) -> 0
A10: =IF(B10="","",VLOOKUP(B10,PROVEEDORES!$B:$C,2,FALSE)) | E10: 0 | G10: DIFERENCIA: | H10: =+H11-H9 -> 0 | I10: DIFERENCIA: | J10: =+J11-J9 -> 0
A11: =IF(B11="","",VLOOKUP(B11,PROVEEDORES!$B:$C,2,FALSE)) | E11: 0 | G11: TOTAL VENTA: | H11: 0 | I11: TOTAL VENTA: | J11: 0
A12: =IF(B12="","",VLOOKUP(B12,PROVEEDORES!$B:$C,2,FALSE)) | E12: 0
A13: PROPINA TRANSFERENCIA: | C13: =SUM(H2,J2) -> 0 | D13: ACUM. PROPINA TRANFERENCIA: | E13: =SUM(C13,I37)-C57 -> 0 | G13: DIFERENCIA PLANILLA VS CUADRE DE CAJA | I13: =+C20-(SUM(H9,J9)) -> 0
A14: PROPINA POR BANCO: | C14: =SUM(H3,J3) -> 0 | D14: ACUM. PROPINA BANCO: | E14: =SUM(C14,I38)-C58 -> 0
A15: PROPINA EN EFECTIVO: | C15: =SUM(H4,J4) -> 0 | D15: ACUM. PROPINA EFECTIVO: | E15: =SUM(C15,I39)-C59 -> 0 | G15: FACTURAS EN EFECTIVO: | I15: 0
A16: TOTAL EGRESOS: | C16: =SUM(E3:E12) -> 0 | D16: ACUMULADO TRANSFERENCIA: | E16: =SUM(C17,I40) -> 0 | G16: EFECTIVO: | I16: 0
A17: TRANSFERENCIA: | C17: =SUM(H6,J6) -> 0 | D17: ACUMULADO BANCO: | E17: =SUM(C18,I41) -> 0 | G17: TOTAL EFECTIVO REAL ACTUAL: | I17: =SUM(I15,I16) -> 0
A18: BANCO: | C18: =SUM(H7,J7) -> 0 | D18: TOTAL BANCO: | E18: =SUM(C18,I42)-(SUM(E36:E55)) -> 0 | G18: DIFERENCIA: | I18: =+I19-I17 -> 0
A19: EFECTIVO: | C19: =SUM(H8,J8) -> 0 | D19: TOTAL EFECTIVO: | E19: =SUM(C19,E20,E57:E59)-(SUM(E23:E34)) -> 0 | G19: EFECTIVO ACTUAL PLANILLA: | I19: =E19 -> 0
A20: TOTAL VENTA: | C20: =SUM(C16:C19) -> 0 | D20: EFECTIVO ANTERIOR: | E20: =+I43 -> 0
A21: EGRESO DE CAJA MAYOR | G21: CONTEO DE EFECTIVO
A22: NIT | B22: PROVEEDOR | C22: CONCEPTO | D22: DESCRIPCIÓN | E22: EFECTIVO | G22: DENOMINACIÓN | H22: CANTIDAD | I22: EFECTIVO
A23: =IF(B23="","",VLOOKUP(B23,PROVEEDORES!$B:$C,2,FALSE)) | E23: 0 | G23: MONEDAS DE 100 | H23: 0 | I23: =100*H23 -> 0
A24: =IF(B24="","",VLOOKUP(B24,PROVEEDORES!$B:$C,2,FALSE)) | E24: 0 | G24: MONEDAS DE 200 | H24: 0 | I24: =200*H24 -> 0
A25: =IF(B25="","",VLOOKUP(B25,PROVEEDORES!$B:$C,2,FALSE)) | E25: 0 | G25: MONEDAS DE 500 | H25: 0 | I25: =500*H25 -> 0
A26: =IF(B26="","",VLOOKUP(B26,PROVEEDORES!$B:$C,2,FALSE)) | E26: 0 | G26: MONEDAS DE 1.000 | H26: 0 | I26: =1000*H26 -> 0
A27: =IF(B27="","",VLOOKUP(B27,PROVEEDORES!$B:$C,2,FALSE)) | E27: 0 | G27: BILLETES DE 2.000 | H27: 0 | I27: =2000*H27 -> 0
A28: =IF(B28="","",VLOOKUP(B28,PROVEEDORES!$B:$C,2,FALSE)) | E28: 0 | G28: BILLETES DE 5.000 | H28: 0 | I28: =5000*H28 -> 0
A29: =IF(B29="","",VLOOKUP(B29,PROVEEDORES!$B:$C,2,FALSE)) | E29: 0 | G29: BILLETES DE 10.000 | H29: 0 | I29: =10000*H29 -> 0
A30: =IF(B30="","",VLOOKUP(B30,PROVEEDORES!$B:$C,2,FALSE)) | E30: 0 | G30: BILLETES DE 20.000 | H30: 0 | I30: =20000*H30 -> 0
A31: =IF(B31="","",VLOOKUP(B31,PROVEEDORES!$B:$C,2,FALSE)) | E31: 0 | G31: BILLETES DE 50.000 | H31: 0 | I31: =50000*H31 -> 0
A32: =IF(B32="","",VLOOKUP(B32,PROVEEDORES!$B:$C,2,FALSE)) | E32: 0 | G32: BILLETES DE 100.000 | H32: 0 | I32: =100000*H32 -> 0
A33: =IF(B33="","",VLOOKUP(B33,PROVEEDORES!$B:$C,2,FALSE)) | E33: 0 | G33: TOTAL EFECTIVO: | I33: =SUM(I23:I32) -> 0
A34: =IF(B34="","",VLOOKUP(B34,PROVEEDORES!$B:$C,2,FALSE)) | E34: 0 | G34: BASE: | I34: 0
A35: NIT | B35: PROVEEDOR | C35: CONCEPTO | D35: DESCRIPCIÓN | E35: BANCO | G35: TOTAL EFECTIVO MENOS LA BASE: | I35: =I33-I34 -> 0
A36: =IF(B36="","",VLOOKUP(B36,PROVEEDORES!$B:$C,2,FALSE)) | E36: 0
A37: =IF(B37="","",VLOOKUP(B37,PROVEEDORES!$B:$C,2,FALSE)) | E37: 0 | G37: ACUM. DE PROPINA TRANSFERENCIA: | I37: =+'19'!E13 -> 0
A38: =IF(B38="","",VLOOKUP(B38,PROVEEDORES!$B:$C,2,FALSE)) | E38: 0 | G38: ACUMULADO DE PROPINA EN BANCO: | I38: =+'19'!E14 -> 0
A39: =IF(B39="","",VLOOKUP(B39,PROVEEDORES!$B:$C,2,FALSE)) | E39: 0 | G39: ACUMULADO DE PROPINA POR EFECTIVO: | I39: =+'19'!E15 -> 0
A40: =IF(B40="","",VLOOKUP(B40,PROVEEDORES!$B:$C,2,FALSE)) | E40: 0 | G40: ACUMULADO DE TRANSFERENCIA: | I40: =+'19'!E16 -> 0
A41: =IF(B41="","",VLOOKUP(B41,PROVEEDORES!$B:$C,2,FALSE)) | E41: 0 | G41: ACUMULADO DE BANCO: | I41: =+'19'!E17 -> 0
A42: =IF(B42="","",VLOOKUP(B42,PROVEEDORES!$B:$C,2,FALSE)) | E42: 0 | G42: REAL DE BANCO: | I42: =+'19'!E18 -> 0
A43: =IF(B43="","",VLOOKUP(B43,PROVEEDORES!$B:$C,2,FALSE)) | E43: 0 | G43: EFECTIVO ANTERIOR: | I43: =+'19'!E19 -> 0
A44: =IF(B44="","",VLOOKUP(B44,PROVEEDORES!$B:$C,2,FALSE)) | E44: 0
A45: =IF(B45="","",VLOOKUP(B45,PROVEEDORES!$B:$C,2,FALSE)) | E45: 0
A46: =IF(B46="","",VLOOKUP(B46,PROVEEDORES!$B:$C,2,FALSE)) | E46: 0
A47: =IF(B47="","",VLOOKUP(B47,PROVEEDORES!$B:$C,2,FALSE)) | E47: 0
A48: =IF(B48="","",VLOOKUP(B48,PROVEEDORES!$B:$C,2,FALSE)) | E48: 0
A49: =IF(B49="","",VLOOKUP(B49,PROVEEDORES!$B:$C,2,FALSE)) | E49: 0
A50: =IF(B50="","",VLOOKUP(B50,PROVEEDORES!$B:$C,2,FALSE)) | E50: 0
A51: =IF(B51="","",VLOOKUP(B51,PROVEEDORES!$B:$C,2,FALSE)) | E51: 0
A52: =IF(B52="","",VLOOKUP(B52,PROVEEDORES!$B:$C,2,FALSE)) | E52: 0
A53: =IF(B53="","",VLOOKUP(B53,PROVEEDORES!$B:$C,2,FALSE)) | E53: 0
A54: =IF(B54="","",VLOOKUP(B54,PROVEEDORES!$B:$C,2,FALSE)) | E54: 0
A55: =IF(B55="","",VLOOKUP(B55,PROVEEDORES!$B:$C,2,FALSE)) | E55: 0
A56: EGRESO PROPINA | D56: INGRESO DE EFECTIVO
A57: PROPINA TRANSFERENCIA: | C57: 0 | E57: 0
A58: PROPINA BANCO: | C58: 0 | E58: 0
A59: PROPINA EFECTIVO: | C59: 0 | E59: 0

Sheet 21
A1: ='20'!A1+1 -> 21 | B1: =+'1'!B1 -> QUESO Y CAFÉ | D1: =+'20'!D1:E1+1 -> 46163 | G1: CUADRE DE CAJA MAÑANA | I1: CUADRE DE CAJA TARDE
A2: NIT | B2: PROVEEDOR | C2: CONCEPTO | D2: DESCRIPCIÓN | E2: VALOR | G2: PROP. TRANSF.: | H2: 0 | I2: PROP. TRANSF.: | J2: 0
A3: =IF(B3="","",VLOOKUP(B3,PROVEEDORES!$B:$C,2,FALSE)) | E3: 0 | G3: PROP. BANCO: | H3: 0 | I3: PROP. BANCO: | J3: 0
A4: =IF(B4="","",VLOOKUP(B4,PROVEEDORES!$B:$C,2,FALSE)) | E4: 0 | G4: PROP. EFECTIVO: | H4: 0 | I4: PROP. EFECTIVO: | J4: 0
A5: =IF(B5="","",VLOOKUP(B5,PROVEEDORES!$B:$C,2,FALSE)) | E5: 0 | G5: GASTO: | H5: 0 | I5: GASTO: | J5: 0
A6: =IF(B6="","",VLOOKUP(B6,PROVEEDORES!$B:$C,2,FALSE)) | E6: 0 | G6: TRANSFERENCIA: | H6: 0 | I6: TRANSFERENCIA: | J6: 0
A7: =IF(B7="","",VLOOKUP(B7,PROVEEDORES!$B:$C,2,FALSE)) | E7: 0 | G7: BANCO: | H7: 0 | I7: BANCO: | J7: 0
A8: =IF(B8="","",VLOOKUP(B8,PROVEEDORES!$B:$C,2,FALSE)) | E8: 0 | G8: EFECTIVO: | H8: 0 | I8: EFECTIVO: | J8: 0
A9: =IF(B9="","",VLOOKUP(B9,PROVEEDORES!$B:$C,2,FALSE)) | E9: 0 | G9: TOTAL: | H9: =SUM(H5:H8) -> 0 | I9: TOTAL: | J9: =SUM(J5:J8) -> 0
A10: =IF(B10="","",VLOOKUP(B10,PROVEEDORES!$B:$C,2,FALSE)) | E10: 0 | G10: DIFERENCIA: | H10: =+H11-H9 -> 0 | I10: DIFERENCIA: | J10: =+J11-J9 -> 0
A11: =IF(B11="","",VLOOKUP(B11,PROVEEDORES!$B:$C,2,FALSE)) | E11: 0 | G11: TOTAL VENTA: | H11: 0 | I11: TOTAL VENTA: | J11: 0
A12: =IF(B12="","",VLOOKUP(B12,PROVEEDORES!$B:$C,2,FALSE)) | E12: 0
A13: PROPINA TRANSFERENCIA: | C13: =SUM(H2,J2) -> 0 | D13: ACUM. PROPINA TRANFERENCIA: | E13: =SUM(C13,I37)-C57 -> 0 | G13: DIFERENCIA PLANILLA VS CUADRE DE CAJA | I13: =+C20-(SUM(H9,J9)) -> 0
A14: PROPINA POR BANCO: | C14: =SUM(H3,J3) -> 0 | D14: ACUM. PROPINA BANCO: | E14: =SUM(C14,I38)-C58 -> 0
A15: PROPINA EN EFECTIVO: | C15: =SUM(H4,J4) -> 0 | D15: ACUM. PROPINA EFECTIVO: | E15: =SUM(C15,I39)-C59 -> 0 | G15: FACTURAS EN EFECTIVO: | I15: 0
A16: TOTAL EGRESOS: | C16: =SUM(E3:E12) -> 0 | D16: ACUMULADO TRANSFERENCIA: | E16: =SUM(C17,I40) -> 0 | G16: EFECTIVO: | I16: 0
A17: TRANSFERENCIA: | C17: =SUM(H6,J6) -> 0 | D17: ACUMULADO BANCO: | E17: =SUM(C18,I41) -> 0 | G17: TOTAL EFECTIVO REAL ACTUAL: | I17: =SUM(I15,I16) -> 0
A18: BANCO: | C18: =SUM(H7,J7) -> 0 | D18: TOTAL BANCO: | E18: =SUM(C18,I42)-(SUM(E36:E55)) -> 0 | G18: DIFERENCIA: | I18: =+I19-I17 -> 0
A19: EFECTIVO: | C19: =SUM(H8,J8) -> 0 | D19: TOTAL EFECTIVO: | E19: =SUM(C19,E20,E57:E59)-(SUM(E23:E34)) -> 0 | G19: EFECTIVO ACTUAL PLANILLA: | I19: =E19 -> 0
A20: TOTAL VENTA: | C20: =SUM(C16:C19) -> 0 | D20: EFECTIVO ANTERIOR: | E20: =+I43 -> 0
A21: EGRESO DE CAJA MAYOR | G21: CONTEO DE EFECTIVO
A22: NIT | B22: PROVEEDOR | C22: CONCEPTO | D22: DESCRIPCIÓN | E22: EFECTIVO | G22: DENOMINACIÓN | H22: CANTIDAD | I22: EFECTIVO
A23: =IF(B23="","",VLOOKUP(B23,PROVEEDORES!$B:$C,2,FALSE)) | E23: 0 | G23: MONEDAS DE 100 | H23: 0 | I23: =100*H23 -> 0
A24: =IF(B24="","",VLOOKUP(B24,PROVEEDORES!$B:$C,2,FALSE)) | E24: 0 | G24: MONEDAS DE 200 | H24: 0 | I24: =200*H24 -> 0
A25: =IF(B25="","",VLOOKUP(B25,PROVEEDORES!$B:$C,2,FALSE)) | E25: 0 | G25: MONEDAS DE 500 | H25: 0 | I25: =500*H25 -> 0
A26: =IF(B26="","",VLOOKUP(B26,PROVEEDORES!$B:$C,2,FALSE)) | E26: 0 | G26: MONEDAS DE 1.000 | H26: 0 | I26: =1000*H26 -> 0
A27: =IF(B27="","",VLOOKUP(B27,PROVEEDORES!$B:$C,2,FALSE)) | E27: 0 | G27: BILLETES DE 2.000 | H27: 0 | I27: =2000*H27 -> 0
A28: =IF(B28="","",VLOOKUP(B28,PROVEEDORES!$B:$C,2,FALSE)) | E28: 0 | G28: BILLETES DE 5.000 | H28: 0 | I28: =5000*H28 -> 0
A29: =IF(B29="","",VLOOKUP(B29,PROVEEDORES!$B:$C,2,FALSE)) | E29: 0 | G29: BILLETES DE 10.000 | H29: 0 | I29: =10000*H29 -> 0
A30: =IF(B30="","",VLOOKUP(B30,PROVEEDORES!$B:$C,2,FALSE)) | E30: 0 | G30: BILLETES DE 20.000 | H30: 0 | I30: =20000*H30 -> 0
A31: =IF(B31="","",VLOOKUP(B31,PROVEEDORES!$B:$C,2,FALSE)) | E31: 0 | G31: BILLETES DE 50.000 | H31: 0 | I31: =50000*H31 -> 0
A32: =IF(B32="","",VLOOKUP(B32,PROVEEDORES!$B:$C,2,FALSE)) | E32: 0 | G32: BILLETES DE 100.000 | H32: 0 | I32: =100000*H32 -> 0
A33: =IF(B33="","",VLOOKUP(B33,PROVEEDORES!$B:$C,2,FALSE)) | E33: 0 | G33: TOTAL EFECTIVO: | I33: =SUM(I23:I32) -> 0
A34: =IF(B34="","",VLOOKUP(B34,PROVEEDORES!$B:$C,2,FALSE)) | E34: 0 | G34: BASE: | I34: 0
A35: NIT | B35: PROVEEDOR | C35: CONCEPTO | D35: DESCRIPCIÓN | E35: BANCO | G35: TOTAL EFECTIVO MENOS LA BASE: | I35: =I33-I34 -> 0
A36: =IF(B36="","",VLOOKUP(B36,PROVEEDORES!$B:$C,2,FALSE)) | E36: 0
A37: =IF(B37="","",VLOOKUP(B37,PROVEEDORES!$B:$C,2,FALSE)) | E37: 0 | G37: ACUM. DE PROPINA TRANSFERENCIA: | I37: =+'20'!E13 -> 0
A38: =IF(B38="","",VLOOKUP(B38,PROVEEDORES!$B:$C,2,FALSE)) | E38: 0 | G38: ACUMULADO DE PROPINA EN BANCO: | I38: =+'20'!E14 -> 0
A39: =IF(B39="","",VLOOKUP(B39,PROVEEDORES!$B:$C,2,FALSE)) | E39: 0 | G39: ACUMULADO DE PROPINA POR EFECTIVO: | I39: =+'20'!E15 -> 0
A40: =IF(B40="","",VLOOKUP(B40,PROVEEDORES!$B:$C,2,FALSE)) | E40: 0 | G40: ACUMULADO DE TRANSFERENCIA: | I40: =+'20'!E16 -> 0
A41: =IF(B41="","",VLOOKUP(B41,PROVEEDORES!$B:$C,2,FALSE)) | E41: 0 | G41: ACUMULADO DE BANCO: | I41: =+'20'!E17 -> 0
A42: =IF(B42="","",VLOOKUP(B42,PROVEEDORES!$B:$C,2,FALSE)) | E42: 0 | G42: REAL DE BANCO: | I42: =+'20'!E18 -> 0
A43: =IF(B43="","",VLOOKUP(B43,PROVEEDORES!$B:$C,2,FALSE)) | E43: 0 | G43: EFECTIVO ANTERIOR: | I43: =+'20'!E19 -> 0
A44: =IF(B44="","",VLOOKUP(B44,PROVEEDORES!$B:$C,2,FALSE)) | E44: 0
A45: =IF(B45="","",VLOOKUP(B45,PROVEEDORES!$B:$C,2,FALSE)) | E45: 0
A46: =IF(B46="","",VLOOKUP(B46,PROVEEDORES!$B:$C,2,FALSE)) | E46: 0
A47: =IF(B47="","",VLOOKUP(B47,PROVEEDORES!$B:$C,2,FALSE)) | E47: 0
A48: =IF(B48="","",VLOOKUP(B48,PROVEEDORES!$B:$C,2,FALSE)) | E48: 0
A49: =IF(B49="","",VLOOKUP(B49,PROVEEDORES!$B:$C,2,FALSE)) | E49: 0
A50: =IF(B50="","",VLOOKUP(B50,PROVEEDORES!$B:$C,2,FALSE)) | E50: 0
A51: =IF(B51="","",VLOOKUP(B51,PROVEEDORES!$B:$C,2,FALSE)) | E51: 0
A52: =IF(B52="","",VLOOKUP(B52,PROVEEDORES!$B:$C,2,FALSE)) | E52: 0
A53: =IF(B53="","",VLOOKUP(B53,PROVEEDORES!$B:$C,2,FALSE)) | E53: 0
A54: =IF(B54="","",VLOOKUP(B54,PROVEEDORES!$B:$C,2,FALSE)) | E54: 0
A55: =IF(B55="","",VLOOKUP(B55,PROVEEDORES!$B:$C,2,FALSE)) | E55: 0
A56: EGRESO PROPINA | D56: INGRESO DE EFECTIVO
A57: PROPINA TRANSFERENCIA: | C57: 0 | E57: 0
A58: PROPINA BANCO: | C58: 0 | E58: 0
A59: PROPINA EFECTIVO: | C59: 0 | E59: 0

Sheet 22
A1: ='21'!A1+1 -> 22 | B1: =+'1'!B1 -> QUESO Y CAFÉ | D1: =+'21'!D1:E1+1 -> 46164 | G1: CUADRE DE CAJA MAÑANA | I1: CUADRE DE CAJA TARDE
A2: NIT | B2: PROVEEDOR | C2: CONCEPTO | D2: DESCRIPCIÓN | E2: VALOR | G2: PROP. TRANSF.: | H2: 0 | I2: PROP. TRANSF.: | J2: 0
A3: =IF(B3="","",VLOOKUP(B3,PROVEEDORES!$B:$C,2,FALSE)) | E3: 0 | G3: PROP. BANCO: | H3: 0 | I3: PROP. BANCO: | J3: 0
A4: =IF(B4="","",VLOOKUP(B4,PROVEEDORES!$B:$C,2,FALSE)) | E4: 0 | G4: PROP. EFECTIVO: | H4: 0 | I4: PROP. EFECTIVO: | J4: 0
A5: =IF(B5="","",VLOOKUP(B5,PROVEEDORES!$B:$C,2,FALSE)) | E5: 0 | G5: GASTO: | H5: 0 | I5: GASTO: | J5: 0
A6: =IF(B6="","",VLOOKUP(B6,PROVEEDORES!$B:$C,2,FALSE)) | E6: 0 | G6: TRANSFERENCIA: | H6: 0 | I6: TRANSFERENCIA: | J6: 0
A7: =IF(B7="","",VLOOKUP(B7,PROVEEDORES!$B:$C,2,FALSE)) | E7: 0 | G7: BANCO: | H7: 0 | I7: BANCO: | J7: 0
A8: =IF(B8="","",VLOOKUP(B8,PROVEEDORES!$B:$C,2,FALSE)) | E8: 0 | G8: EFECTIVO: | H8: 0 | I8: EFECTIVO: | J8: 0
A9: =IF(B9="","",VLOOKUP(B9,PROVEEDORES!$B:$C,2,FALSE)) | E9: 0 | G9: TOTAL: | H9: =SUM(H5:H8) -> 0 | I9: TOTAL: | J9: =SUM(J5:J8) -> 0
A10: =IF(B10="","",VLOOKUP(B10,PROVEEDORES!$B:$C,2,FALSE)) | E10: 0 | G10: DIFERENCIA: | H10: =+H11-H9 -> 0 | I10: DIFERENCIA: | J10: =+J11-J9 -> 0
A11: =IF(B11="","",VLOOKUP(B11,PROVEEDORES!$B:$C,2,FALSE)) | E11: 0 | G11: TOTAL VENTA: | H11: 0 | I11: TOTAL VENTA: | J11: 0
A12: =IF(B12="","",VLOOKUP(B12,PROVEEDORES!$B:$C,2,FALSE)) | E12: 0
A13: PROPINA TRANSFERENCIA: | C13: =SUM(H2,J2) -> 0 | D13: ACUM. PROPINA TRANFERENCIA: | E13: =SUM(C13,I37)-C57 -> 0 | G13: DIFERENCIA PLANILLA VS CUADRE DE CAJA | I13: =+C20-(SUM(H9,J9)) -> 0
A14: PROPINA POR BANCO: | C14: =SUM(H3,J3) -> 0 | D14: ACUM. PROPINA BANCO: | E14: =SUM(C14,I38)-C58 -> 0
A15: PROPINA EN EFECTIVO: | C15: =SUM(H4,J4) -> 0 | D15: ACUM. PROPINA EFECTIVO: | E15: =SUM(C15,I39)-C59 -> 0 | G15: FACTURAS EN EFECTIVO: | I15: 0
A16: TOTAL EGRESOS: | C16: =SUM(E3:E12) -> 0 | D16: ACUMULADO TRANSFERENCIA: | E16: =SUM(C17,I40) -> 0 | G16: EFECTIVO: | I16: 0
A17: TRANSFERENCIA: | C17: =SUM(H6,J6) -> 0 | D17: ACUMULADO BANCO: | E17: =SUM(C18,I41) -> 0 | G17: TOTAL EFECTIVO REAL ACTUAL: | I17: =SUM(I15,I16) -> 0
A18: BANCO: | C18: =SUM(H7,J7) -> 0 | D18: TOTAL BANCO: | E18: =SUM(C18,I42)-(SUM(E36:E55)) -> 0 | G18: DIFERENCIA: | I18: =+I19-I17 -> 0
A19: EFECTIVO: | C19: =SUM(H8,J8) -> 0 | D19: TOTAL EFECTIVO: | E19: =SUM(C19,E20,E57:E59)-(SUM(E23:E34)) -> 0 | G19: EFECTIVO ACTUAL PLANILLA: | I19: =E19 -> 0
A20: TOTAL VENTA: | C20: =SUM(C16:C19) -> 0 | D20: EFECTIVO ANTERIOR: | E20: =+I43 -> 0
A21: EGRESO DE CAJA MAYOR | G21: CONTEO DE EFECTIVO
A22: NIT | B22: PROVEEDOR | C22: CONCEPTO | D22: DESCRIPCIÓN | E22: EFECTIVO | G22: DENOMINACIÓN | H22: CANTIDAD | I22: EFECTIVO
A23: =IF(B23="","",VLOOKUP(B23,PROVEEDORES!$B:$C,2,FALSE)) | E23: 0 | G23: MONEDAS DE 100 | H23: 0 | I23: =100*H23 -> 0
A24: =IF(B24="","",VLOOKUP(B24,PROVEEDORES!$B:$C,2,FALSE)) | E24: 0 | G24: MONEDAS DE 200 | H24: 0 | I24: =200*H24 -> 0
A25: =IF(B25="","",VLOOKUP(B25,PROVEEDORES!$B:$C,2,FALSE)) | E25: 0 | G25: MONEDAS DE 500 | H25: 0 | I25: =500*H25 -> 0
A26: =IF(B26="","",VLOOKUP(B26,PROVEEDORES!$B:$C,2,FALSE)) | E26: 0 | G26: MONEDAS DE 1.000 | H26: 0 | I26: =1000*H26 -> 0
A27: =IF(B27="","",VLOOKUP(B27,PROVEEDORES!$B:$C,2,FALSE)) | E27: 0 | G27: BILLETES DE 2.000 | H27: 0 | I27: =2000*H27 -> 0
A28: =IF(B28="","",VLOOKUP(B28,PROVEEDORES!$B:$C,2,FALSE)) | E28: 0 | G28: BILLETES DE 5.000 | H28: 0 | I28: =5000*H28 -> 0
A29: =IF(B29="","",VLOOKUP(B29,PROVEEDORES!$B:$C,2,FALSE)) | E29: 0 | G29: BILLETES DE 10.000 | H29: 0 | I29: =10000*H29 -> 0
A30: =IF(B30="","",VLOOKUP(B30,PROVEEDORES!$B:$C,2,FALSE)) | E30: 0 | G30: BILLETES DE 20.000 | H30: 0 | I30: =20000*H30 -> 0
A31: =IF(B31="","",VLOOKUP(B31,PROVEEDORES!$B:$C,2,FALSE)) | E31: 0 | G31: BILLETES DE 50.000 | H31: 0 | I31: =50000*H31 -> 0
A32: =IF(B32="","",VLOOKUP(B32,PROVEEDORES!$B:$C,2,FALSE)) | E32: 0 | G32: BILLETES DE 100.000 | H32: 0 | I32: =100000*H32 -> 0
A33: =IF(B33="","",VLOOKUP(B33,PROVEEDORES!$B:$C,2,FALSE)) | E33: 0 | G33: TOTAL EFECTIVO: | I33: =SUM(I23:I32) -> 0
A34: =IF(B34="","",VLOOKUP(B34,PROVEEDORES!$B:$C,2,FALSE)) | E34: 0 | G34: BASE: | I34: 0
A35: NIT | B35: PROVEEDOR | C35: CONCEPTO | D35: DESCRIPCIÓN | E35: BANCO | G35: TOTAL EFECTIVO MENOS LA BASE: | I35: =I33-I34 -> 0
A36: =IF(B36="","",VLOOKUP(B36,PROVEEDORES!$B:$C,2,FALSE)) | E36: 0
A37: =IF(B37="","",VLOOKUP(B37,PROVEEDORES!$B:$C,2,FALSE)) | E37: 0 | G37: ACUM. DE PROPINA TRANSFERENCIA: | I37: =+'21'!E13 -> 0
A38: =IF(B38="","",VLOOKUP(B38,PROVEEDORES!$B:$C,2,FALSE)) | E38: 0 | G38: ACUMULADO DE PROPINA EN BANCO: | I38: =+'21'!E14 -> 0
A39: =IF(B39="","",VLOOKUP(B39,PROVEEDORES!$B:$C,2,FALSE)) | E39: 0 | G39: ACUMULADO DE PROPINA POR EFECTIVO: | I39: =+'21'!E15 -> 0
A40: =IF(B40="","",VLOOKUP(B40,PROVEEDORES!$B:$C,2,FALSE)) | E40: 0 | G40: ACUMULADO DE TRANSFERENCIA: | I40: =+'21'!E16 -> 0
A41: =IF(B41="","",VLOOKUP(B41,PROVEEDORES!$B:$C,2,FALSE)) | E41: 0 | G41: ACUMULADO DE BANCO: | I41: =+'21'!E17 -> 0
A42: =IF(B42="","",VLOOKUP(B42,PROVEEDORES!$B:$C,2,FALSE)) | E42: 0 | G42: REAL DE BANCO: | I42: =+'21'!E18 -> 0
A43: =IF(B43="","",VLOOKUP(B43,PROVEEDORES!$B:$C,2,FALSE)) | E43: 0 | G43: EFECTIVO ANTERIOR: | I43: =+'21'!E19 -> 0
A44: =IF(B44="","",VLOOKUP(B44,PROVEEDORES!$B:$C,2,FALSE)) | E44: 0
A45: =IF(B45="","",VLOOKUP(B45,PROVEEDORES!$B:$C,2,FALSE)) | E45: 0
A46: =IF(B46="","",VLOOKUP(B46,PROVEEDORES!$B:$C,2,FALSE)) | E46: 0
A47: =IF(B47="","",VLOOKUP(B47,PROVEEDORES!$B:$C,2,FALSE)) | E47: 0
A48: =IF(B48="","",VLOOKUP(B48,PROVEEDORES!$B:$C,2,FALSE)) | E48: 0
A49: =IF(B49="","",VLOOKUP(B49,PROVEEDORES!$B:$C,2,FALSE)) | E49: 0
A50: =IF(B50="","",VLOOKUP(B50,PROVEEDORES!$B:$C,2,FALSE)) | E50: 0
A51: =IF(B51="","",VLOOKUP(B51,PROVEEDORES!$B:$C,2,FALSE)) | E51: 0
A52: =IF(B52="","",VLOOKUP(B52,PROVEEDORES!$B:$C,2,FALSE)) | E52: 0
A53: =IF(B53="","",VLOOKUP(B53,PROVEEDORES!$B:$C,2,FALSE)) | E53: 0
A54: =IF(B54="","",VLOOKUP(B54,PROVEEDORES!$B:$C,2,FALSE)) | E54: 0
A55: =IF(B55="","",VLOOKUP(B55,PROVEEDORES!$B:$C,2,FALSE)) | E55: 0
A56: EGRESO PROPINA | D56: INGRESO DE EFECTIVO
A57: PROPINA TRANSFERENCIA: | C57: 0 | E57: 0
A58: PROPINA BANCO: | C58: 0 | E58: 0
A59: PROPINA EFECTIVO: | C59: 0 | E59: 0

Sheet 23
A1: ='22'!A1+1 -> 23 | B1: =+'1'!B1 -> QUESO Y CAFÉ | D1: =+'22'!D1:E1+1 -> 46165 | G1: CUADRE DE CAJA MAÑANA | I1: CUADRE DE CAJA TARDE
A2: NIT | B2: PROVEEDOR | C2: CONCEPTO | D2: DESCRIPCIÓN | E2: VALOR | G2: PROP. TRANSF.: | H2: 0 | I2: PROP. TRANSF.: | J2: 0
A3: =IF(B3="","",VLOOKUP(B3,PROVEEDORES!$B:$C,2,FALSE)) | E3: 0 | G3: PROP. BANCO: | H3: 0 | I3: PROP. BANCO: | J3: 0
A4: =IF(B4="","",VLOOKUP(B4,PROVEEDORES!$B:$C,2,FALSE)) | E4: 0 | G4: PROP. EFECTIVO: | H4: 0 | I4: PROP. EFECTIVO: | J4: 0
A5: =IF(B5="","",VLOOKUP(B5,PROVEEDORES!$B:$C,2,FALSE)) | E5: 0 | G5: GASTO: | H5: 0 | I5: GASTO: | J5: 0
A6: =IF(B6="","",VLOOKUP(B6,PROVEEDORES!$B:$C,2,FALSE)) | E6: 0 | G6: TRANSFERENCIA: | H6: 0 | I6: TRANSFERENCIA: | J6: 0
A7: =IF(B7="","",VLOOKUP(B7,PROVEEDORES!$B:$C,2,FALSE)) | E7: 0 | G7: BANCO: | H7: 0 | I7: BANCO: | J7: 0
A8: =IF(B8="","",VLOOKUP(B8,PROVEEDORES!$B:$C,2,FALSE)) | E8: 0 | G8: EFECTIVO: | H8: 0 | I8: EFECTIVO: | J8: 0
A9: =IF(B9="","",VLOOKUP(B9,PROVEEDORES!$B:$C,2,FALSE)) | E9: 0 | G9: TOTAL: | H9: =SUM(H5:H8) -> 0 | I9: TOTAL: | J9: =SUM(J5:J8) -> 0
A10: =IF(B10="","",VLOOKUP(B10,PROVEEDORES!$B:$C,2,FALSE)) | E10: 0 | G10: DIFERENCIA: | H10: =+H11-H9 -> 0 | I10: DIFERENCIA: | J10: =+J11-J9 -> 0
A11: =IF(B11="","",VLOOKUP(B11,PROVEEDORES!$B:$C,2,FALSE)) | E11: 0 | G11: TOTAL VENTA: | H11: 0 | I11: TOTAL VENTA: | J11: 0
A12: =IF(B12="","",VLOOKUP(B12,PROVEEDORES!$B:$C,2,FALSE)) | E12: 0
A13: PROPINA TRANSFERENCIA: | C13: =SUM(H2,J2) -> 0 | D13: ACUM. PROPINA TRANFERENCIA: | E13: =SUM(C13,I37)-C57 -> 0 | G13: DIFERENCIA PLANILLA VS CUADRE DE CAJA | I13: =+C20-(SUM(H9,J9)) -> 0
A14: PROPINA POR BANCO: | C14: =SUM(H3,J3) -> 0 | D14: ACUM. PROPINA BANCO: | E14: =SUM(C14,I38)-C58 -> 0
A15: PROPINA EN EFECTIVO: | C15: =SUM(H4,J4) -> 0 | D15: ACUM. PROPINA EFECTIVO: | E15: =SUM(C15,I39)-C59 -> 0 | G15: FACTURAS EN EFECTIVO: | I15: 0
A16: TOTAL EGRESOS: | C16: =SUM(E3:E12) -> 0 | D16: ACUMULADO TRANSFERENCIA: | E16: =SUM(C17,I40) -> 0 | G16: EFECTIVO: | I16: 0
A17: TRANSFERENCIA: | C17: =SUM(H6,J6) -> 0 | D17: ACUMULADO BANCO: | E17: =SUM(C18,I41) -> 0 | G17: TOTAL EFECTIVO REAL ACTUAL: | I17: =SUM(I15,I16) -> 0
A18: BANCO: | C18: =SUM(H7,J7) -> 0 | D18: TOTAL BANCO: | E18: =SUM(C18,I42)-(SUM(E36:E55)) -> 0 | G18: DIFERENCIA: | I18: =+I19-I17 -> 0
A19: EFECTIVO: | C19: =SUM(H8,J8) -> 0 | D19: TOTAL EFECTIVO: | E19: =SUM(C19,E20,E57:E59)-(SUM(E23:E34)) -> 0 | G19: EFECTIVO ACTUAL PLANILLA: | I19: =E19 -> 0
A20: TOTAL VENTA: | C20: =SUM(C16:C19) -> 0 | D20: EFECTIVO ANTERIOR: | E20: =+I43 -> 0
A21: EGRESO DE CAJA MAYOR | G21: CONTEO DE EFECTIVO
A22: NIT | B22: PROVEEDOR | C22: CONCEPTO | D22: DESCRIPCIÓN | E22: EFECTIVO | G22: DENOMINACIÓN | H22: CANTIDAD | I22: EFECTIVO
A23: =IF(B23="","",VLOOKUP(B23,PROVEEDORES!$B:$C,2,FALSE)) | E23: 0 | G23: MONEDAS DE 100 | H23: 0 | I23: =100*H23 -> 0
A24: =IF(B24="","",VLOOKUP(B24,PROVEEDORES!$B:$C,2,FALSE)) | E24: 0 | G24: MONEDAS DE 200 | H24: 0 | I24: =200*H24 -> 0
A25: =IF(B25="","",VLOOKUP(B25,PROVEEDORES!$B:$C,2,FALSE)) | E25: 0 | G25: MONEDAS DE 500 | H25: 0 | I25: =500*H25 -> 0
A26: =IF(B26="","",VLOOKUP(B26,PROVEEDORES!$B:$C,2,FALSE)) | E26: 0 | G26: MONEDAS DE 1.000 | H26: 0 | I26: =1000*H26 -> 0
A27: =IF(B27="","",VLOOKUP(B27,PROVEEDORES!$B:$C,2,FALSE)) | E27: 0 | G27: BILLETES DE 2.000 | H27: 0 | I27: =2000*H27 -> 0
A28: =IF(B28="","",VLOOKUP(B28,PROVEEDORES!$B:$C,2,FALSE)) | E28: 0 | G28: BILLETES DE 5.000 | H28: 0 | I28: =5000*H28 -> 0
A29: =IF(B29="","",VLOOKUP(B29,PROVEEDORES!$B:$C,2,FALSE)) | E29: 0 | G29: BILLETES DE 10.000 | H29: 0 | I29: =10000*H29 -> 0
A30: =IF(B30="","",VLOOKUP(B30,PROVEEDORES!$B:$C,2,FALSE)) | E30: 0 | G30: BILLETES DE 20.000 | H30: 0 | I30: =20000*H30 -> 0
A31: =IF(B31="","",VLOOKUP(B31,PROVEEDORES!$B:$C,2,FALSE)) | E31: 0 | G31: BILLETES DE 50.000 | H31: 0 | I31: =50000*H31 -> 0
A32: =IF(B32="","",VLOOKUP(B32,PROVEEDORES!$B:$C,2,FALSE)) | E32: 0 | G32: BILLETES DE 100.000 | H32: 0 | I32: =100000*H32 -> 0
A33: =IF(B33="","",VLOOKUP(B33,PROVEEDORES!$B:$C,2,FALSE)) | E33: 0 | G33: TOTAL EFECTIVO: | I33: =SUM(I23:I32) -> 0
A34: =IF(B34="","",VLOOKUP(B34,PROVEEDORES!$B:$C,2,FALSE)) | E34: 0 | G34: BASE: | I34: 0
A35: NIT | B35: PROVEEDOR | C35: CONCEPTO | D35: DESCRIPCIÓN | E35: BANCO | G35: TOTAL EFECTIVO MENOS LA BASE: | I35: =I33-I34 -> 0
A36: =IF(B36="","",VLOOKUP(B36,PROVEEDORES!$B:$C,2,FALSE)) | E36: 0
A37: =IF(B37="","",VLOOKUP(B37,PROVEEDORES!$B:$C,2,FALSE)) | E37: 0 | G37: ACUM. DE PROPINA TRANSFERENCIA: | I37: =+'22'!E13 -> 0
A38: =IF(B38="","",VLOOKUP(B38,PROVEEDORES!$B:$C,2,FALSE)) | E38: 0 | G38: ACUMULADO DE PROPINA EN BANCO: | I38: =+'22'!E14 -> 0
A39: =IF(B39="","",VLOOKUP(B39,PROVEEDORES!$B:$C,2,FALSE)) | E39: 0 | G39: ACUMULADO DE PROPINA POR EFECTIVO: | I39: =+'22'!E15 -> 0
A40: =IF(B40="","",VLOOKUP(B40,PROVEEDORES!$B:$C,2,FALSE)) | E40: 0 | G40: ACUMULADO DE TRANSFERENCIA: | I40: =+'22'!E16 -> 0
A41: =IF(B41="","",VLOOKUP(B41,PROVEEDORES!$B:$C,2,FALSE)) | E41: 0 | G41: ACUMULADO DE BANCO: | I41: =+'22'!E17 -> 0
A42: =IF(B42="","",VLOOKUP(B42,PROVEEDORES!$B:$C,2,FALSE)) | E42: 0 | G42: REAL DE BANCO: | I42: =+'22'!E18 -> 0
A43: =IF(B43="","",VLOOKUP(B43,PROVEEDORES!$B:$C,2,FALSE)) | E43: 0 | G43: EFECTIVO ANTERIOR: | I43: =+'22'!E19 -> 0
A44: =IF(B44="","",VLOOKUP(B44,PROVEEDORES!$B:$C,2,FALSE)) | E44: 0
A45: =IF(B45="","",VLOOKUP(B45,PROVEEDORES!$B:$C,2,FALSE)) | E45: 0
A46: =IF(B46="","",VLOOKUP(B46,PROVEEDORES!$B:$C,2,FALSE)) | E46: 0
A47: =IF(B47="","",VLOOKUP(B47,PROVEEDORES!$B:$C,2,FALSE)) | E47: 0
A48: =IF(B48="","",VLOOKUP(B48,PROVEEDORES!$B:$C,2,FALSE)) | E48: 0
A49: =IF(B49="","",VLOOKUP(B49,PROVEEDORES!$B:$C,2,FALSE)) | E49: 0
A50: =IF(B50="","",VLOOKUP(B50,PROVEEDORES!$B:$C,2,FALSE)) | E50: 0
A51: =IF(B51="","",VLOOKUP(B51,PROVEEDORES!$B:$C,2,FALSE)) | E51: 0
A52: =IF(B52="","",VLOOKUP(B52,PROVEEDORES!$B:$C,2,FALSE)) | E52: 0
A53: =IF(B53="","",VLOOKUP(B53,PROVEEDORES!$B:$C,2,FALSE)) | E53: 0
A54: =IF(B54="","",VLOOKUP(B54,PROVEEDORES!$B:$C,2,FALSE)) | E54: 0
A55: =IF(B55="","",VLOOKUP(B55,PROVEEDORES!$B:$C,2,FALSE)) | E55: 0
A56: EGRESO PROPINA | D56: INGRESO DE EFECTIVO
A57: PROPINA TRANSFERENCIA: | C57: 0 | E57: 0
A58: PROPINA BANCO: | C58: 0 | E58: 0
A59: PROPINA EFECTIVO: | C59: 0 | E59: 0

Sheet 24
A1: ='23'!A1+1 -> 24 | B1: =+'1'!B1 -> QUESO Y CAFÉ | D1: =+'23'!D1:E1+1 -> 46166 | G1: CUADRE DE CAJA MAÑANA | I1: CUADRE DE CAJA TARDE
A2: NIT | B2: PROVEEDOR | C2: CONCEPTO | D2: DESCRIPCIÓN | E2: VALOR | G2: PROP. TRANSF.: | H2: 0 | I2: PROP. TRANSF.: | J2: 0
A3: =IF(B3="","",VLOOKUP(B3,PROVEEDORES!$B:$C,2,FALSE)) | E3: 0 | G3: PROP. BANCO: | H3: 0 | I3: PROP. BANCO: | J3: 0
A4: =IF(B4="","",VLOOKUP(B4,PROVEEDORES!$B:$C,2,FALSE)) | E4: 0 | G4: PROP. EFECTIVO: | H4: 0 | I4: PROP. EFECTIVO: | J4: 0
A5: =IF(B5="","",VLOOKUP(B5,PROVEEDORES!$B:$C,2,FALSE)) | E5: 0 | G5: GASTO: | H5: 0 | I5: GASTO: | J5: 0
A6: =IF(B6="","",VLOOKUP(B6,PROVEEDORES!$B:$C,2,FALSE)) | E6: 0 | G6: TRANSFERENCIA: | H6: 0 | I6: TRANSFERENCIA: | J6: 0
A7: =IF(B7="","",VLOOKUP(B7,PROVEEDORES!$B:$C,2,FALSE)) | E7: 0 | G7: BANCO: | H7: 0 | I7: BANCO: | J7: 0
A8: =IF(B8="","",VLOOKUP(B8,PROVEEDORES!$B:$C,2,FALSE)) | E8: 0 | G8: EFECTIVO: | H8: 0 | I8: EFECTIVO: | J8: 0
A9: =IF(B9="","",VLOOKUP(B9,PROVEEDORES!$B:$C,2,FALSE)) | E9: 0 | G9: TOTAL: | H9: =SUM(H5:H8) -> 0 | I9: TOTAL: | J9: =SUM(J5:J8) -> 0
A10: =IF(B10="","",VLOOKUP(B10,PROVEEDORES!$B:$C,2,FALSE)) | E10: 0 | G10: DIFERENCIA: | H10: =+H11-H9 -> 0 | I10: DIFERENCIA: | J10: =+J11-J9 -> 0
A11: =IF(B11="","",VLOOKUP(B11,PROVEEDORES!$B:$C,2,FALSE)) | E11: 0 | G11: TOTAL VENTA: | H11: 0 | I11: TOTAL VENTA: | J11: 0
A12: =IF(B12="","",VLOOKUP(B12,PROVEEDORES!$B:$C,2,FALSE)) | E12: 0
A13: PROPINA TRANSFERENCIA: | C13: =SUM(H2,J2) -> 0 | D13: ACUM. PROPINA TRANFERENCIA: | E13: =SUM(C13,I37)-C57 -> 0 | G13: DIFERENCIA PLANILLA VS CUADRE DE CAJA | I13: =+C20-(SUM(H9,J9)) -> 0
A14: PROPINA POR BANCO: | C14: =SUM(H3,J3) -> 0 | D14: ACUM. PROPINA BANCO: | E14: =SUM(C14,I38)-C58 -> 0
A15: PROPINA EN EFECTIVO: | C15: =SUM(H4,J4) -> 0 | D15: ACUM. PROPINA EFECTIVO: | E15: =SUM(C15,I39)-C59 -> 0 | G15: FACTURAS EN EFECTIVO: | I15: 0
A16: TOTAL EGRESOS: | C16: =SUM(E3:E12) -> 0 | D16: ACUMULADO TRANSFERENCIA: | E16: =SUM(C17,I40) -> 0 | G16: EFECTIVO: | I16: 0
A17: TRANSFERENCIA: | C17: =SUM(H6,J6) -> 0 | D17: ACUMULADO BANCO: | E17: =SUM(C18,I41) -> 0 | G17: TOTAL EFECTIVO REAL ACTUAL: | I17: =SUM(I15,I16) -> 0
A18: BANCO: | C18: =SUM(H7,J7) -> 0 | D18: TOTAL BANCO: | E18: =SUM(C18,I42)-(SUM(E36:E55)) -> 0 | G18: DIFERENCIA: | I18: =+I19-I17 -> 0
A19: EFECTIVO: | C19: =SUM(H8,J8) -> 0 | D19: TOTAL EFECTIVO: | E19: =SUM(C19,E20,E57:E59)-(SUM(E23:E34)) -> 0 | G19: EFECTIVO ACTUAL PLANILLA: | I19: =E19 -> 0
A20: TOTAL VENTA: | C20: =SUM(C16:C19) -> 0 | D20: EFECTIVO ANTERIOR: | E20: =+I43 -> 0
A21: EGRESO DE CAJA MAYOR | G21: CONTEO DE EFECTIVO
A22: NIT | B22: PROVEEDOR | C22: CONCEPTO | D22: DESCRIPCIÓN | E22: EFECTIVO | G22: DENOMINACIÓN | H22: CANTIDAD | I22: EFECTIVO
A23: =IF(B23="","",VLOOKUP(B23,PROVEEDORES!$B:$C,2,FALSE)) | E23: 0 | G23: MONEDAS DE 100 | H23: 0 | I23: =100*H23 -> 0
A24: =IF(B24="","",VLOOKUP(B24,PROVEEDORES!$B:$C,2,FALSE)) | E24: 0 | G24: MONEDAS DE 200 | H24: 0 | I24: =200*H24 -> 0
A25: =IF(B25="","",VLOOKUP(B25,PROVEEDORES!$B:$C,2,FALSE)) | E25: 0 | G25: MONEDAS DE 500 | H25: 0 | I25: =500*H25 -> 0
A26: =IF(B26="","",VLOOKUP(B26,PROVEEDORES!$B:$C,2,FALSE)) | E26: 0 | G26: MONEDAS DE 1.000 | H26: 0 | I26: =1000*H26 -> 0
A27: =IF(B27="","",VLOOKUP(B27,PROVEEDORES!$B:$C,2,FALSE)) | E27: 0 | G27: BILLETES DE 2.000 | H27: 0 | I27: =2000*H27 -> 0
A28: =IF(B28="","",VLOOKUP(B28,PROVEEDORES!$B:$C,2,FALSE)) | E28: 0 | G28: BILLETES DE 5.000 | H28: 0 | I28: =5000*H28 -> 0
A29: =IF(B29="","",VLOOKUP(B29,PROVEEDORES!$B:$C,2,FALSE)) | E29: 0 | G29: BILLETES DE 10.000 | H29: 0 | I29: =10000*H29 -> 0
A30: =IF(B30="","",VLOOKUP(B30,PROVEEDORES!$B:$C,2,FALSE)) | E30: 0 | G30: BILLETES DE 20.000 | H30: 0 | I30: =20000*H30 -> 0
A31: =IF(B31="","",VLOOKUP(B31,PROVEEDORES!$B:$C,2,FALSE)) | E31: 0 | G31: BILLETES DE 50.000 | H31: 0 | I31: =50000*H31 -> 0
A32: =IF(B32="","",VLOOKUP(B32,PROVEEDORES!$B:$C,2,FALSE)) | E32: 0 | G32: BILLETES DE 100.000 | H32: 0 | I32: =100000*H32 -> 0
A33: =IF(B33="","",VLOOKUP(B33,PROVEEDORES!$B:$C,2,FALSE)) | E33: 0 | G33: TOTAL EFECTIVO: | I33: =SUM(I23:I32) -> 0
A34: =IF(B34="","",VLOOKUP(B34,PROVEEDORES!$B:$C,2,FALSE)) | E34: 0 | G34: BASE: | I34: 0
A35: NIT | B35: PROVEEDOR | C35: CONCEPTO | D35: DESCRIPCIÓN | E35: BANCO | G35: TOTAL EFECTIVO MENOS LA BASE: | I35: =I33-I34 -> 0
A36: =IF(B36="","",VLOOKUP(B36,PROVEEDORES!$B:$C,2,FALSE)) | E36: 0
A37: =IF(B37="","",VLOOKUP(B37,PROVEEDORES!$B:$C,2,FALSE)) | E37: 0 | G37: ACUM. DE PROPINA TRANSFERENCIA: | I37: =+'23'!E13 -> 0
A38: =IF(B38="","",VLOOKUP(B38,PROVEEDORES!$B:$C,2,FALSE)) | E38: 0 | G38: ACUMULADO DE PROPINA EN BANCO: | I38: =+'23'!E14 -> 0
A39: =IF(B39="","",VLOOKUP(B39,PROVEEDORES!$B:$C,2,FALSE)) | E39: 0 | G39: ACUMULADO DE PROPINA POR EFECTIVO: | I39: =+'23'!E15 -> 0
A40: =IF(B40="","",VLOOKUP(B40,PROVEEDORES!$B:$C,2,FALSE)) | E40: 0 | G40: ACUMULADO DE TRANSFERENCIA: | I40: =+'23'!E16 -> 0
A41: =IF(B41="","",VLOOKUP(B41,PROVEEDORES!$B:$C,2,FALSE)) | E41: 0 | G41: ACUMULADO DE BANCO: | I41: =+'23'!E17 -> 0
A42: =IF(B42="","",VLOOKUP(B42,PROVEEDORES!$B:$C,2,FALSE)) | E42: 0 | G42: REAL DE BANCO: | I42: =+'23'!E18 -> 0
A43: =IF(B43="","",VLOOKUP(B43,PROVEEDORES!$B:$C,2,FALSE)) | E43: 0 | G43: EFECTIVO ANTERIOR: | I43: =+'23'!E19 -> 0
A44: =IF(B44="","",VLOOKUP(B44,PROVEEDORES!$B:$C,2,FALSE)) | E44: 0
A45: =IF(B45="","",VLOOKUP(B45,PROVEEDORES!$B:$C,2,FALSE)) | E45: 0
A46: =IF(B46="","",VLOOKUP(B46,PROVEEDORES!$B:$C,2,FALSE)) | E46: 0
A47: =IF(B47="","",VLOOKUP(B47,PROVEEDORES!$B:$C,2,FALSE)) | E47: 0
A48: =IF(B48="","",VLOOKUP(B48,PROVEEDORES!$B:$C,2,FALSE)) | E48: 0
A49: =IF(B49="","",VLOOKUP(B49,PROVEEDORES!$B:$C,2,FALSE)) | E49: 0
A50: =IF(B50="","",VLOOKUP(B50,PROVEEDORES!$B:$C,2,FALSE)) | E50: 0
A51: =IF(B51="","",VLOOKUP(B51,PROVEEDORES!$B:$C,2,FALSE)) | E51: 0
A52: =IF(B52="","",VLOOKUP(B52,PROVEEDORES!$B:$C,2,FALSE)) | E52: 0
A53: =IF(B53="","",VLOOKUP(B53,PROVEEDORES!$B:$C,2,FALSE)) | E53: 0
A54: =IF(B54="","",VLOOKUP(B54,PROVEEDORES!$B:$C,2,FALSE)) | E54: 0
A55: =IF(B55="","",VLOOKUP(B55,PROVEEDORES!$B:$C,2,FALSE)) | E55: 0
A56: EGRESO PROPINA | D56: INGRESO DE EFECTIVO
A57: PROPINA TRANSFERENCIA: | C57: 0 | E57: 0
A58: PROPINA BANCO: | C58: 0 | E58: 0
A59: PROPINA EFECTIVO: | C59: 0 | E59: 0

Sheet 25
A1: ='24'!A1+1 -> 25 | B1: =+'1'!B1 -> QUESO Y CAFÉ | D1: =+'24'!D1:E1+1 -> 46167 | G1: CUADRE DE CAJA MAÑANA | I1: CUADRE DE CAJA TARDE
A2: NIT | B2: PROVEEDOR | C2: CONCEPTO | D2: DESCRIPCIÓN | E2: VALOR | G2: PROP. TRANSF.: | H2: 0 | I2: PROP. TRANSF.: | J2: 0
A3: =IF(B3="","",VLOOKUP(B3,PROVEEDORES!$B:$C,2,FALSE)) | E3: 0 | G3: PROP. BANCO: | H3: 0 | I3: PROP. BANCO: | J3: 0
A4: =IF(B4="","",VLOOKUP(B4,PROVEEDORES!$B:$C,2,FALSE)) | E4: 0 | G4: PROP. EFECTIVO: | H4: 0 | I4: PROP. EFECTIVO: | J4: 0
A5: =IF(B5="","",VLOOKUP(B5,PROVEEDORES!$B:$C,2,FALSE)) | E5: 0 | G5: GASTO: | H5: 0 | I5: GASTO: | J5: 0
A6: =IF(B6="","",VLOOKUP(B6,PROVEEDORES!$B:$C,2,FALSE)) | E6: 0 | G6: TRANSFERENCIA: | H6: 0 | I6: TRANSFERENCIA: | J6: 0
A7: =IF(B7="","",VLOOKUP(B7,PROVEEDORES!$B:$C,2,FALSE)) | E7: 0 | G7: BANCO: | H7: 0 | I7: BANCO: | J7: 0
A8: =IF(B8="","",VLOOKUP(B8,PROVEEDORES!$B:$C,2,FALSE)) | E8: 0 | G8: EFECTIVO: | H8: 0 | I8: EFECTIVO: | J8: 0
A9: =IF(B9="","",VLOOKUP(B9,PROVEEDORES!$B:$C,2,FALSE)) | E9: 0 | G9: TOTAL: | H9: =SUM(H5:H8) -> 0 | I9: TOTAL: | J9: =SUM(J5:J8) -> 0
A10: =IF(B10="","",VLOOKUP(B10,PROVEEDORES!$B:$C,2,FALSE)) | E10: 0 | G10: DIFERENCIA: | H10: =+H11-H9 -> 0 | I10: DIFERENCIA: | J10: =+J11-J9 -> 0
A11: =IF(B11="","",VLOOKUP(B11,PROVEEDORES!$B:$C,2,FALSE)) | E11: 0 | G11: TOTAL VENTA: | H11: 0 | I11: TOTAL VENTA: | J11: 0
A12: =IF(B12="","",VLOOKUP(B12,PROVEEDORES!$B:$C,2,FALSE)) | E12: 0
A13: PROPINA TRANSFERENCIA: | C13: =SUM(H2,J2) -> 0 | D13: ACUM. PROPINA TRANFERENCIA: | E13: =SUM(C13,I37)-C57 -> 0 | G13: DIFERENCIA PLANILLA VS CUADRE DE CAJA | I13: =+C20-(SUM(H9,J9)) -> 0
A14: PROPINA POR BANCO: | C14: =SUM(H3,J3) -> 0 | D14: ACUM. PROPINA BANCO: | E14: =SUM(C14,I38)-C58 -> 0
A15: PROPINA EN EFECTIVO: | C15: =SUM(H4,J4) -> 0 | D15: ACUM. PROPINA EFECTIVO: | E15: =SUM(C15,I39)-C59 -> 0 | G15: FACTURAS EN EFECTIVO: | I15: 0
A16: TOTAL EGRESOS: | C16: =SUM(E3:E12) -> 0 | D16: ACUMULADO TRANSFERENCIA: | E16: =SUM(C17,I40) -> 0 | G16: EFECTIVO: | I16: 0
A17: TRANSFERENCIA: | C17: =SUM(H6,J6) -> 0 | D17: ACUMULADO BANCO: | E17: =SUM(C18,I41) -> 0 | G17: TOTAL EFECTIVO REAL ACTUAL: | I17: =SUM(I15,I16) -> 0
A18: BANCO: | C18: =SUM(H7,J7) -> 0 | D18: TOTAL BANCO: | E18: =SUM(C18,I42)-(SUM(E36:E55)) -> 0 | G18: DIFERENCIA: | I18: =+I19-I17 -> 0
A19: EFECTIVO: | C19: =SUM(H8,J8) -> 0 | D19: TOTAL EFECTIVO: | E19: =SUM(C19,E20,E57:E59)-(SUM(E23:E34)) -> 0 | G19: EFECTIVO ACTUAL PLANILLA: | I19: =E19 -> 0
A20: TOTAL VENTA: | C20: =SUM(C16:C19) -> 0 | D20: EFECTIVO ANTERIOR: | E20: =+I43 -> 0
A21: EGRESO DE CAJA MAYOR | G21: CONTEO DE EFECTIVO
A22: NIT | B22: PROVEEDOR | C22: CONCEPTO | D22: DESCRIPCIÓN | E22: EFECTIVO | G22: DENOMINACIÓN | H22: CANTIDAD | I22: EFECTIVO
A23: =IF(B23="","",VLOOKUP(B23,PROVEEDORES!$B:$C,2,FALSE)) | E23: 0 | G23: MONEDAS DE 100 | H23: 0 | I23: =100*H23 -> 0
A24: =IF(B24="","",VLOOKUP(B24,PROVEEDORES!$B:$C,2,FALSE)) | E24: 0 | G24: MONEDAS DE 200 | H24: 0 | I24: =200*H24 -> 0
A25: =IF(B25="","",VLOOKUP(B25,PROVEEDORES!$B:$C,2,FALSE)) | E25: 0 | G25: MONEDAS DE 500 | H25: 0 | I25: =500*H25 -> 0
A26: =IF(B26="","",VLOOKUP(B26,PROVEEDORES!$B:$C,2,FALSE)) | E26: 0 | G26: MONEDAS DE 1.000 | H26: 0 | I26: =1000*H26 -> 0
A27: =IF(B27="","",VLOOKUP(B27,PROVEEDORES!$B:$C,2,FALSE)) | E27: 0 | G27: BILLETES DE 2.000 | H27: 0 | I27: =2000*H27 -> 0
A28: =IF(B28="","",VLOOKUP(B28,PROVEEDORES!$B:$C,2,FALSE)) | E28: 0 | G28: BILLETES DE 5.000 | H28: 0 | I28: =5000*H28 -> 0
A29: =IF(B29="","",VLOOKUP(B29,PROVEEDORES!$B:$C,2,FALSE)) | E29: 0 | G29: BILLETES DE 10.000 | H29: 0 | I29: =10000*H29 -> 0
A30: =IF(B30="","",VLOOKUP(B30,PROVEEDORES!$B:$C,2,FALSE)) | E30: 0 | G30: BILLETES DE 20.000 | H30: 0 | I30: =20000*H30 -> 0
A31: =IF(B31="","",VLOOKUP(B31,PROVEEDORES!$B:$C,2,FALSE)) | E31: 0 | G31: BILLETES DE 50.000 | H31: 0 | I31: =50000*H31 -> 0
A32: =IF(B32="","",VLOOKUP(B32,PROVEEDORES!$B:$C,2,FALSE)) | E32: 0 | G32: BILLETES DE 100.000 | H32: 0 | I32: =100000*H32 -> 0
A33: =IF(B33="","",VLOOKUP(B33,PROVEEDORES!$B:$C,2,FALSE)) | E33: 0 | G33: TOTAL EFECTIVO: | I33: =SUM(I23:I32) -> 0
A34: =IF(B34="","",VLOOKUP(B34,PROVEEDORES!$B:$C,2,FALSE)) | E34: 0 | G34: BASE: | I34: 0
A35: NIT | B35: PROVEEDOR | C35: CONCEPTO | D35: DESCRIPCIÓN | E35: BANCO | G35: TOTAL EFECTIVO MENOS LA BASE: | I35: =I33-I34 -> 0
A36: =IF(B36="","",VLOOKUP(B36,PROVEEDORES!$B:$C,2,FALSE)) | E36: 0
A37: =IF(B37="","",VLOOKUP(B37,PROVEEDORES!$B:$C,2,FALSE)) | E37: 0 | G37: ACUM. DE PROPINA TRANSFERENCIA: | I37: =+'24'!E13 -> 0
A38: =IF(B38="","",VLOOKUP(B38,PROVEEDORES!$B:$C,2,FALSE)) | E38: 0 | G38: ACUMULADO DE PROPINA EN BANCO: | I38: =+'24'!E14 -> 0
A39: =IF(B39="","",VLOOKUP(B39,PROVEEDORES!$B:$C,2,FALSE)) | E39: 0 | G39: ACUMULADO DE PROPINA POR EFECTIVO: | I39: =+'24'!E15 -> 0
A40: =IF(B40="","",VLOOKUP(B40,PROVEEDORES!$B:$C,2,FALSE)) | E40: 0 | G40: ACUMULADO DE TRANSFERENCIA: | I40: =+'24'!E16 -> 0
A41: =IF(B41="","",VLOOKUP(B41,PROVEEDORES!$B:$C,2,FALSE)) | E41: 0 | G41: ACUMULADO DE BANCO: | I41: =+'24'!E17 -> 0
A42: =IF(B42="","",VLOOKUP(B42,PROVEEDORES!$B:$C,2,FALSE)) | E42: 0 | G42: REAL DE BANCO: | I42: =+'24'!E18 -> 0
A43: =IF(B43="","",VLOOKUP(B43,PROVEEDORES!$B:$C,2,FALSE)) | E43: 0 | G43: EFECTIVO ANTERIOR: | I43: =+'24'!E19 -> 0
A44: =IF(B44="","",VLOOKUP(B44,PROVEEDORES!$B:$C,2,FALSE)) | E44: 0
A45: =IF(B45="","",VLOOKUP(B45,PROVEEDORES!$B:$C,2,FALSE)) | E45: 0
A46: =IF(B46="","",VLOOKUP(B46,PROVEEDORES!$B:$C,2,FALSE)) | E46: 0
A47: =IF(B47="","",VLOOKUP(B47,PROVEEDORES!$B:$C,2,FALSE)) | E47: 0
A48: =IF(B48="","",VLOOKUP(B48,PROVEEDORES!$B:$C,2,FALSE)) | E48: 0
A49: =IF(B49="","",VLOOKUP(B49,PROVEEDORES!$B:$C,2,FALSE)) | E49: 0
A50: =IF(B50="","",VLOOKUP(B50,PROVEEDORES!$B:$C,2,FALSE)) | E50: 0
A51: =IF(B51="","",VLOOKUP(B51,PROVEEDORES!$B:$C,2,FALSE)) | E51: 0
A52: =IF(B52="","",VLOOKUP(B52,PROVEEDORES!$B:$C,2,FALSE)) | E52: 0
A53: =IF(B53="","",VLOOKUP(B53,PROVEEDORES!$B:$C,2,FALSE)) | E53: 0
A54: =IF(B54="","",VLOOKUP(B54,PROVEEDORES!$B:$C,2,FALSE)) | E54: 0
A55: =IF(B55="","",VLOOKUP(B55,PROVEEDORES!$B:$C,2,FALSE)) | E55: 0
A56: EGRESO PROPINA | D56: INGRESO DE EFECTIVO
A57: PROPINA TRANSFERENCIA: | C57: 0 | E57: 0
A58: PROPINA BANCO: | C58: 0 | E58: 0
A59: PROPINA EFECTIVO: | C59: 0 | E59: 0

Sheet 26
A1: ='25'!A1+1 -> 26 | B1: =+'1'!B1 -> QUESO Y CAFÉ | D1: =+'25'!D1:E1+1 -> 46168 | G1: CUADRE DE CAJA MAÑANA | I1: CUADRE DE CAJA TARDE
A2: NIT | B2: PROVEEDOR | C2: CONCEPTO | D2: DESCRIPCIÓN | E2: VALOR | G2: PROP. TRANSF.: | H2: 0 | I2: PROP. TRANSF.: | J2: 0
A3: =IF(B3="","",VLOOKUP(B3,PROVEEDORES!$B:$C,2,FALSE)) | E3: 0 | G3: PROP. BANCO: | H3: 0 | I3: PROP. BANCO: | J3: 0
A4: =IF(B4="","",VLOOKUP(B4,PROVEEDORES!$B:$C,2,FALSE)) | E4: 0 | G4: PROP. EFECTIVO: | H4: 0 | I4: PROP. EFECTIVO: | J4: 0
A5: =IF(B5="","",VLOOKUP(B5,PROVEEDORES!$B:$C,2,FALSE)) | E5: 0 | G5: GASTO: | H5: 0 | I5: GASTO: | J5: 0
A6: =IF(B6="","",VLOOKUP(B6,PROVEEDORES!$B:$C,2,FALSE)) | E6: 0 | G6: TRANSFERENCIA: | H6: 0 | I6: TRANSFERENCIA: | J6: 0
A7: =IF(B7="","",VLOOKUP(B7,PROVEEDORES!$B:$C,2,FALSE)) | E7: 0 | G7: BANCO: | H7: 0 | I7: BANCO: | J7: 0
A8: =IF(B8="","",VLOOKUP(B8,PROVEEDORES!$B:$C,2,FALSE)) | E8: 0 | G8: EFECTIVO: | H8: 0 | I8: EFECTIVO: | J8: 0
A9: =IF(B9="","",VLOOKUP(B9,PROVEEDORES!$B:$C,2,FALSE)) | E9: 0 | G9: TOTAL: | H9: =SUM(H5:H8) -> 0 | I9: TOTAL: | J9: =SUM(J5:J8) -> 0
A10: =IF(B10="","",VLOOKUP(B10,PROVEEDORES!$B:$C,2,FALSE)) | E10: 0 | G10: DIFERENCIA: | H10: =+H11-H9 -> 0 | I10: DIFERENCIA: | J10: =+J11-J9 -> 0
A11: =IF(B11="","",VLOOKUP(B11,PROVEEDORES!$B:$C,2,FALSE)) | E11: 0 | G11: TOTAL VENTA: | H11: 0 | I11: TOTAL VENTA: | J11: 0
A12: =IF(B12="","",VLOOKUP(B12,PROVEEDORES!$B:$C,2,FALSE)) | E12: 0
A13: PROPINA TRANSFERENCIA: | C13: =SUM(H2,J2) -> 0 | D13: ACUM. PROPINA TRANFERENCIA: | E13: =SUM(C13,I37)-C57 -> 0 | G13: DIFERENCIA PLANILLA VS CUADRE DE CAJA | I13: =+C20-(SUM(H9,J9)) -> 0
A14: PROPINA POR BANCO: | C14: =SUM(H3,J3) -> 0 | D14: ACUM. PROPINA BANCO: | E14: =SUM(C14,I38)-C58 -> 0
A15: PROPINA EN EFECTIVO: | C15: =SUM(H4,J4) -> 0 | D15: ACUM. PROPINA EFECTIVO: | E15: =SUM(C15,I39)-C59 -> 0 | G15: FACTURAS EN EFECTIVO: | I15: 0
A16: TOTAL EGRESOS: | C16: =SUM(E3:E12) -> 0 | D16: ACUMULADO TRANSFERENCIA: | E16: =SUM(C17,I40) -> 0 | G16: EFECTIVO: | I16: 0
A17: TRANSFERENCIA: | C17: =SUM(H6,J6) -> 0 | D17: ACUMULADO BANCO: | E17: =SUM(C18,I41) -> 0 | G17: TOTAL EFECTIVO REAL ACTUAL: | I17: =SUM(I15,I16) -> 0
A18: BANCO: | C18: =SUM(H7,J7) -> 0 | D18: TOTAL BANCO: | E18: =SUM(C18,I42)-(SUM(E36:E55)) -> 0 | G18: DIFERENCIA: | I18: =+I19-I17 -> 0
A19: EFECTIVO: | C19: =SUM(H8,J8) -> 0 | D19: TOTAL EFECTIVO: | E19: =SUM(C19,E20,E57:E59)-(SUM(E23:E34)) -> 0 | G19: EFECTIVO ACTUAL PLANILLA: | I19: =E19 -> 0
A20: TOTAL VENTA: | C20: =SUM(C16:C19) -> 0 | D20: EFECTIVO ANTERIOR: | E20: =+I43 -> 0
A21: EGRESO DE CAJA MAYOR | G21: CONTEO DE EFECTIVO
A22: NIT | B22: PROVEEDOR | C22: CONCEPTO | D22: DESCRIPCIÓN | E22: EFECTIVO | G22: DENOMINACIÓN | H22: CANTIDAD | I22: EFECTIVO
A23: =IF(B23="","",VLOOKUP(B23,PROVEEDORES!$B:$C,2,FALSE)) | E23: 0 | G23: MONEDAS DE 100 | H23: 0 | I23: =100*H23 -> 0
A24: =IF(B24="","",VLOOKUP(B24,PROVEEDORES!$B:$C,2,FALSE)) | E24: 0 | G24: MONEDAS DE 200 | H24: 0 | I24: =200*H24 -> 0
A25: =IF(B25="","",VLOOKUP(B25,PROVEEDORES!$B:$C,2,FALSE)) | E25: 0 | G25: MONEDAS DE 500 | H25: 0 | I25: =500*H25 -> 0
A26: =IF(B26="","",VLOOKUP(B26,PROVEEDORES!$B:$C,2,FALSE)) | E26: 0 | G26: MONEDAS DE 1.000 | H26: 0 | I26: =1000*H26 -> 0
A27: =IF(B27="","",VLOOKUP(B27,PROVEEDORES!$B:$C,2,FALSE)) | E27: 0 | G27: BILLETES DE 2.000 | H27: 0 | I27: =2000*H27 -> 0
A28: =IF(B28="","",VLOOKUP(B28,PROVEEDORES!$B:$C,2,FALSE)) | E28: 0 | G28: BILLETES DE 5.000 | H28: 0 | I28: =5000*H28 -> 0
A29: =IF(B29="","",VLOOKUP(B29,PROVEEDORES!$B:$C,2,FALSE)) | E29: 0 | G29: BILLETES DE 10.000 | H29: 0 | I29: =10000*H29 -> 0
A30: =IF(B30="","",VLOOKUP(B30,PROVEEDORES!$B:$C,2,FALSE)) | E30: 0 | G30: BILLETES DE 20.000 | H30: 0 | I30: =20000*H30 -> 0
A31: =IF(B31="","",VLOOKUP(B31,PROVEEDORES!$B:$C,2,FALSE)) | E31: 0 | G31: BILLETES DE 50.000 | H31: 0 | I31: =50000*H31 -> 0
A32: =IF(B32="","",VLOOKUP(B32,PROVEEDORES!$B:$C,2,FALSE)) | E32: 0 | G32: BILLETES DE 100.000 | H32: 0 | I32: =100000*H32 -> 0
A33: =IF(B33="","",VLOOKUP(B33,PROVEEDORES!$B:$C,2,FALSE)) | E33: 0 | G33: TOTAL EFECTIVO: | I33: =SUM(I23:I32) -> 0
A34: =IF(B34="","",VLOOKUP(B34,PROVEEDORES!$B:$C,2,FALSE)) | E34: 0 | G34: BASE: | I34: 0
A35: NIT | B35: PROVEEDOR | C35: CONCEPTO | D35: DESCRIPCIÓN | E35: BANCO | G35: TOTAL EFECTIVO MENOS LA BASE: | I35: =I33-I34 -> 0
A36: =IF(B36="","",VLOOKUP(B36,PROVEEDORES!$B:$C,2,FALSE)) | E36: 0
A37: =IF(B37="","",VLOOKUP(B37,PROVEEDORES!$B:$C,2,FALSE)) | E37: 0 | G37: ACUM. DE PROPINA TRANSFERENCIA: | I37: =+'25'!E13 -> 0
A38: =IF(B38="","",VLOOKUP(B38,PROVEEDORES!$B:$C,2,FALSE)) | E38: 0 | G38: ACUMULADO DE PROPINA EN BANCO: | I38: =+'25'!E14 -> 0
A39: =IF(B39="","",VLOOKUP(B39,PROVEEDORES!$B:$C,2,FALSE)) | E39: 0 | G39: ACUMULADO DE PROPINA POR EFECTIVO: | I39: =+'25'!E15 -> 0
A40: =IF(B40="","",VLOOKUP(B40,PROVEEDORES!$B:$C,2,FALSE)) | E40: 0 | G40: ACUMULADO DE TRANSFERENCIA: | I40: =+'25'!E16 -> 0
A41: =IF(B41="","",VLOOKUP(B41,PROVEEDORES!$B:$C,2,FALSE)) | E41: 0 | G41: ACUMULADO DE BANCO: | I41: =+'25'!E17 -> 0
A42: =IF(B42="","",VLOOKUP(B42,PROVEEDORES!$B:$C,2,FALSE)) | E42: 0 | G42: REAL DE BANCO: | I42: =+'25'!E18 -> 0
A43: =IF(B43="","",VLOOKUP(B43,PROVEEDORES!$B:$C,2,FALSE)) | E43: 0 | G43: EFECTIVO ANTERIOR: | I43: =+'25'!E19 -> 0
A44: =IF(B44="","",VLOOKUP(B44,PROVEEDORES!$B:$C,2,FALSE)) | E44: 0
A45: =IF(B45="","",VLOOKUP(B45,PROVEEDORES!$B:$C,2,FALSE)) | E45: 0
A46: =IF(B46="","",VLOOKUP(B46,PROVEEDORES!$B:$C,2,FALSE)) | E46: 0
A47: =IF(B47="","",VLOOKUP(B47,PROVEEDORES!$B:$C,2,FALSE)) | E47: 0
A48: =IF(B48="","",VLOOKUP(B48,PROVEEDORES!$B:$C,2,FALSE)) | E48: 0
A49: =IF(B49="","",VLOOKUP(B49,PROVEEDORES!$B:$C,2,FALSE)) | E49: 0
A50: =IF(B50="","",VLOOKUP(B50,PROVEEDORES!$B:$C,2,FALSE)) | E50: 0
A51: =IF(B51="","",VLOOKUP(B51,PROVEEDORES!$B:$C,2,FALSE)) | E51: 0
A52: =IF(B52="","",VLOOKUP(B52,PROVEEDORES!$B:$C,2,FALSE)) | E52: 0
A53: =IF(B53="","",VLOOKUP(B53,PROVEEDORES!$B:$C,2,FALSE)) | E53: 0
A54: =IF(B54="","",VLOOKUP(B54,PROVEEDORES!$B:$C,2,FALSE)) | E54: 0
A55: =IF(B55="","",VLOOKUP(B55,PROVEEDORES!$B:$C,2,FALSE)) | E55: 0
A56: EGRESO PROPINA | D56: INGRESO DE EFECTIVO
A57: PROPINA TRANSFERENCIA: | C57: 0 | E57: 0
A58: PROPINA BANCO: | C58: 0 | E58: 0
A59: PROPINA EFECTIVO: | C59: 0 | E59: 0

Sheet 27
A1: ='26'!A1+1 -> 27 | B1: =+'1'!B1 -> QUESO Y CAFÉ | D1: =+'26'!D1:E1+1 -> 46169 | G1: CUADRE DE CAJA MAÑANA | I1: CUADRE DE CAJA TARDE
A2: NIT | B2: PROVEEDOR | C2: CONCEPTO | D2: DESCRIPCIÓN | E2: VALOR | G2: PROP. TRANSF.: | H2: 0 | I2: PROP. TRANSF.: | J2: 0
A3: =IF(B3="","",VLOOKUP(B3,PROVEEDORES!$B:$C,2,FALSE)) | E3: 0 | G3: PROP. BANCO: | H3: 0 | I3: PROP. BANCO: | J3: 0
A4: =IF(B4="","",VLOOKUP(B4,PROVEEDORES!$B:$C,2,FALSE)) | E4: 0 | G4: PROP. EFECTIVO: | H4: 0 | I4: PROP. EFECTIVO: | J4: 0
A5: =IF(B5="","",VLOOKUP(B5,PROVEEDORES!$B:$C,2,FALSE)) | E5: 0 | G5: GASTO: | H5: 0 | I5: GASTO: | J5: 0
A6: =IF(B6="","",VLOOKUP(B6,PROVEEDORES!$B:$C,2,FALSE)) | E6: 0 | G6: TRANSFERENCIA: | H6: 0 | I6: TRANSFERENCIA: | J6: 0
A7: =IF(B7="","",VLOOKUP(B7,PROVEEDORES!$B:$C,2,FALSE)) | E7: 0 | G7: BANCO: | H7: 0 | I7: BANCO: | J7: 0
A8: =IF(B8="","",VLOOKUP(B8,PROVEEDORES!$B:$C,2,FALSE)) | E8: 0 | G8: EFECTIVO: | H8: 0 | I8: EFECTIVO: | J8: 0
A9: =IF(B9="","",VLOOKUP(B9,PROVEEDORES!$B:$C,2,FALSE)) | E9: 0 | G9: TOTAL: | H9: =SUM(H5:H8) -> 0 | I9: TOTAL: | J9: =SUM(J5:J8) -> 0
A10: =IF(B10="","",VLOOKUP(B10,PROVEEDORES!$B:$C,2,FALSE)) | E10: 0 | G10: DIFERENCIA: | H10: =+H11-H9 -> 0 | I10: DIFERENCIA: | J10: =+J11-J9 -> 0
A11: =IF(B11="","",VLOOKUP(B11,PROVEEDORES!$B:$C,2,FALSE)) | E11: 0 | G11: TOTAL VENTA: | H11: 0 | I11: TOTAL VENTA: | J11: 0
A12: =IF(B12="","",VLOOKUP(B12,PROVEEDORES!$B:$C,2,FALSE)) | E12: 0
A13: PROPINA TRANSFERENCIA: | C13: =SUM(H2,J2) -> 0 | D13: ACUM. PROPINA TRANFERENCIA: | E13: =SUM(C13,I37)-C57 -> 0 | G13: DIFERENCIA PLANILLA VS CUADRE DE CAJA | I13: =+C20-(SUM(H9,J9)) -> 0
A14: PROPINA POR BANCO: | C14: =SUM(H3,J3) -> 0 | D14: ACUM. PROPINA BANCO: | E14: =SUM(C14,I38)-C58 -> 0
A15: PROPINA EN EFECTIVO: | C15: =SUM(H4,J4) -> 0 | D15: ACUM. PROPINA EFECTIVO: | E15: =SUM(C15,I39)-C59 -> 0 | G15: FACTURAS EN EFECTIVO: | I15: 0
A16: TOTAL EGRESOS: | C16: =SUM(E3:E12) -> 0 | D16: ACUMULADO TRANSFERENCIA: | E16: =SUM(C17,I40) -> 0 | G16: EFECTIVO: | I16: 0
A17: TRANSFERENCIA: | C17: =SUM(H6,J6) -> 0 | D17: ACUMULADO BANCO: | E17: =SUM(C18,I41) -> 0 | G17: TOTAL EFECTIVO REAL ACTUAL: | I17: =SUM(I15,I16) -> 0
A18: BANCO: | C18: =SUM(H7,J7) -> 0 | D18: TOTAL BANCO: | E18: =SUM(C18,I42)-(SUM(E36:E55)) -> 0 | G18: DIFERENCIA: | I18: =+I19-I17 -> 0
A19: EFECTIVO: | C19: =SUM(H8,J8) -> 0 | D19: TOTAL EFECTIVO: | E19: =SUM(C19,E20,E57:E59)-(SUM(E23:E34)) -> 0 | G19: EFECTIVO ACTUAL PLANILLA: | I19: =E19 -> 0
A20: TOTAL VENTA: | C20: =SUM(C16:C19) -> 0 | D20: EFECTIVO ANTERIOR: | E20: =+I43 -> 0
A21: EGRESO DE CAJA MAYOR | G21: CONTEO DE EFECTIVO
A22: NIT | B22: PROVEEDOR | C22: CONCEPTO | D22: DESCRIPCIÓN | E22: EFECTIVO | G22: DENOMINACIÓN | H22: CANTIDAD | I22: EFECTIVO
A23: =IF(B23="","",VLOOKUP(B23,PROVEEDORES!$B:$C,2,FALSE)) | E23: 0 | G23: MONEDAS DE 100 | H23: 0 | I23: =100*H23 -> 0
A24: =IF(B24="","",VLOOKUP(B24,PROVEEDORES!$B:$C,2,FALSE)) | E24: 0 | G24: MONEDAS DE 200 | H24: 0 | I24: =200*H24 -> 0
A25: =IF(B25="","",VLOOKUP(B25,PROVEEDORES!$B:$C,2,FALSE)) | E25: 0 | G25: MONEDAS DE 500 | H25: 0 | I25: =500*H25 -> 0
A26: =IF(B26="","",VLOOKUP(B26,PROVEEDORES!$B:$C,2,FALSE)) | E26: 0 | G26: MONEDAS DE 1.000 | H26: 0 | I26: =1000*H26 -> 0
A27: =IF(B27="","",VLOOKUP(B27,PROVEEDORES!$B:$C,2,FALSE)) | E27: 0 | G27: BILLETES DE 2.000 | H27: 0 | I27: =2000*H27 -> 0
A28: =IF(B28="","",VLOOKUP(B28,PROVEEDORES!$B:$C,2,FALSE)) | E28: 0 | G28: BILLETES DE 5.000 | H28: 0 | I28: =5000*H28 -> 0
A29: =IF(B29="","",VLOOKUP(B29,PROVEEDORES!$B:$C,2,FALSE)) | E29: 0 | G29: BILLETES DE 10.000 | H29: 0 | I29: =10000*H29 -> 0
A30: =IF(B30="","",VLOOKUP(B30,PROVEEDORES!$B:$C,2,FALSE)) | E30: 0 | G30: BILLETES DE 20.000 | H30: 0 | I30: =20000*H30 -> 0
A31: =IF(B31="","",VLOOKUP(B31,PROVEEDORES!$B:$C,2,FALSE)) | E31: 0 | G31: BILLETES DE 50.000 | H31: 0 | I31: =50000*H31 -> 0
A32: =IF(B32="","",VLOOKUP(B32,PROVEEDORES!$B:$C,2,FALSE)) | E32: 0 | G32: BILLETES DE 100.000 | H32: 0 | I32: =100000*H32 -> 0
A33: =IF(B33="","",VLOOKUP(B33,PROVEEDORES!$B:$C,2,FALSE)) | E33: 0 | G33: TOTAL EFECTIVO: | I33: =SUM(I23:I32) -> 0
A34: =IF(B34="","",VLOOKUP(B34,PROVEEDORES!$B:$C,2,FALSE)) | E34: 0 | G34: BASE: | I34: 0
A35: NIT | B35: PROVEEDOR | C35: CONCEPTO | D35: DESCRIPCIÓN | E35: BANCO | G35: TOTAL EFECTIVO MENOS LA BASE: | I35: =I33-I34 -> 0
A36: =IF(B36="","",VLOOKUP(B36,PROVEEDORES!$B:$C,2,FALSE)) | E36: 0
A37: =IF(B37="","",VLOOKUP(B37,PROVEEDORES!$B:$C,2,FALSE)) | E37: 0 | G37: ACUM. DE PROPINA TRANSFERENCIA: | I37: =+'26'!E13 -> 0
A38: =IF(B38="","",VLOOKUP(B38,PROVEEDORES!$B:$C,2,FALSE)) | E38: 0 | G38: ACUMULADO DE PROPINA EN BANCO: | I38: =+'26'!E14 -> 0
A39: =IF(B39="","",VLOOKUP(B39,PROVEEDORES!$B:$C,2,FALSE)) | E39: 0 | G39: ACUMULADO DE PROPINA POR EFECTIVO: | I39: =+'26'!E15 -> 0
A40: =IF(B40="","",VLOOKUP(B40,PROVEEDORES!$B:$C,2,FALSE)) | E40: 0 | G40: ACUMULADO DE TRANSFERENCIA: | I40: =+'26'!E16 -> 0
A41: =IF(B41="","",VLOOKUP(B41,PROVEEDORES!$B:$C,2,FALSE)) | E41: 0 | G41: ACUMULADO DE BANCO: | I41: =+'26'!E17 -> 0
A42: =IF(B42="","",VLOOKUP(B42,PROVEEDORES!$B:$C,2,FALSE)) | E42: 0 | G42: REAL DE BANCO: | I42: =+'26'!E18 -> 0
A43: =IF(B43="","",VLOOKUP(B43,PROVEEDORES!$B:$C,2,FALSE)) | E43: 0 | G43: EFECTIVO ANTERIOR: | I43: =+'26'!E19 -> 0
A44: =IF(B44="","",VLOOKUP(B44,PROVEEDORES!$B:$C,2,FALSE)) | E44: 0
A45: =IF(B45="","",VLOOKUP(B45,PROVEEDORES!$B:$C,2,FALSE)) | E45: 0
A46: =IF(B46="","",VLOOKUP(B46,PROVEEDORES!$B:$C,2,FALSE)) | E46: 0
A47: =IF(B47="","",VLOOKUP(B47,PROVEEDORES!$B:$C,2,FALSE)) | E47: 0
A48: =IF(B48="","",VLOOKUP(B48,PROVEEDORES!$B:$C,2,FALSE)) | E48: 0
A49: =IF(B49="","",VLOOKUP(B49,PROVEEDORES!$B:$C,2,FALSE)) | E49: 0
A50: =IF(B50="","",VLOOKUP(B50,PROVEEDORES!$B:$C,2,FALSE)) | E50: 0
A51: =IF(B51="","",VLOOKUP(B51,PROVEEDORES!$B:$C,2,FALSE)) | E51: 0
A52: =IF(B52="","",VLOOKUP(B52,PROVEEDORES!$B:$C,2,FALSE)) | E52: 0
A53: =IF(B53="","",VLOOKUP(B53,PROVEEDORES!$B:$C,2,FALSE)) | E53: 0
A54: =IF(B54="","",VLOOKUP(B54,PROVEEDORES!$B:$C,2,FALSE)) | E54: 0
A55: =IF(B55="","",VLOOKUP(B55,PROVEEDORES!$B:$C,2,FALSE)) | E55: 0
A56: EGRESO PROPINA | D56: INGRESO DE EFECTIVO
A57: PROPINA TRANSFERENCIA: | C57: 0 | E57: 0
A58: PROPINA BANCO: | C58: 0 | E58: 0
A59: PROPINA EFECTIVO: | C59: 0 | E59: 0

Sheet 28
A1: ='27'!A1+1 -> 28 | B1: =+'1'!B1 -> QUESO Y CAFÉ | D1: =+'27'!D1:E1+1 -> 46170 | G1: CUADRE DE CAJA MAÑANA | I1: CUADRE DE CAJA TARDE
A2: NIT | B2: PROVEEDOR | C2: CONCEPTO | D2: DESCRIPCIÓN | E2: VALOR | G2: PROP. TRANSF.: | H2: 0 | I2: PROP. TRANSF.: | J2: 0
A3: =IF(B3="","",VLOOKUP(B3,PROVEEDORES!$B:$C,2,FALSE)) | E3: 0 | G3: PROP. BANCO: | H3: 0 | I3: PROP. BANCO: | J3: 0
A4: =IF(B4="","",VLOOKUP(B4,PROVEEDORES!$B:$C,2,FALSE)) | E4: 0 | G4: PROP. EFECTIVO: | H4: 0 | I4: PROP. EFECTIVO: | J4: 0
A5: =IF(B5="","",VLOOKUP(B5,PROVEEDORES!$B:$C,2,FALSE)) | E5: 0 | G5: GASTO: | H5: 0 | I5: GASTO: | J5: 0
A6: =IF(B6="","",VLOOKUP(B6,PROVEEDORES!$B:$C,2,FALSE)) | E6: 0 | G6: TRANSFERENCIA: | H6: 0 | I6: TRANSFERENCIA: | J6: 0
A7: =IF(B7="","",VLOOKUP(B7,PROVEEDORES!$B:$C,2,FALSE)) | E7: 0 | G7: BANCO: | H7: 0 | I7: BANCO: | J7: 0
A8: =IF(B8="","",VLOOKUP(B8,PROVEEDORES!$B:$C,2,FALSE)) | E8: 0 | G8: EFECTIVO: | H8: 0 | I8: EFECTIVO: | J8: 0
A9: =IF(B9="","",VLOOKUP(B9,PROVEEDORES!$B:$C,2,FALSE)) | E9: 0 | G9: TOTAL: | H9: =SUM(H5:H8) -> 0 | I9: TOTAL: | J9: =SUM(J5:J8) -> 0
A10: =IF(B10="","",VLOOKUP(B10,PROVEEDORES!$B:$C,2,FALSE)) | E10: 0 | G10: DIFERENCIA: | H10: =+H11-H9 -> 0 | I10: DIFERENCIA: | J10: =+J11-J9 -> 0
A11: =IF(B11="","",VLOOKUP(B11,PROVEEDORES!$B:$C,2,FALSE)) | E11: 0 | G11: TOTAL VENTA: | H11: 0 | I11: TOTAL VENTA: | J11: 0
A12: =IF(B12="","",VLOOKUP(B12,PROVEEDORES!$B:$C,2,FALSE)) | E12: 0
A13: PROPINA TRANSFERENCIA: | C13: =SUM(H2,J2) -> 0 | D13: ACUM. PROPINA TRANFERENCIA: | E13: =SUM(C13,I37)-C57 -> 0 | G13: DIFERENCIA PLANILLA VS CUADRE DE CAJA | I13: =+C20-(SUM(H9,J9)) -> 0
A14: PROPINA POR BANCO: | C14: =SUM(H3,J3) -> 0 | D14: ACUM. PROPINA BANCO: | E14: =SUM(C14,I38)-C58 -> 0
A15: PROPINA EN EFECTIVO: | C15: =SUM(H4,J4) -> 0 | D15: ACUM. PROPINA EFECTIVO: | E15: =SUM(C15,I39)-C59 -> 0 | G15: FACTURAS EN EFECTIVO: | I15: 0
A16: TOTAL EGRESOS: | C16: =SUM(E3:E12) -> 0 | D16: ACUMULADO TRANSFERENCIA: | E16: =SUM(C17,I40) -> 0 | G16: EFECTIVO: | I16: 0
A17: TRANSFERENCIA: | C17: =SUM(H6,J6) -> 0 | D17: ACUMULADO BANCO: | E17: =SUM(C18,I41) -> 0 | G17: TOTAL EFECTIVO REAL ACTUAL: | I17: =SUM(I15,I16) -> 0
A18: BANCO: | C18: =SUM(H7,J7) -> 0 | D18: TOTAL BANCO: | E18: =SUM(C18,I42)-(SUM(E36:E55)) -> 0 | G18: DIFERENCIA: | I18: =+I19-I17 -> 0
A19: EFECTIVO: | C19: =SUM(H8,J8) -> 0 | D19: TOTAL EFECTIVO: | E19: =SUM(C19,E20,E57:E59)-(SUM(E23:E34)) -> 0 | G19: EFECTIVO ACTUAL PLANILLA: | I19: =E19 -> 0
A20: TOTAL VENTA: | C20: =SUM(C16:C19) -> 0 | D20: EFECTIVO ANTERIOR: | E20: =+I43 -> 0
A21: EGRESO DE CAJA MAYOR | G21: CONTEO DE EFECTIVO
A22: NIT | B22: PROVEEDOR | C22: CONCEPTO | D22: DESCRIPCIÓN | E22: EFECTIVO | G22: DENOMINACIÓN | H22: CANTIDAD | I22: EFECTIVO
A23: =IF(B23="","",VLOOKUP(B23,PROVEEDORES!$B:$C,2,FALSE)) | E23: 0 | G23: MONEDAS DE 100 | H23: 0 | I23: =100*H23 -> 0
A24: =IF(B24="","",VLOOKUP(B24,PROVEEDORES!$B:$C,2,FALSE)) | E24: 0 | G24: MONEDAS DE 200 | H24: 0 | I24: =200*H24 -> 0
A25: =IF(B25="","",VLOOKUP(B25,PROVEEDORES!$B:$C,2,FALSE)) | E25: 0 | G25: MONEDAS DE 500 | H25: 0 | I25: =500*H25 -> 0
A26: =IF(B26="","",VLOOKUP(B26,PROVEEDORES!$B:$C,2,FALSE)) | E26: 0 | G26: MONEDAS DE 1.000 | H26: 0 | I26: =1000*H26 -> 0
A27: =IF(B27="","",VLOOKUP(B27,PROVEEDORES!$B:$C,2,FALSE)) | E27: 0 | G27: BILLETES DE 2.000 | H27: 0 | I27: =2000*H27 -> 0
A28: =IF(B28="","",VLOOKUP(B28,PROVEEDORES!$B:$C,2,FALSE)) | E28: 0 | G28: BILLETES DE 5.000 | H28: 0 | I28: =5000*H28 -> 0
A29: =IF(B29="","",VLOOKUP(B29,PROVEEDORES!$B:$C,2,FALSE)) | E29: 0 | G29: BILLETES DE 10.000 | H29: 0 | I29: =10000*H29 -> 0
A30: =IF(B30="","",VLOOKUP(B30,PROVEEDORES!$B:$C,2,FALSE)) | E30: 0 | G30: BILLETES DE 20.000 | H30: 0 | I30: =20000*H30 -> 0
A31: =IF(B31="","",VLOOKUP(B31,PROVEEDORES!$B:$C,2,FALSE)) | E31: 0 | G31: BILLETES DE 50.000 | H31: 0 | I31: =50000*H31 -> 0
A32: =IF(B32="","",VLOOKUP(B32,PROVEEDORES!$B:$C,2,FALSE)) | E32: 0 | G32: BILLETES DE 100.000 | H32: 0 | I32: =100000*H32 -> 0
A33: =IF(B33="","",VLOOKUP(B33,PROVEEDORES!$B:$C,2,FALSE)) | E33: 0 | G33: TOTAL EFECTIVO: | I33: =SUM(I23:I32) -> 0
A34: =IF(B34="","",VLOOKUP(B34,PROVEEDORES!$B:$C,2,FALSE)) | E34: 0 | G34: BASE: | I34: 0
A35: NIT | B35: PROVEEDOR | C35: CONCEPTO | D35: DESCRIPCIÓN | E35: BANCO | G35: TOTAL EFECTIVO MENOS LA BASE: | I35: =I33-I34 -> 0
A36: =IF(B36="","",VLOOKUP(B36,PROVEEDORES!$B:$C,2,FALSE)) | E36: 0
A37: =IF(B37="","",VLOOKUP(B37,PROVEEDORES!$B:$C,2,FALSE)) | E37: 0 | G37: ACUM. DE PROPINA TRANSFERENCIA: | I37: =+'27'!E13 -> 0
A38: =IF(B38="","",VLOOKUP(B38,PROVEEDORES!$B:$C,2,FALSE)) | E38: 0 | G38: ACUMULADO DE PROPINA EN BANCO: | I38: =+'27'!E14 -> 0
A39: =IF(B39="","",VLOOKUP(B39,PROVEEDORES!$B:$C,2,FALSE)) | E39: 0 | G39: ACUMULADO DE PROPINA POR EFECTIVO: | I39: =+'27'!E15 -> 0
A40: =IF(B40="","",VLOOKUP(B40,PROVEEDORES!$B:$C,2,FALSE)) | E40: 0 | G40: ACUMULADO DE TRANSFERENCIA: | I40: =+'27'!E16 -> 0
A41: =IF(B41="","",VLOOKUP(B41,PROVEEDORES!$B:$C,2,FALSE)) | E41: 0 | G41: ACUMULADO DE BANCO: | I41: =+'27'!E17 -> 0
A42: =IF(B42="","",VLOOKUP(B42,PROVEEDORES!$B:$C,2,FALSE)) | E42: 0 | G42: REAL DE BANCO: | I42: =+'27'!E18 -> 0
A43: =IF(B43="","",VLOOKUP(B43,PROVEEDORES!$B:$C,2,FALSE)) | E43: 0 | G43: EFECTIVO ANTERIOR: | I43: =+'27'!E19 -> 0
A44: =IF(B44="","",VLOOKUP(B44,PROVEEDORES!$B:$C,2,FALSE)) | E44: 0
A45: =IF(B45="","",VLOOKUP(B45,PROVEEDORES!$B:$C,2,FALSE)) | E45: 0
A46: =IF(B46="","",VLOOKUP(B46,PROVEEDORES!$B:$C,2,FALSE)) | E46: 0
A47: =IF(B47="","",VLOOKUP(B47,PROVEEDORES!$B:$C,2,FALSE)) | E47: 0
A48: =IF(B48="","",VLOOKUP(B48,PROVEEDORES!$B:$C,2,FALSE)) | E48: 0
A49: =IF(B49="","",VLOOKUP(B49,PROVEEDORES!$B:$C,2,FALSE)) | E49: 0
A50: =IF(B50="","",VLOOKUP(B50,PROVEEDORES!$B:$C,2,FALSE)) | E50: 0
A51: =IF(B51="","",VLOOKUP(B51,PROVEEDORES!$B:$C,2,FALSE)) | E51: 0
A52: =IF(B52="","",VLOOKUP(B52,PROVEEDORES!$B:$C,2,FALSE)) | E52: 0
A53: =IF(B53="","",VLOOKUP(B53,PROVEEDORES!$B:$C,2,FALSE)) | E53: 0
A54: =IF(B54="","",VLOOKUP(B54,PROVEEDORES!$B:$C,2,FALSE)) | E54: 0
A55: =IF(B55="","",VLOOKUP(B55,PROVEEDORES!$B:$C,2,FALSE)) | E55: 0
A56: EGRESO PROPINA | D56: INGRESO DE EFECTIVO
A57: PROPINA TRANSFERENCIA: | C57: 0 | E57: 0
A58: PROPINA BANCO: | C58: 0 | E58: 0
A59: PROPINA EFECTIVO: | C59: 0 | E59: 0

Sheet 29
A1: ='28'!A1+1 -> 29 | B1: =+'1'!B1 -> QUESO Y CAFÉ | D1: =+'28'!D1:E1+1 -> 46171 | G1: CUADRE DE CAJA MAÑANA | I1: CUADRE DE CAJA TARDE
A2: NIT | B2: PROVEEDOR | C2: CONCEPTO | D2: DESCRIPCIÓN | E2: VALOR | G2: PROP. TRANSF.: | H2: 0 | I2: PROP. TRANSF.: | J2: 0
A3: =IF(B3="","",VLOOKUP(B3,PROVEEDORES!$B:$C,2,FALSE)) | E3: 0 | G3: PROP. BANCO: | H3: 0 | I3: PROP. BANCO: | J3: 0
A4: =IF(B4="","",VLOOKUP(B4,PROVEEDORES!$B:$C,2,FALSE)) | E4: 0 | G4: PROP. EFECTIVO: | H4: 0 | I4: PROP. EFECTIVO: | J4: 0
A5: =IF(B5="","",VLOOKUP(B5,PROVEEDORES!$B:$C,2,FALSE)) | E5: 0 | G5: GASTO: | H5: 0 | I5: GASTO: | J5: 0
A6: =IF(B6="","",VLOOKUP(B6,PROVEEDORES!$B:$C,2,FALSE)) | E6: 0 | G6: TRANSFERENCIA: | H6: 0 | I6: TRANSFERENCIA: | J6: 0
A7: =IF(B7="","",VLOOKUP(B7,PROVEEDORES!$B:$C,2,FALSE)) | E7: 0 | G7: BANCO: | H7: 0 | I7: BANCO: | J7: 0
A8: =IF(B8="","",VLOOKUP(B8,PROVEEDORES!$B:$C,2,FALSE)) | E8: 0 | G8: EFECTIVO: | H8: 0 | I8: EFECTIVO: | J8: 0
A9: =IF(B9="","",VLOOKUP(B9,PROVEEDORES!$B:$C,2,FALSE)) | E9: 0 | G9: TOTAL: | H9: =SUM(H5:H8) -> 0 | I9: TOTAL: | J9: =SUM(J5:J8) -> 0
A10: =IF(B10="","",VLOOKUP(B10,PROVEEDORES!$B:$C,2,FALSE)) | E10: 0 | G10: DIFERENCIA: | H10: =+H11-H9 -> 0 | I10: DIFERENCIA: | J10: =+J11-J9 -> 0
A11: =IF(B11="","",VLOOKUP(B11,PROVEEDORES!$B:$C,2,FALSE)) | E11: 0 | G11: TOTAL VENTA: | H11: 0 | I11: TOTAL VENTA: | J11: 0
A12: =IF(B12="","",VLOOKUP(B12,PROVEEDORES!$B:$C,2,FALSE)) | E12: 0
A13: PROPINA TRANSFERENCIA: | C13: =SUM(H2,J2) -> 0 | D13: ACUM. PROPINA TRANFERENCIA: | E13: =SUM(C13,I37)-C57 -> 0 | G13: DIFERENCIA PLANILLA VS CUADRE DE CAJA | I13: =+C20-(SUM(H9,J9)) -> 0
A14: PROPINA POR BANCO: | C14: =SUM(H3,J3) -> 0 | D14: ACUM. PROPINA BANCO: | E14: =SUM(C14,I38)-C58 -> 0
A15: PROPINA EN EFECTIVO: | C15: =SUM(H4,J4) -> 0 | D15: ACUM. PROPINA EFECTIVO: | E15: =SUM(C15,I39)-C59 -> 0 | G15: FACTURAS EN EFECTIVO: | I15: 0
A16: TOTAL EGRESOS: | C16: =SUM(E3:E12) -> 0 | D16: ACUMULADO TRANSFERENCIA: | E16: =SUM(C17,I40) -> 0 | G16: EFECTIVO: | I16: 0
A17: TRANSFERENCIA: | C17: =SUM(H6,J6) -> 0 | D17: ACUMULADO BANCO: | E17: =SUM(C18,I41) -> 0 | G17: TOTAL EFECTIVO REAL ACTUAL: | I17: =SUM(I15,I16) -> 0
A18: BANCO: | C18: =SUM(H7,J7) -> 0 | D18: TOTAL BANCO: | E18: =SUM(C18,I42)-(SUM(E36:E55)) -> 0 | G18: DIFERENCIA: | I18: =+I19-I17 -> 0
A19: EFECTIVO: | C19: =SUM(H8,J8) -> 0 | D19: TOTAL EFECTIVO: | E19: =SUM(C19,E20,E57:E59)-(SUM(E23:E34)) -> 0 | G19: EFECTIVO ACTUAL PLANILLA: | I19: =E19 -> 0
A20: TOTAL VENTA: | C20: =SUM(C16:C19) -> 0 | D20: EFECTIVO ANTERIOR: | E20: =+I43 -> 0
A21: EGRESO DE CAJA MAYOR | G21: CONTEO DE EFECTIVO
A22: NIT | B22: PROVEEDOR | C22: CONCEPTO | D22: DESCRIPCIÓN | E22: EFECTIVO | G22: DENOMINACIÓN | H22: CANTIDAD | I22: EFECTIVO
A23: =IF(B23="","",VLOOKUP(B23,PROVEEDORES!$B:$C,2,FALSE)) | E23: 0 | G23: MONEDAS DE 100 | H23: 0 | I23: =100*H23 -> 0
A24: =IF(B24="","",VLOOKUP(B24,PROVEEDORES!$B:$C,2,FALSE)) | E24: 0 | G24: MONEDAS DE 200 | H24: 0 | I24: =200*H24 -> 0
A25: =IF(B25="","",VLOOKUP(B25,PROVEEDORES!$B:$C,2,FALSE)) | E25: 0 | G25: MONEDAS DE 500 | H25: 0 | I25: =500*H25 -> 0
A26: =IF(B26="","",VLOOKUP(B26,PROVEEDORES!$B:$C,2,FALSE)) | E26: 0 | G26: MONEDAS DE 1.000 | H26: 0 | I26: =1000*H26 -> 0
A27: =IF(B27="","",VLOOKUP(B27,PROVEEDORES!$B:$C,2,FALSE)) | E27: 0 | G27: BILLETES DE 2.000 | H27: 0 | I27: =2000*H27 -> 0
A28: =IF(B28="","",VLOOKUP(B28,PROVEEDORES!$B:$C,2,FALSE)) | E28: 0 | G28: BILLETES DE 5.000 | H28: 0 | I28: =5000*H28 -> 0
A29: =IF(B29="","",VLOOKUP(B29,PROVEEDORES!$B:$C,2,FALSE)) | E29: 0 | G29: BILLETES DE 10.000 | H29: 0 | I29: =10000*H29 -> 0
A30: =IF(B30="","",VLOOKUP(B30,PROVEEDORES!$B:$C,2,FALSE)) | E30: 0 | G30: BILLETES DE 20.000 | H30: 0 | I30: =20000*H30 -> 0
A31: =IF(B31="","",VLOOKUP(B31,PROVEEDORES!$B:$C,2,FALSE)) | E31: 0 | G31: BILLETES DE 50.000 | H31: 0 | I31: =50000*H31 -> 0
A32: =IF(B32="","",VLOOKUP(B32,PROVEEDORES!$B:$C,2,FALSE)) | E32: 0 | G32: BILLETES DE 100.000 | H32: 0 | I32: =100000*H32 -> 0
A33: =IF(B33="","",VLOOKUP(B33,PROVEEDORES!$B:$C,2,FALSE)) | E33: 0 | G33: TOTAL EFECTIVO: | I33: =SUM(I23:I32) -> 0
A34: =IF(B34="","",VLOOKUP(B34,PROVEEDORES!$B:$C,2,FALSE)) | E34: 0 | G34: BASE: | I34: 0
A35: NIT | B35: PROVEEDOR | C35: CONCEPTO | D35: DESCRIPCIÓN | E35: BANCO | G35: TOTAL EFECTIVO MENOS LA BASE: | I35: =I33-I34 -> 0
A36: =IF(B36="","",VLOOKUP(B36,PROVEEDORES!$B:$C,2,FALSE)) | E36: 0
A37: =IF(B37="","",VLOOKUP(B37,PROVEEDORES!$B:$C,2,FALSE)) | E37: 0 | G37: ACUM. DE PROPINA TRANSFERENCIA: | I37: =+'28'!E13 -> 0
A38: =IF(B38="","",VLOOKUP(B38,PROVEEDORES!$B:$C,2,FALSE)) | E38: 0 | G38: ACUMULADO DE PROPINA EN BANCO: | I38: =+'28'!E14 -> 0
A39: =IF(B39="","",VLOOKUP(B39,PROVEEDORES!$B:$C,2,FALSE)) | E39: 0 | G39: ACUMULADO DE PROPINA POR EFECTIVO: | I39: =+'28'!E15 -> 0
A40: =IF(B40="","",VLOOKUP(B40,PROVEEDORES!$B:$C,2,FALSE)) | E40: 0 | G40: ACUMULADO DE TRANSFERENCIA: | I40: =+'28'!E16 -> 0
A41: =IF(B41="","",VLOOKUP(B41,PROVEEDORES!$B:$C,2,FALSE)) | E41: 0 | G41: ACUMULADO DE BANCO: | I41: =+'28'!E17 -> 0
A42: =IF(B42="","",VLOOKUP(B42,PROVEEDORES!$B:$C,2,FALSE)) | E42: 0 | G42: REAL DE BANCO: | I42: =+'28'!E18 -> 0
A43: =IF(B43="","",VLOOKUP(B43,PROVEEDORES!$B:$C,2,FALSE)) | E43: 0 | G43: EFECTIVO ANTERIOR: | I43: =+'28'!E19 -> 0
A44: =IF(B44="","",VLOOKUP(B44,PROVEEDORES!$B:$C,2,FALSE)) | E44: 0
A45: =IF(B45="","",VLOOKUP(B45,PROVEEDORES!$B:$C,2,FALSE)) | E45: 0
A46: =IF(B46="","",VLOOKUP(B46,PROVEEDORES!$B:$C,2,FALSE)) | E46: 0
A47: =IF(B47="","",VLOOKUP(B47,PROVEEDORES!$B:$C,2,FALSE)) | E47: 0
A48: =IF(B48="","",VLOOKUP(B48,PROVEEDORES!$B:$C,2,FALSE)) | E48: 0
A49: =IF(B49="","",VLOOKUP(B49,PROVEEDORES!$B:$C,2,FALSE)) | E49: 0
A50: =IF(B50="","",VLOOKUP(B50,PROVEEDORES!$B:$C,2,FALSE)) | E50: 0
A51: =IF(B51="","",VLOOKUP(B51,PROVEEDORES!$B:$C,2,FALSE)) | E51: 0
A52: =IF(B52="","",VLOOKUP(B52,PROVEEDORES!$B:$C,2,FALSE)) | E52: 0
A53: =IF(B53="","",VLOOKUP(B53,PROVEEDORES!$B:$C,2,FALSE)) | E53: 0
A54: =IF(B54="","",VLOOKUP(B54,PROVEEDORES!$B:$C,2,FALSE)) | E54: 0
A55: =IF(B55="","",VLOOKUP(B55,PROVEEDORES!$B:$C,2,FALSE)) | E55: 0
A56: EGRESO PROPINA | D56: INGRESO DE EFECTIVO
A57: PROPINA TRANSFERENCIA: | C57: 0 | E57: 0
A58: PROPINA BANCO: | C58: 0 | E58: 0
A59: PROPINA EFECTIVO: | C59: 0 | E59: 0

Sheet 30
A1: ='29'!A1+1 -> 30 | B1: =+'1'!B1 -> QUESO Y CAFÉ | D1: =+'29'!D1:E1+1 -> 46172 | G1: CUADRE DE CAJA MAÑANA | I1: CUADRE DE CAJA TARDE
A2: NIT | B2: PROVEEDOR | C2: CONCEPTO | D2: DESCRIPCIÓN | E2: VALOR | G2: PROP. TRANSF.: | H2: 0 | I2: PROP. TRANSF.: | J2: 0
A3: =IF(B3="","",VLOOKUP(B3,PROVEEDORES!$B:$C,2,FALSE)) | E3: 0 | G3: PROP. BANCO: | H3: 0 | I3: PROP. BANCO: | J3: 0
A4: =IF(B4="","",VLOOKUP(B4,PROVEEDORES!$B:$C,2,FALSE)) | E4: 0 | G4: PROP. EFECTIVO: | H4: 0 | I4: PROP. EFECTIVO: | J4: 0
A5: =IF(B5="","",VLOOKUP(B5,PROVEEDORES!$B:$C,2,FALSE)) | E5: 0 | G5: GASTO: | H5: 0 | I5: GASTO: | J5: 0
A6: =IF(B6="","",VLOOKUP(B6,PROVEEDORES!$B:$C,2,FALSE)) | E6: 0 | G6: TRANSFERENCIA: | H6: 0 | I6: TRANSFERENCIA: | J6: 0
A7: =IF(B7="","",VLOOKUP(B7,PROVEEDORES!$B:$C,2,FALSE)) | E7: 0 | G7: BANCO: | H7: 0 | I7: BANCO: | J7: 0
A8: =IF(B8="","",VLOOKUP(B8,PROVEEDORES!$B:$C,2,FALSE)) | E8: 0 | G8: EFECTIVO: | H8: 0 | I8: EFECTIVO: | J8: 0
A9: =IF(B9="","",VLOOKUP(B9,PROVEEDORES!$B:$C,2,FALSE)) | E9: 0 | G9: TOTAL: | H9: =SUM(H5:H8) -> 0 | I9: TOTAL: | J9: =SUM(J5:J8) -> 0
A10: =IF(B10="","",VLOOKUP(B10,PROVEEDORES!$B:$C,2,FALSE)) | E10: 0 | G10: DIFERENCIA: | H10: =+H11-H9 -> 0 | I10: DIFERENCIA: | J10: =+J11-J9 -> 0
A11: =IF(B11="","",VLOOKUP(B11,PROVEEDORES!$B:$C,2,FALSE)) | E11: 0 | G11: TOTAL VENTA: | H11: 0 | I11: TOTAL VENTA: | J11: 0
A12: =IF(B12="","",VLOOKUP(B12,PROVEEDORES!$B:$C,2,FALSE)) | E12: 0
A13: PROPINA TRANSFERENCIA: | C13: =SUM(H2,J2) -> 0 | D13: ACUM. PROPINA TRANFERENCIA: | E13: =SUM(C13,I37)-C57 -> 0 | G13: DIFERENCIA PLANILLA VS CUADRE DE CAJA | I13: =+C20-(SUM(H9,J9)) -> 0
A14: PROPINA POR BANCO: | C14: =SUM(H3,J3) -> 0 | D14: ACUM. PROPINA BANCO: | E14: =SUM(C14,I38)-C58 -> 0
A15: PROPINA EN EFECTIVO: | C15: =SUM(H4,J4) -> 0 | D15: ACUM. PROPINA EFECTIVO: | E15: =SUM(C15,I39)-C59 -> 0 | G15: FACTURAS EN EFECTIVO: | I15: 0
A16: TOTAL EGRESOS: | C16: =SUM(E3:E12) -> 0 | D16: ACUMULADO TRANSFERENCIA: | E16: =SUM(C17,I40) -> 0 | G16: EFECTIVO: | I16: 0
A17: TRANSFERENCIA: | C17: =SUM(H6,J6) -> 0 | D17: ACUMULADO BANCO: | E17: =SUM(C18,I41) -> 0 | G17: TOTAL EFECTIVO REAL ACTUAL: | I17: =SUM(I15,I16) -> 0
A18: BANCO: | C18: =SUM(H7,J7) -> 0 | D18: TOTAL BANCO: | E18: =SUM(C18,I42)-(SUM(E36:E55)) -> 0 | G18: DIFERENCIA: | I18: =+I19-I17 -> 0
A19: EFECTIVO: | C19: =SUM(H8,J8) -> 0 | D19: TOTAL EFECTIVO: | E19: =SUM(C19,E20,E57:E59)-(SUM(E23:E34)) -> 0 | G19: EFECTIVO ACTUAL PLANILLA: | I19: =E19 -> 0
A20: TOTAL VENTA: | C20: =SUM(C16:C19) -> 0 | D20: EFECTIVO ANTERIOR: | E20: =+I43 -> 0
A21: EGRESO DE CAJA MAYOR | G21: CONTEO DE EFECTIVO
A22: NIT | B22: PROVEEDOR | C22: CONCEPTO | D22: DESCRIPCIÓN | E22: EFECTIVO | G22: DENOMINACIÓN | H22: CANTIDAD | I22: EFECTIVO
A23: =IF(B23="","",VLOOKUP(B23,PROVEEDORES!$B:$C,2,FALSE)) | E23: 0 | G23: MONEDAS DE 100 | H23: 0 | I23: =100*H23 -> 0
A24: =IF(B24="","",VLOOKUP(B24,PROVEEDORES!$B:$C,2,FALSE)) | E24: 0 | G24: MONEDAS DE 200 | H24: 0 | I24: =200*H24 -> 0
A25: =IF(B25="","",VLOOKUP(B25,PROVEEDORES!$B:$C,2,FALSE)) | E25: 0 | G25: MONEDAS DE 500 | H25: 0 | I25: =500*H25 -> 0
A26: =IF(B26="","",VLOOKUP(B26,PROVEEDORES!$B:$C,2,FALSE)) | E26: 0 | G26: MONEDAS DE 1.000 | H26: 0 | I26: =1000*H26 -> 0
A27: =IF(B27="","",VLOOKUP(B27,PROVEEDORES!$B:$C,2,FALSE)) | E27: 0 | G27: BILLETES DE 2.000 | H27: 0 | I27: =2000*H27 -> 0
A28: =IF(B28="","",VLOOKUP(B28,PROVEEDORES!$B:$C,2,FALSE)) | E28: 0 | G28: BILLETES DE 5.000 | H28: 0 | I28: =5000*H28 -> 0
A29: =IF(B29="","",VLOOKUP(B29,PROVEEDORES!$B:$C,2,FALSE)) | E29: 0 | G29: BILLETES DE 10.000 | H29: 0 | I29: =10000*H29 -> 0
A30: =IF(B30="","",VLOOKUP(B30,PROVEEDORES!$B:$C,2,FALSE)) | E30: 0 | G30: BILLETES DE 20.000 | H30: 0 | I30: =20000*H30 -> 0
A31: =IF(B31="","",VLOOKUP(B31,PROVEEDORES!$B:$C,2,FALSE)) | E31: 0 | G31: BILLETES DE 50.000 | H31: 0 | I31: =50000*H31 -> 0
A32: =IF(B32="","",VLOOKUP(B32,PROVEEDORES!$B:$C,2,FALSE)) | E32: 0 | G32: BILLETES DE 100.000 | H32: 0 | I32: =100000*H32 -> 0
A33: =IF(B33="","",VLOOKUP(B33,PROVEEDORES!$B:$C,2,FALSE)) | E33: 0 | G33: TOTAL EFECTIVO: | I33: =SUM(I23:I32) -> 0
A34: =IF(B34="","",VLOOKUP(B34,PROVEEDORES!$B:$C,2,FALSE)) | E34: 0 | G34: BASE: | I34: 0
A35: NIT | B35: PROVEEDOR | C35: CONCEPTO | D35: DESCRIPCIÓN | E35: BANCO | G35: TOTAL EFECTIVO MENOS LA BASE: | I35: =I33-I34 -> 0
A36: =IF(B36="","",VLOOKUP(B36,PROVEEDORES!$B:$C,2,FALSE)) | E36: 0
A37: =IF(B37="","",VLOOKUP(B37,PROVEEDORES!$B:$C,2,FALSE)) | E37: 0 | G37: ACUM. DE PROPINA TRANSFERENCIA: | I37: =+'29'!E13 -> 0
A38: =IF(B38="","",VLOOKUP(B38,PROVEEDORES!$B:$C,2,FALSE)) | E38: 0 | G38: ACUMULADO DE PROPINA EN BANCO: | I38: =+'29'!E14 -> 0
A39: =IF(B39="","",VLOOKUP(B39,PROVEEDORES!$B:$C,2,FALSE)) | E39: 0 | G39: ACUMULADO DE PROPINA POR EFECTIVO: | I39: =+'29'!E15 -> 0
A40: =IF(B40="","",VLOOKUP(B40,PROVEEDORES!$B:$C,2,FALSE)) | E40: 0 | G40: ACUMULADO DE TRANSFERENCIA: | I40: =+'29'!E16 -> 0
A41: =IF(B41="","",VLOOKUP(B41,PROVEEDORES!$B:$C,2,FALSE)) | E41: 0 | G41: ACUMULADO DE BANCO: | I41: =+'29'!E17 -> 0
A42: =IF(B42="","",VLOOKUP(B42,PROVEEDORES!$B:$C,2,FALSE)) | E42: 0 | G42: REAL DE BANCO: | I42: =+'29'!E18 -> 0
A43: =IF(B43="","",VLOOKUP(B43,PROVEEDORES!$B:$C,2,FALSE)) | E43: 0 | G43: EFECTIVO ANTERIOR: | I43: =+'29'!E19 -> 0
A44: =IF(B44="","",VLOOKUP(B44,PROVEEDORES!$B:$C,2,FALSE)) | E44: 0
A45: =IF(B45="","",VLOOKUP(B45,PROVEEDORES!$B:$C,2,FALSE)) | E45: 0
A46: =IF(B46="","",VLOOKUP(B46,PROVEEDORES!$B:$C,2,FALSE)) | E46: 0
A47: =IF(B47="","",VLOOKUP(B47,PROVEEDORES!$B:$C,2,FALSE)) | E47: 0
A48: =IF(B48="","",VLOOKUP(B48,PROVEEDORES!$B:$C,2,FALSE)) | E48: 0
A49: =IF(B49="","",VLOOKUP(B49,PROVEEDORES!$B:$C,2,FALSE)) | E49: 0
A50: =IF(B50="","",VLOOKUP(B50,PROVEEDORES!$B:$C,2,FALSE)) | E50: 0
A51: =IF(B51="","",VLOOKUP(B51,PROVEEDORES!$B:$C,2,FALSE)) | E51: 0
A52: =IF(B52="","",VLOOKUP(B52,PROVEEDORES!$B:$C,2,FALSE)) | E52: 0
A53: =IF(B53="","",VLOOKUP(B53,PROVEEDORES!$B:$C,2,FALSE)) | E53: 0
A54: =IF(B54="","",VLOOKUP(B54,PROVEEDORES!$B:$C,2,FALSE)) | E54: 0
A55: =IF(B55="","",VLOOKUP(B55,PROVEEDORES!$B:$C,2,FALSE)) | E55: 0
A56: EGRESO PROPINA | D56: INGRESO DE EFECTIVO
A57: PROPINA TRANSFERENCIA: | C57: 0 | E57: 0
A58: PROPINA BANCO: | C58: 0 | E58: 0
A59: PROPINA EFECTIVO: | C59: 0 | E59: 0

Sheet 31
A1: ='30'!A1+1 -> 31 | B1: =+'1'!B1 -> QUESO Y CAFÉ | D1: =+'30'!D1:E1+1 -> 46173 | G1: CUADRE DE CAJA MAÑANA | I1: CUADRE DE CAJA TARDE
A2: NIT | B2: PROVEEDOR | C2: CONCEPTO | D2: DESCRIPCIÓN | E2: VALOR | G2: PROP. TRANSF.: | H2: 0 | I2: PROP. TRANSF.: | J2: 0
A3: =IF(B3="","",VLOOKUP(B3,PROVEEDORES!$B:$C,2,FALSE)) | E3: 0 | G3: PROP. BANCO: | H3: 0 | I3: PROP. BANCO: | J3: 0
A4: =IF(B4="","",VLOOKUP(B4,PROVEEDORES!$B:$C,2,FALSE)) | E4: 0 | G4: PROP. EFECTIVO: | H4: 0 | I4: PROP. EFECTIVO: | J4: 0
A5: =IF(B5="","",VLOOKUP(B5,PROVEEDORES!$B:$C,2,FALSE)) | E5: 0 | G5: GASTO: | H5: 0 | I5: GASTO: | J5: 0
A6: =IF(B6="","",VLOOKUP(B6,PROVEEDORES!$B:$C,2,FALSE)) | E6: 0 | G6: TRANSFERENCIA: | H6: 0 | I6: TRANSFERENCIA: | J6: 0
A7: =IF(B7="","",VLOOKUP(B7,PROVEEDORES!$B:$C,2,FALSE)) | E7: 0 | G7: BANCO: | H7: 0 | I7: BANCO: | J7: 0
A8: =IF(B8="","",VLOOKUP(B8,PROVEEDORES!$B:$C,2,FALSE)) | E8: 0 | G8: EFECTIVO: | H8: 0 | I8: EFECTIVO: | J8: 0
A9: =IF(B9="","",VLOOKUP(B9,PROVEEDORES!$B:$C,2,FALSE)) | E9: 0 | G9: TOTAL: | H9: =SUM(H5:H8) -> 0 | I9: TOTAL: | J9: =SUM(J5:J8) -> 0
A10: =IF(B10="","",VLOOKUP(B10,PROVEEDORES!$B:$C,2,FALSE)) | E10: 0 | G10: DIFERENCIA: | H10: =+H11-H9 -> 0 | I10: DIFERENCIA: | J10: =+J11-J9 -> 0
A11: =IF(B11="","",VLOOKUP(B11,PROVEEDORES!$B:$C,2,FALSE)) | E11: 0 | G11: TOTAL VENTA: | H11: 0 | I11: TOTAL VENTA: | J11: 0
A12: =IF(B12="","",VLOOKUP(B12,PROVEEDORES!$B:$C,2,FALSE)) | E12: 0
A13: PROPINA TRANSFERENCIA: | C13: =SUM(H2,J2) -> 0 | D13: ACUM. PROPINA TRANFERENCIA: | E13: =SUM(C13,I37)-C57 -> 0 | G13: DIFERENCIA PLANILLA VS CUADRE DE CAJA | I13: =+C20-(SUM(H9,J9)) -> 0
A14: PROPINA POR BANCO: | C14: =SUM(H3,J3) -> 0 | D14: ACUM. PROPINA BANCO: | E14: =SUM(C14,I38)-C58 -> 0
A15: PROPINA EN EFECTIVO: | C15: =SUM(H4,J4) -> 0 | D15: ACUM. PROPINA EFECTIVO: | E15: =SUM(C15,I39)-C59 -> 0 | G15: FACTURAS EN EFECTIVO: | I15: 0
A16: TOTAL EGRESOS: | C16: =SUM(E3:E12) -> 0 | D16: ACUMULADO TRANSFERENCIA: | E16: =SUM(C17,I40) -> 0 | G16: EFECTIVO: | I16: 0
A17: TRANSFERENCIA: | C17: =SUM(H6,J6) -> 0 | D17: ACUMULADO BANCO: | E17: =SUM(C18,I41) -> 0 | G17: TOTAL EFECTIVO REAL ACTUAL: | I17: =SUM(I15,I16) -> 0
A18: BANCO: | C18: =SUM(H7,J7) -> 0 | D18: TOTAL BANCO: | E18: =SUM(C18,I42)-(SUM(E36:E55)) -> 0 | G18: DIFERENCIA: | I18: =+I19-I17 -> 0
A19: EFECTIVO: | C19: =SUM(H8,J8) -> 0 | D19: TOTAL EFECTIVO: | E19: =SUM(C19,E20,E57:E59)-(SUM(E23:E34)) -> 0 | G19: EFECTIVO ACTUAL PLANILLA: | I19: =E19 -> 0
A20: TOTAL VENTA: | C20: =SUM(C16:C19) -> 0 | D20: EFECTIVO ANTERIOR: | E20: =+I43 -> 0
A21: EGRESO DE CAJA MAYOR | G21: CONTEO DE EFECTIVO
A22: NIT | B22: PROVEEDOR | C22: CONCEPTO | D22: DESCRIPCIÓN | E22: EFECTIVO | G22: DENOMINACIÓN | H22: CANTIDAD | I22: EFECTIVO
A23: =IF(B23="","",VLOOKUP(B23,PROVEEDORES!$B:$C,2,FALSE)) | E23: 0 | G23: MONEDAS DE 100 | H23: 0 | I23: =100*H23 -> 0
A24: =IF(B24="","",VLOOKUP(B24,PROVEEDORES!$B:$C,2,FALSE)) | E24: 0 | G24: MONEDAS DE 200 | H24: 0 | I24: =200*H24 -> 0
A25: =IF(B25="","",VLOOKUP(B25,PROVEEDORES!$B:$C,2,FALSE)) | E25: 0 | G25: MONEDAS DE 500 | H25: 0 | I25: =500*H25 -> 0
A26: =IF(B26="","",VLOOKUP(B26,PROVEEDORES!$B:$C,2,FALSE)) | E26: 0 | G26: MONEDAS DE 1.000 | H26: 0 | I26: =1000*H26 -> 0
A27: =IF(B27="","",VLOOKUP(B27,PROVEEDORES!$B:$C,2,FALSE)) | E27: 0 | G27: BILLETES DE 2.000 | H27: 0 | I27: =2000*H27 -> 0
A28: =IF(B28="","",VLOOKUP(B28,PROVEEDORES!$B:$C,2,FALSE)) | E28: 0 | G28: BILLETES DE 5.000 | H28: 0 | I28: =5000*H28 -> 0
A29: =IF(B29="","",VLOOKUP(B29,PROVEEDORES!$B:$C,2,FALSE)) | E29: 0 | G29: BILLETES DE 10.000 | H29: 0 | I29: =10000*H29 -> 0
A30: =IF(B30="","",VLOOKUP(B30,PROVEEDORES!$B:$C,2,FALSE)) | E30: 0 | G30: BILLETES DE 20.000 | H30: 0 | I30: =20000*H30 -> 0
A31: =IF(B31="","",VLOOKUP(B31,PROVEEDORES!$B:$C,2,FALSE)) | E31: 0 | G31: BILLETES DE 50.000 | H31: 0 | I31: =50000*H31 -> 0
A32: =IF(B32="","",VLOOKUP(B32,PROVEEDORES!$B:$C,2,FALSE)) | E32: 0 | G32: BILLETES DE 100.000 | H32: 0 | I32: =100000*H32 -> 0
A33: =IF(B33="","",VLOOKUP(B33,PROVEEDORES!$B:$C,2,FALSE)) | E33: 0 | G33: TOTAL EFECTIVO: | I33: =SUM(I23:I32) -> 0
A34: =IF(B34="","",VLOOKUP(B34,PROVEEDORES!$B:$C,2,FALSE)) | E34: 0 | G34: BASE: | I34: 0
A35: NIT | B35: PROVEEDOR | C35: CONCEPTO | D35: DESCRIPCIÓN | E35: BANCO | G35: TOTAL EFECTIVO MENOS LA BASE: | I35: =I33-I34 -> 0
A36: =IF(B36="","",VLOOKUP(B36,PROVEEDORES!$B:$C,2,FALSE)) | E36: 0
A37: =IF(B37="","",VLOOKUP(B37,PROVEEDORES!$B:$C,2,FALSE)) | E37: 0 | G37: ACUM. DE PROPINA TRANSFERENCIA: | I37: =+'30'!E13 -> 0
A38: =IF(B38="","",VLOOKUP(B38,PROVEEDORES!$B:$C,2,FALSE)) | E38: 0 | G38: ACUMULADO DE PROPINA EN BANCO: | I38: =+'30'!E14 -> 0
A39: =IF(B39="","",VLOOKUP(B39,PROVEEDORES!$B:$C,2,FALSE)) | E39: 0 | G39: ACUMULADO DE PROPINA POR EFECTIVO: | I39: =+'30'!E15 -> 0
A40: =IF(B40="","",VLOOKUP(B40,PROVEEDORES!$B:$C,2,FALSE)) | E40: 0 | G40: ACUMULADO DE TRANSFERENCIA: | I40: =+'30'!E16 -> 0
A41: =IF(B41="","",VLOOKUP(B41,PROVEEDORES!$B:$C,2,FALSE)) | E41: 0 | G41: ACUMULADO DE BANCO: | I41: =+'30'!E17 -> 0
A42: =IF(B42="","",VLOOKUP(B42,PROVEEDORES!$B:$C,2,FALSE)) | E42: 0 | G42: REAL DE BANCO: | I42: =+'30'!E18 -> 0
A43: =IF(B43="","",VLOOKUP(B43,PROVEEDORES!$B:$C,2,FALSE)) | E43: 0 | G43: EFECTIVO ANTERIOR: | I43: =+'30'!E19 -> 0
A44: =IF(B44="","",VLOOKUP(B44,PROVEEDORES!$B:$C,2,FALSE)) | E44: 0
A45: =IF(B45="","",VLOOKUP(B45,PROVEEDORES!$B:$C,2,FALSE)) | E45: 0
A46: =IF(B46="","",VLOOKUP(B46,PROVEEDORES!$B:$C,2,FALSE)) | E46: 0
A47: =IF(B47="","",VLOOKUP(B47,PROVEEDORES!$B:$C,2,FALSE)) | E47: 0
A48: =IF(B48="","",VLOOKUP(B48,PROVEEDORES!$B:$C,2,FALSE)) | E48: 0
A49: =IF(B49="","",VLOOKUP(B49,PROVEEDORES!$B:$C,2,FALSE)) | E49: 0
A50: =IF(B50="","",VLOOKUP(B50,PROVEEDORES!$B:$C,2,FALSE)) | E50: 0
A51: =IF(B51="","",VLOOKUP(B51,PROVEEDORES!$B:$C,2,FALSE)) | E51: 0
A52: =IF(B52="","",VLOOKUP(B52,PROVEEDORES!$B:$C,2,FALSE)) | E52: 0
A53: =IF(B53="","",VLOOKUP(B53,PROVEEDORES!$B:$C,2,FALSE)) | E53: 0
A54: =IF(B54="","",VLOOKUP(B54,PROVEEDORES!$B:$C,2,FALSE)) | E54: 0
A55: =IF(B55="","",VLOOKUP(B55,PROVEEDORES!$B:$C,2,FALSE)) | E55: 0
A56: EGRESO PROPINA | D56: INGRESO DE EFECTIVO
A57: PROPINA TRANSFERENCIA: | C57: 0 | E57: 0
A58: PROPINA BANCO: | C58: 0 | E58: 0
A59: PROPINA EFECTIVO: | C59: 0 | E59: 0

Sheet TOTAL
B2: PROYECCIÓN | C2: TOTAL VENTA | D2: FECHA | F2: CONCEPTO | G2: VALOR | H2: %
B3: =SUM(B4:B34) -> 0 | C3: =SUM(C4:C34)+DETALLADO!C69-DETALLADO!C61 -> 0 | F3: =+DETALLADO!B3 -> COMPRAS (M.P.) | G3: =+DETALLADO!C3 -> 0 | H3: =IF(ISERROR(G3/$C$3),"0%",G3/$C$3) -> 0%
B4: 0 | C4: =+'1'!C20 -> 0 | D4: =+'1'!D1 -> 46143 | F4: =+DETALLADO!B25 -> ASEO | G4: =+DETALLADO!C25 -> 0 | H4: =IF(ISERROR(G4/$C$3),"0%",G4/$C$3) -> 0%
B5: 0 | C5: =+'2'!C20 -> 0 | D5: =+'2'!D1 -> 46144 | F5: =+DETALLADO!B27 -> DESECHABLES | G5: =+DETALLADO!C27 -> 0 | H5: =IF(ISERROR(G5/$C$3),"0%",G5/$C$3) -> 0%
B6: 0 | C6: =+'3'!C20 -> 0 | D6: =+'3'!D1 -> 46145 | F6: =+DETALLADO!B38 -> PAPELERIA Y DECORACION | G6: =+DETALLADO!C38 -> 0 | H6: =IF(ISERROR(G6/$C$3),"0%",G6/$C$3) -> 0%
B7: 0 | C7: =+'4'!C20 -> 0 | D7: =+'4'!D1 -> 46146 | F7: =+DETALLADO!B34 -> MANTENIMIENTO | G7: =+DETALLADO!C34 -> 0 | H7: =IF(ISERROR(G7/$C$3),"0%",G7/$C$3) -> 0%
B8: 0 | C8: =+'5'!C20 -> 0 | D8: =+'5'!D1 -> 46147 | F8: =+DETALLADO!B22 -> SEGURIDAD SOCIAL | G8: =+DETALLADO!C22 -> 0 | H8: =IF(ISERROR(G8/$C$3),"0%",G8/$C$3) -> 0%
B9: 0 | C9: =+'6'!C20 -> 0 | D9: =+'6'!D1 -> 46148 | F9: =+DETALLADO!B23 -> NÓMINA | G9: =+DETALLADO!C23 -> 0 | H9: =IF(ISERROR(G9/$C$3),"0%",G9/$C$3) -> 0%
B10: 0 | C10: =+'7'!C20 -> 0 | D10: =+'7'!D1 -> 46149 | F10: =+DETALLADO!B24 -> TURNOS Y H. EXTRAS | G10: =+DETALLADO!C24 -> 0 | H10: =IF(ISERROR(G10/$C$3),"0%",G10/$C$3) -> 0%
B11: 0 | C11: =+'8'!C20 -> 0 | D11: =+'8'!D1 -> 46150
B12: 0 | C12: =+'9'!C20 -> 0 | D12: =+'9'!D1 -> 46151 | F12: % MATERIA PRIMA
B13: 0 | C13: =+'10'!C20 -> 0 | D13: =+'10'!D1 -> 46152 | F13: INVENTARIO INICIAL: | G13: 0
B14: 0 | C14: =+'11'!C20 -> 0 | D14: =+'11'!D1 -> 46153 | F14: INVENTARIO FINAL: | G14: 0
B15: 0 | C15: =+'12'!C20 -> 0 | D15: =+'12'!D1 -> 46154 | F15: AVERIAS: | G15: 0
B16: 0 | C16: =+'13'!C20 -> 0 | D16: =+'13'!D1 -> 46155 | F16: COMPRAS: | G16: =+DETALLADO!C3 -> 0 | H16: =IF(ISERROR(G16/C3),"0%",G16/C3) -> 0%
B17: 0 | C17: =+'14'!C20 -> 0 | D17: =+'14'!D1 -> 46156 | F17: TOTAL: | G17: =+G13-G14-G15+G16 -> 0 | H17: =IF(ISERROR(G17/C3),"0%",G17/C3) -> 0%
B18: 0 | C18: =+'15'!C20 -> 0 | D18: =+'15'!D1 -> 46157
B19: 0 | C19: =+'16'!C20 -> 0 | D19: =+'16'!D1 -> 46158 | F19: % NÓMINA
B20: 0 | C20: =+'17'!C20 -> 0 | D20: =+'17'!D1 -> 46159 | F20: SEGURIDAD SOCIAL: | G20: =+DETALLADO!C22 -> 0 | H20: =IF(ISERROR(G20/$C$3),"0%",G20/$C$3) -> 0%
B21: 0 | C21: =+'18'!C20 -> 0 | D21: =+'18'!D1 -> 46160 | F21: NÓMINA: | G21: =+DETALLADO!C23 -> 0 | H21: =IF(ISERROR(G21/$C$3),"0%",G21/$C$3) -> 0%
B22: 0 | C22: =+'19'!C20 -> 0 | D22: =+'19'!D1 -> 46161 | F22: TURNOS Y H. EXTRAS: | G22: =+DETALLADO!C24 -> 0 | H22: =IF(ISERROR(G22/$C$3),"0%",G22/$C$3) -> 0%
B23: 0 | C23: =+'20'!C20 -> 0 | D23: =+'20'!D1 -> 46162 | F23: TOTAL: | G23: =SUM(G20:G22) -> 0 | H23: =IF(ISERROR(G23/$C$3),"0%",G23/$C$3) -> 0%
B24: 0 | C24: =+'21'!C20 -> 0 | D24: =+'21'!D1 -> 46163
B25: 0 | C25: =+'22'!C20 -> 0 | D25: =+'22'!D1 -> 46164 | F25: SIMULACIÓN, (SE MODIFICAN LA VENTA Y LOS PORCENTAJES)
B26: 0 | C26: =+'23'!C20 -> 0 | D26: =+'23'!D1 -> 46165 | F26: VENTA: | G26: 0 | H26: %
B27: 0 | C27: =+'24'!C20 -> 0 | D27: =+'24'!D1 -> 46166 | F27: MATERIA PRIMA: | G27: =G26*H27 -> 0 | H27: 0
B28: 0 | C28: =+'25'!C20 -> 0 | D28: =+'25'!D1 -> 46167 | F28: NÓMINA: | G28: =G26*H28 -> 0 | H28: 0
B29: 0 | C29: =+'26'!C20 -> 0 | D29: =+'26'!D1 -> 46168
B30: 0 | C30: =+'27'!C20 -> 0 | D30: =+'27'!D1 -> 46169 | F30: SIMULACIÓN, (SE MODIFICA LA VENTA Y EL EFECTIVO)
B31: 0 | C31: =+'28'!C20 -> 0 | D31: =+'28'!D1 -> 46170 | F31: VENTA: | G31: 0 | H31: %
B32: 0 | C32: =+'29'!C20 -> 0 | D32: =+'29'!D1 -> 46171 | F32: MATERIA PRIMA: | G32: 0 | H32: =IF(ISERROR(G32/G31),"0%",G32/G31) -> 0%
B33: 0 | C33: =+'30'!C20 -> 0 | D33: =+'30'!D1 -> 46172 | F33: NÓMINA: | G33: 0 | H33: =IF(ISERROR(G33/G31),"0%",G33/G31) -> 0%
B34: 0 | C34: =+'31'!C20 -> 0 | D34: =+'31'!D1 -> 46173

Sheet DETALLADO
B1: TOTAL DE EGRESOS
B2: CONCEPTO | C2: VALOR TOTAL | D2: % | F2: FECHA | G2: NIT | H2: PROVEEDOR | I2: CONCEPTO | J2: DESCRIPCIÓN | K2: VALOR | M2: FECHA | N2: NIT | O2: PROVEEDOR | P2: CONCEPTO | Q2: DESCRIPCIÓN | R2: EFECTIVO | T2: FECHA | U2: NIT | V2: PROVEEDOR | W2: CONCEPTO | X2: DESCRIPCIÓN | Y2: BANCO | AA2: FECHA | AB2: DESCRIPCIÓN | AC2: EFECTIVO
B3: COMPRAS (M.P.) | C3: =SUMIF(I:I,B3,K:K)+SUMIF(P:P,B3,R:R)+SUMIF(W:W,B3,Y:Y) -> 0 | D3: =IF(ISERROR(C3/TOTAL!$C$3),"0%",C3/TOTAL!$C$3) -> 0% | F3: =+'1'!D1 -> 46143 | G3: =+'1'!A3 | H3: =+'1'!B3 -> 0 | I3: =+'1'!C3 -> 0 | J3: =+'1'!D3 -> 0 | K3: =+'1'!E3 -> 0 | M3: =+'1'!D1 -> 46143 | N3: =+'1'!A23 | O3: =+'1'!B23 -> 0 | P3: =+'1'!C23 -> 0 | Q3: =+'1'!D23 -> 0 | R3: =+'1'!E23 -> 0 | T3: =+'1'!D1 -> 46143 | U3: =+'1'!A36 | V3: =+'1'!B36 -> 0 | W3: =+'1'!C36 -> 0 | X3: =+'1'!D36 -> 0 | Y3: =+'1'!E36 -> 0 | AA3: =+'1'!D1 -> 46143 | AB3: =+'1'!D57 -> 0 | AC3: =+'1'!E57 -> 0
B4: ARRIENDO | C4: =SUMIF(I:I,B4,K:K)+SUMIF(P:P,B4,R:R)+SUMIF(W:W,B4,Y:Y) -> 0 | D4: =IF(ISERROR(C4/TOTAL!$C$3),"0%",C4/TOTAL!$C$3) -> 0% | F4: =+'1'!D1 -> 46143 | G4: =+'1'!A4 | H4: =+'1'!B4 -> 0 | I4: =+'1'!C4 -> 0 | J4: =+'1'!D4 -> 0 | K4: =+'1'!E4 -> 0 | M4: =+'1'!D1 -> 46143 | N4: =+'1'!A24 | O4: =+'1'!B24 -> 0 | P4: =+'1'!C24 -> 0 | Q4: =+'1'!D24 -> 0 | R4: =+'1'!E24 -> 0 | T4: =+'1'!D1 -> 46143 | U4: =+'1'!A37 | V4: =+'1'!B37 -> 0 | W4: =+'1'!C37 -> 0 | X4: =+'1'!D37 -> 0 | Y4: =+'1'!E37 -> 0 | AA4: =+'1'!D1 -> 46143 | AB4: =+'1'!D58 -> 0 | AC4: =+'1'!E58 -> 0
B5: MENSUALIDAD ADMINISTRACIÓN | C5: =SUMIF(I:I,B5,K:K)+SUMIF(P:P,B5,R:R)+SUMIF(W:W,B5,Y:Y) -> 0 | D5: =IF(ISERROR(C5/TOTAL!$C$3),"0%",C5/TOTAL!$C$3) -> 0% | F5: =+'1'!D1 -> 46143 | G5: =+'1'!A5 | H5: =+'1'!B5 -> 0 | I5: =+'1'!C5 -> 0 | J5: =+'1'!D5 -> 0 | K5: =+'1'!E5 -> 0 | M5: =+'1'!D1 -> 46143 | N5: =+'1'!A25 | O5: =+'1'!B25 -> 0 | P5: =+'1'!C25 -> 0 | Q5: =+'1'!D25 -> 0 | R5: =+'1'!E25 -> 0 | T5: =+'1'!D1 -> 46143 | U5: =+'1'!A38 | V5: =+'1'!B38 -> 0 | W5: =+'1'!C38 -> 0 | X5: =+'1'!D38 -> 0 | Y5: =+'1'!E38 -> 0 | AA5: =+'1'!D1 -> 46143 | AB5: =+'1'!D59 -> 0 | AC5: =+'1'!E59 -> 0
B6: MENSUALIDAD PARQUEADERO | C6: =SUMIF(I:I,B6,K:K)+SUMIF(P:P,B6,R:R)+SUMIF(W:W,B6,Y:Y) -> 0 | D6: =IF(ISERROR(C6/TOTAL!$C$3),"0%",C6/TOTAL!$C$3) -> 0% | F6: =+'1'!D1 -> 46143 | G6: =+'1'!A6 | H6: =+'1'!B6 -> 0 | I6: =+'1'!C6 -> 0 | J6: =+'1'!D6 -> 0 | K6: =+'1'!E6 -> 0 | M6: =+'1'!D1 -> 46143 | N6: =+'1'!A26 | O6: =+'1'!B26 -> 0 | P6: =+'1'!C26 -> 0 | Q6: =+'1'!D26 -> 0 | R6: =+'1'!E26 -> 0 | T6: =+'1'!D1 -> 46143 | U6: =+'1'!A39 | V6: =+'1'!B39 -> 0 | W6: =+'1'!C39 -> 0 | X6: =+'1'!D39 -> 0 | Y6: =+'1'!E39 -> 0 | AA6: =+'2'!D1 -> 46144 | AB6: =+'2'!D57 -> 0 | AC6: =+'2'!E57 -> 0
